Workbook

Sheet ReadMe
A1: Chitrakala Inventory Sync Template - Updated to Match Actual DB Exports
A2: Paste refreshed DB export CSVs into the matching DB_* tabs starting at A1 including headers. The Inventory_Master, Potential_Issues_Auto, and Sync_Summary tabs update from formulas.
A4: DB_Artworks_Export exact columns | B4: id, title, category_slug, category_name, description, materials, price_inr, price_usd, fx_rate_used, multiplier_used, featured, image, created_at, updated_at
A5: DB_Artwork_Sizes_Export exact columns | B5: id, artwork_id, artwork_title, size_label, price, price_usd, created_at
A6: DB_Categories_Export exact columns | B6: id, name, description, image, display_order
A7: Do not edit DB tabs | B7: These tabs are raw exports. Replace/paste exports only, keeping the same column order.
A8: Inventory_Master | B8: DB columns are auto-populated from DB_Artworks_Export in the exact exported order. Do not type over DB columns. Use Corrected_* columns for proposed changes.
A9: Manual columns | B9: Sync Action, Inventory SKU, Corrected_* fields, Inventory Notes, Intern Review Notes.
A10: Formula columns | B10: Formula columns include Suggested Sync Action, Validation Status, DB current fields, Category Validation, Size Variant Count, First Size Label/Price fields, Size Review Flag, and Final_* fields.
A11: Potential_Issues_Auto | B11: Automatically flags invalid category, missing price, missing image, and size variant review rows.
A12: Reconciliation_Report | B12: Manual issue log. Use Potential_Issues_Auto to identify what to log.
A13: Import_Validation_Rules | B13: Updated for actual export columns. Add rules only if a new business rule is discovered.

Sheet Sync_Summary
A1: Chitrakala Inventory Sync Summary
A3: Metric | B3: Formula/Value | C3: Notes
A4: DB artworks count | B4: =MAX(COUNTA(DB_Artworks_Export!$A:$A)-1,0) -> 36 | C4: Rows in DB_Artworks_Export
A5: DB artwork size rows count | B5: =MAX(COUNTA(DB_Artwork_Sizes_Export!$A:$A)-1,0) -> 73 | C5: Rows in DB_Artwork_Sizes_Export
A6: DB categories count | B6: =MAX(COUNTA(DB_Categories_Export!$A:$A)-1,0) -> 5 | C6: Rows in DB_Categories_Export
A7: Inventory rows loaded | B7: =MAX(COUNTA(DB_Artworks_Export!$A:$A)-1,0) -> 36 | C7: Auto-populated from DB export
A8: Manual Sync Action - CREATE | B8: =COUNTIF(Inventory_Master!$A:$A,"CREATE") -> 0 | C8: Entered by intern
A9: Manual Sync Action - UPDATE | B9: =COUNTIF(Inventory_Master!$A:$A,"UPDATE") -> 9 | C9: Entered by intern
A10: Manual Sync Action - NO_CHANGE | B10: =COUNTIF(Inventory_Master!$A:$A,"NO_CHANGE") -> 27 | C10: Entered by intern
A11: Manual Sync Action - ARCHIVE | B11: =COUNTIF(Inventory_Master!$A:$A,"ARCHIVE") -> 0 | C11: Entered by intern
A12: Manual Sync Action - REVIEW | B12: =COUNTIF(Inventory_Master!$A:$A,"REVIEW") -> 0 | C12: Entered by intern
A13: Potential issue rows | B13: =COUNTIF(Potential_Issues_Auto!$G:$G,"YES") -> 33 | C13: Formula-driven issue helper
A14: Invalid category rows | B14: =COUNTIF(Inventory_Master!$R:$R,"INVALID CATEGORY") -> 0 | C14: Should be zero
A15: Size variant artworks | B15: =COUNTIF(Inventory_Master!$W:$W,"REVIEW_SIZE_PRICING") -> 33 | C15: Review size pricing
A16: Missing image rows | B16: =COUNTIF(Potential_Issues_Auto!$F:$F,"*Missing image*") -> 0 | C16: Review image path

Sheet ⚙️ Assumptions
B1: ⚙️ PRICING & COST ASSUMPTIONS
B2: All blue cells are inputs — update these as your costs change
B4: A. CURRENCY
B5: Parameter | C5: Value | D5: Notes
B6: INR to USD Exchange Rate | C6: 0.01059 | D6: Update weekly — e.g. 1 INR = 0.012 USD
B7: Buffer % for rate fluctuation | C7: 0.03 | D7: 3% buffer protects against rate moves
B9: B. SHIPPING & IMPORT COSTS
B10: Parameter | C10: Value | D10: Notes
B11: Base shipping cost per piece (USD) | C11: 45 | D11: Flat estimate; adjust by actual invoice
B12: Shipping cost per sq ft (USD) | C12: 8 | D12: For size-based calculation override
B13: US Customs duty rate (fine art) | C13: 0 | D13: Fine art (HTS 9701) is typically duty-free
B14: US Customs duty rate (decorative art) | C14: 0.065 | D14: Decorative art may attract ~6.5%
B15: Insurance rate (% of purchase price) | C15: 0.015 | D15: Typical transit insurance ~1.5%
B16: Customs brokerage flat fee (USD) | C16: 85 | D16: Per shipment; allocate across pieces
B17: Avg pieces per shipment | C17: 8 | D17: Used to allocate brokerage per piece
B18: Local delivery / handling (USD) | C18: 25 | D18: Last-mile to your storage/location
B20: C. OVERHEAD ALLOCATION
B21: Parameter | C21: Value | D21: Notes
B22: Monthly website / platform cost (USD) | C22: 49 | D22: Hosting, domain, e-commerce platform
B23: Monthly marketing spend (USD) | C23: 100 | D23: Social media ads, photography, etc.
B24: Monthly misc overhead (USD) | C24: 50 | D24: Packaging materials, admin costs
B25: Avg active inventory pieces | C25: 20 | D25: Used to allocate overhead per piece
B26: → Monthly Overhead Total | C26: =C22+C23+C24 -> 199 | D26: Auto-calculated from above
B27: → Overhead per Piece (USD) | C27: =C26/C25 -> 9.95 | D27: Allocated to each piece in inventory
B29: D. PRICING TIER MARKUPS
B30: Tier | C30: Markup on Landed Cost | D30: Applies When…
B31: Tier 1 — Standard | C31: 2.2 | D31: Unknown/emerging artist, common style
B32: Tier 2 — Mid-range | C32: 2.8 | D32: Recognized regional artist, quality medium
B33: Tier 3 — Premium | C33: 3.5 | D33: Established artist, rare style, large format
B34: Tier 4 — Collector | C34: 4.5 | D34: Signature/numbered work, high provenance
B35: Minimum margin floor | C35: 0.35 | D35: Never price below 35% gross margin
B37: COLOR KEY
B38: Blue text | C38: ■ ■ ■ | D38: Hardcoded input — you edit these
B39: Black text | C39: ■ ■ ■ | D39: Formula — auto-calculated, do not edit
B40: Green text | C40: ■ ■ ■ | D40: Cross-sheet link — pulls from another tab

Sheet DB_Artworks_Export
A1: id | B1: title | C1: category_slug | D1: category_name | E1: description | F1: materials | G1: price_inr | H1: price_usd | I1: fx_rate_used | J1: multiplier_used | K1: featured | L1: image | M1: created_at | N1: updated_at
A2: art-1770419263598 | B2: Eternal Glow – Mandala of Light and Balance | C2: dot-mandala | D2: Dot Mandala Art | E2: A striking hand-painted dot mandala artwork bursting with warmth and movement. Set against a deep black background, layers of flowing petal-like forms in rich shades of orange, amber, gold, and green radiate outward from a detailed center, creating a sense of balance and positive energy. Every dot and stroke is carefully placed by hand, making this piece truly one of a kind. Perfect as a statement wall décor or tabletop display, this mandala brings vibrancy and artistic depth to living rooms, meditation spaces, offices, or creative corners. An eye-catching handmade gift for housewarmings, festivals, weddings, or for anyone who appreciates meaningful, soulful art. | F2: Wood | G2: 4000.00 | H2: 76.00 | I2: 92.4000 | J2: 1.7500 | K2: f | L2: https://chitrakalaarts-production.up.railway.app/api/images/artworks/art-1770419263598 | M2: 2026-02-10 17:54:35.568324 | N2: 2026-03-17 03:31:03.482303
A3: art-1770419392051 | B3: Blush Serenity Mandala – Art in Soft Pink & White | C3: dot-mandala | D3: Dot Mandala Art | E3: A delicate hand-painted dot mandala artwork created in soothing blush pink and white tones. Intricate layers of flowing patterns and finely placed dots form a harmonious circular design that radiates calm, balance, and elegance. Each detail is painted by hand, making this artwork a truly one-of-a-kind piece. Perfect for adding a soft, peaceful touch to living rooms, bedrooms, meditation corners, or creative spaces, this mandala also makes a thoughtful handmade gift for housewarmings, weddings, anniversaries, or festive occasions. Its gentle color palette blends beautifully with modern, boho, and minimalist interiors. | F3: Wood | G3: 4000.00 | H3: 76.00 | I3: 92.4000 | J3: 1.7500 | K3: f | L3: https://chitrakalaarts-production.up.railway.app/api/images/artworks/art-1770419392051 | M3: 2026-02-10 17:54:35.568324 | N3: 2026-03-17 03:31:03.510591
A4: art-1770419460850 | B4: Mandala in Blue and Peach | C4: dot-mandala | D4: Dot Mandala Art | E4: A captivating hand-painted round dot mandala artwork created in serene shades of blue and soft peach. Layers of intricate dot work and flowing floral patterns come together in perfect harmony, evoking a sense of calm, warmth, and balance. The soothing blue tones bring tranquility, while the peach accents add a gentle glow, making this piece both peaceful and uplifting. Each mandala is carefully painted by hand, ensuring every artwork is unique. Perfect as a statement wall décor, shelf display, or meditation centerpiece, this mandala adds refined beauty to living rooms, bedrooms, yoga spaces, or creative corners. It also makes a thoughtful handmade gift for housewarmings, weddings, festivals, or special occasions. 18" - Rs 6200 24" Rs 8000 36" Rs 16000 | F4: Wood | G4: 4000.00 | H4: 76.00 | I4: 92.4000 | J4: 1.7500 | K4: f | L4: https://chitrakalaarts-production.up.railway.app/api/images/artworks/art-1770419460850 | M4: 2026-02-10 17:54:35.568324 | N4: 2026-03-17 03:31:03.532958
A5: art-1770771760544 | B5: Hand-Painted Keychains (set of 5) | C5: dot-mandala | D5: Dot Mandala Art | E5: Brighten someone’s day with these hand-painted dot mandala wooden keychains, full of color and joyful detail. A thoughtful and affordable gift for festivals, return gifts, party favors, or stocking stuffers—each piece handmade to spread happiness and charm. | F5: Wood | G5: 450.00 | H5: 9.00 | I5: 92.4000 | J5: 1.7500 | K5: f | L5: https://chitrakalaarts-production.up.railway.app/api/images/artworks/art-1770771760544 | M5: 2026-02-11 01:02:40.581985 | N5: 2026-03-17 03:31:03.473272
A6: art-1770771970545 | B6: Mango-Shaped storage box | C6: dot-mandala | D6: Dot Mandala Art | E6: Unique hand-painted mango-shaped wooden storage box decorated with detailed dot mandala artwork. Ideal for storing jewelry, trinkets, or small keepsakes while bringing a playful yet traditional artistic touch to your décor. | F6: Wood | G6: 450.00 | H6: 9.00 | I6: 92.4000 | J6: 1.7500 | K6: f | L6: https://chitrakalaarts-production.up.railway.app/api/images/artworks/art-1770771970545 | M6: 2026-02-11 01:06:10.580553 | N6: 2026-03-17 03:31:03.469417
A7: art-1770775579766 | B7: Intricate Floral Mandala Art in Green & Gold | C7: dot-mandala | D7: Dot Mandala Art | E7: An exquisite hand-painted dot mandala artwork, created with intricate layers of delicate dots and flowing floral patterns. Painted in soothing green and warm gold tones, this mandala radiates harmony, balance, and timeless beauty. Every detail is carefully handcrafted, making each piece truly one of a kind. Perfect as a statement wall décor, shelf accent, or meditation centerpiece, this mandala art brings a sense of calm and elegance to living rooms, entryways, yoga spaces, or gifting occasions. A meaningful handmade gift for art lovers, housewarmings, weddings, or festive celebrations. | F7: wood | G7: 4000.00 | H7: 76.00 | I7: 92.4000 | J7: 1.7500 | K7: t | L7: https://chitrakalaarts-production.up.railway.app/api/images/artworks/art-1770775579766 | M7: 2026-02-11 02:06:19.802205 | N7: 2026-03-17 03:31:03.464546
A8: art-1770777152872 | B8: Sacred Geometry in Clay & Mirror | C8: lippan-art | D8: Lippan Art | E8: A stunning Lippan art panel handcrafted with clay motifs and delicate mirror inlays, radiating harmony through its geometric symmetry. Framed by vibrant earthy tones, it brings a serene glow to any space. | F8: Wood | G8: 8000.00 | H8: 152.00 | I8: 92.4000 | J8: 1.7500 | K8: f | L8: https://chitrakalaarts-production.up.railway.app/api/images/artworks/art-1770777152872 | M8: 2026-02-11 02:32:32.911059 | N8: 2026-04-28 17:54:38.817767
A9: art-1770778179564 | B9: Colorful Mandala KeyChain Holder | C9: dot-mandala | D9: Dot Mandala Art | E9: Handcrafted wooden key holder adorned with a vibrant dot mandala design in calming shades of purple and teal. Finished with sturdy hooks, it’s perfect for organizing keys while adding a touch of artistic elegance to your home décor. A beautiful blend of functionality and mindful art—ideal for entryways or as a thoughtful handmade gift. | F9: Wood | G9: 1000.00 | H9: 19.00 | I9: 92.4000 | J9: 1.7500 | K9: f | L9: https://chitrakalaarts-production.up.railway.app/api/images/artworks/art-1770778179564 | M9: 2026-02-11 02:49:39.60251 | N9: 2026-03-17 03:31:03.453632
A10: art-1770778384172 | B10: Butterfly Set (3 pieces) | C10: dot-mandala | D10: Dot Mandala Art | E10: A graceful butterfly brought to life through intricate dot mandala artistry, this hand-painted piece symbolizes transformation, joy, and renewal. Rendered in warm shades of gold, green, and soft orange, each delicate dot adds depth, movement, and a gentle sense of harmony. Perfect as a mindful décor piece, this artwork radiates elegance and positive energy—an exquisite reminder of beauty in transformation. Available in set of 3 - 8*, 6", 4" | F10: Wood | G10: 1500.00 | H10: 28.00 | I10: 92.4000 | J10: 1.7500 | K10: f | L10: https://chitrakalaarts-production.up.railway.app/api/images/artworks/art-1770778384172 | M10: 2026-02-11 02:53:04.203783 | N10: 2026-03-17 03:31:03.447787
A11: art-1770778509370 | B11: Coaster Set (4 pieces) | C11: dot-mandala | D11: Dot Mandala Art | E11: Add a touch of handcrafted elegance to your everyday moments with this hand-painted dot mandala coaster set. Each coaster is meticulously adorned with intricate dot patterns, radiating symmetry, balance, and calming energy. The rich colors and delicate detailing create a harmonious blend of art and function, protecting your surfaces while elevating your décor. Perfect for tea tables, coffee corners, or thoughtful gifting, this coaster set brings mindful beauty and artisanal charm into every sip. Set of 4 - Rs 750 Set of 6 - Rs 1000 | F11: Wood | G11: 800.00 | H11: 15.00 | I11: 92.4000 | J11: 1.7500 | K11: f | L11: https://chitrakalaarts-production.up.railway.app/api/images/artworks/art-1770778509370 | M11: 2026-02-11 02:55:09.407983 | N11: 2026-03-17 03:31:03.442637
A12: art-1770778808201 | B12: Serene Teal Floral Mandala Box | C12: dot-mandala | D12: Dot Mandala Art | E12: Hand-painted dot mandala box in soothing teal and turquoise tones, adorned with intricate floral patterns. A perfect accent piece for storing jewelry, keys, or small keepsakes—bringing calm, color, and handmade charm to any space | F12: Wood | G12: 1000.00 | H12: 19.00 | I12: 92.4000 | J12: 1.7500 | K12: f | L12: https://chitrakalaarts-production.up.railway.app/api/images/artworks/art-1770778808201 | M12: 2026-02-11 03:00:08.235036 | N12: 2026-03-17 03:31:03.439328
... A37: art-1778384550442 | B37: Moonlit Lotus – White Mirror Mosaic Art Work | C37: mirror-mosaic | D37: Mirror Mosaic | E37: Delicate, luminous, and intricately detailed, this white mirror mosaic artwork draws inspiration from blooming lotus patterns and traditional mandala artistry. The soft textured white finish combined with shimmering mirror inlays creates a serene yet luxurious presence, reflecting light beautifully from every angle. Handcrafted with precision, this elegant piece symbolizes harmony, purity, and balance, making it a perfect addition to contemporary, minimal, or spiritual interiors. Its timeless design brings calm sophistication and artistic depth to any wall or décor setting. | F37: Glass Mirrors Cuttings | G37: 13500.00 | H37: 256.00 | I37: 92.4000 | J37: 1.7500 | K37: f | L37: https://chitrakalaarts-production.up.railway.app/api/images/artworks/art-1778384550442 | M37: 2026-05-10 03:42:30.476539 | N37: 2026-05-10 03:42:30.676559

Sheet DB_Artwork_Sizes_Export
A1: id | B1: artwork_id | C1: artwork_title | D1: size_label | E1: price | F1: price_usd | G1: created_at
A2: 608 | B2: art-1770419263598 | C2: Eternal Glow – Mandala of Light and Balance | D2: 12" x 12" | E2: 4500.00 | F2: 76.00 | G2: 2026-03-17 03:31:03.509704
A3: 609 | B3: art-1770419263598 | C3: Eternal Glow – Mandala of Light and Balance | D3: 18" x 18" | E3: 7500.00 | F3: 76.00 | G3: 2026-03-17 03:31:03.509704
A4: 610 | B4: art-1770419263598 | C4: Eternal Glow – Mandala of Light and Balance | D4: 24" x 24" | E4: 10000.00 | F4: 76.00 | G4: 2026-03-17 03:31:03.509704
A5: 611 | B5: art-1770419263598 | C5: Eternal Glow – Mandala of Light and Balance | D5: 36" x 36" | E5: 20000.00 | F5: 76.00 | G5: 2026-03-17 03:31:03.509704
A6: 612 | B6: art-1770419460850 | C6: Mandala in Blue and Peach | D6: 12" | E6: 3500.00 | F6: 76.00 | G6: 2026-03-17 03:31:03.539472
A7: 607 | B7: art-1770771760544 | C7: Hand-Painted Keychains (set of 5) | D7: custom | E7: 450.00 | F7: 9.00 | G7: 2026-03-17 03:31:03.4795
A8: 606 | B8: art-1770771970545 | C8: Mango-Shaped storage box | D8: 4" X 2" | E8: 450.00 | F8: 9.00 | G8: 2026-03-17 03:31:03.472348
A9: 602 | B9: art-1770775579766 | C9: Intricate Floral Mandala Art in Green & Gold | D9: 12" round | E9: 4000.00 | F9: 76.00 | G9: 2026-03-17 03:31:03.468752
A10: 603 | B10: art-1770775579766 | C10: Intricate Floral Mandala Art in Green & Gold | D10: 18" round | E10: 6900.00 | F10: 76.00 | G10: 2026-03-17 03:31:03.468752
A11: 604 | B11: art-1770775579766 | C11: Intricate Floral Mandala Art in Green & Gold | D11: 24" round | E11: 9000.00 | F11: 76.00 | G11: 2026-03-17 03:31:03.468752
A12: 605 | B12: art-1770775579766 | C12: Intricate Floral Mandala Art in Green & Gold | D12: 36" round | E12: 18000.00 | F12: 76.00 | G12: 2026-03-17 03:31:03.468752
... A74: 644 | B74: art-1778384550442 | C74: Moonlit Lotus – White Mirror Mosaic Art Work | D74: 12"x12" | E74: 13500.00 | F74: 256.00 | G74: 2026-05-10 03:42:30.477433

Sheet DB_Categories_Export
A1: id | B1: name | C1: description | D1: image | E1: display_order
A2: dot-mandala | B2: Dot Mandala Art | C2: Intricate dot patterns creating beautiful mandala designs, combining precision and creativity. | D2: /assets/images/categories/dot-mandala.png | E2: 1
A3: lippan-art | B3: Lippan Art | C3: Traditional mirror and clay work art from Gujarat, featuring stunning geometric patterns. | D3: /assets/images/categories/lippan-art.png | E3: 2
A4: mirror-mosaic | B4: Mirror Mosaic | C4: Carefully arranged mirrored elements that catch and scatter light, adding depth, texture, and a subtle shimmer to any space. | D4: /assets/images/categories/mirror-mosaic.png | E4: 3
A5: textile-design | B5: Textile Art | C5: Hand-painted and designed textile pieces that blend tradition with contemporary aesthetics. | D5: /assets/images/categories/textile-design.png | E5: 5
A6: texture-art | B6: Texture Art | C6: Handcrafted pieces where dimension meets design, with layered details, soft depth, and tactile finishes that bring walls to life. | D6: /assets/images/categories/texture-art.png | E6: 4

Sheet Inventory_Master
A1: Sync Action | B1: Suggested Sync Action | C1: Validation Status | D1: DB id | E1: DB title | F1: DB category_slug | G1: DB category_name | H1: DB description | I1: DB materials | J1: DB price_inr | K1: DB price_usd | L1: DB fx_rate_used | M1: DB multiplier_used | N1: DB featured | O1: DB image | P1: DB created_at | Q1: DB updated_at | R1: Category Validation | S1: Size Variant Count | T1: First Size Label | U1: First Size Price INR | V1: First Size Price USD | W1: Size Review Flag | X1: Inventory SKU | Y1: Corrected title | Z1: Corrected category_slug | AA1: Corrected description | AB1: Corrected materials | AC1: Corrected price_inr | AD1: Corrected featured | AE1: Corrected image | AF1: Final title | AG1: Final category_slug | AH1: Final category_name | AI1: Final description | AJ1: Final materials | AK1: Final price_inr | AL1: Final featured | AM1: Final image | AN1: Inventory Notes | AO1: Intern Review Notes
A2: NO_CHANGE | B2: =IF($D2="","",IF(COUNTA($Y2:$AE2)>0,"UPDATE","NO_CHANGE")) -> NO_CHANGE | C2: =IF($D2="","",IF($R2<>"OK","ERROR",IF(OR($E2="", $F2="", $J2=""),"ERROR",IF($W2<>"OK","WARNING","PASS")))) -> WARNING | D2: =IF(DB_Artworks_Export!A2="","",DB_Artworks_Export!A2) -> art-1770419263598 | E2: =IF(DB_Artworks_Export!B2="","",DB_Artworks_Export!B2) -> Eternal Glow – Mandala of Light and Balance | F2: =IF(DB_Artworks_Export!C2="","",DB_Artworks_Export!C2) -> dot-mandala | G2: =IF(DB_Artworks_Export!D2="","",DB_Artworks_Export!D2) -> Dot Mandala Art | H2: =IF(DB_Artworks_Export!E2="","",DB_Artworks_Export!E2) -> A striking hand-painted dot mandala artwork bursting with warmth and movement. Set against a deep black background, layers of flowing petal-like forms in rich shades of orange, amber, gold, and green radiate outward from a detailed center, creating a sense of balance and positive energy. Every dot and stroke is carefully placed by hand, making this piece truly one of a kind. Perfect as a statement wall décor or tabletop display, this mandala brings vibrancy and artistic depth to living rooms, meditation spaces, offices, or creative corners. An eye-catching handmade gift for housewarmings, festivals, weddings, or for anyone who appreciates meaningful, soulful art. | I2: =IF(DB_Artworks_Export!F2="","",DB_Artworks_Export!F2) -> Wood | J2: =IF(DB_Artworks_Export!G2="","",DB_Artworks_Export!G2) -> 4000.00 | K2: =IF(DB_Artworks_Export!H2="","",DB_Artworks_Export!H2) -> 76.00 | ... Q2: =IF(DB_Artworks_Export!N2="","",DB_Artworks_Export!N2) -> 2026-03-17 03:31:03.482303 | R2: =IF($D2="","",IF(COUNTIF(DB_Categories_Export!$A:$A,$F2)>0,"OK","INVALID CATEGORY")) -> OK | S2: =IF($D2="","",COUNTIF(DB_Artwork_Sizes_Export!$B:$B,$D2)) -> 4 | T2: =IF($D2="","",IFERROR(INDEX(DB_Artwork_Sizes_Export!$D:$D,MATCH($D2,DB_Artwork_Sizes_Export!$B:$B,0)),"")) -> 12" x 12" | U2: =IF($D2="","",IFERROR(INDEX(DB_Artwork_Sizes_Export!$E:$E,MATCH($D2,DB_Artwork_Sizes_Export!$B:$B,0)),"")) -> 4500.00 | V2: =IF($D2="","",IFERROR(INDEX(DB_Artwork_Sizes_Export!$F:$F,MATCH($D2,DB_Artwork_Sizes_Export!$B:$B,0)),"")) -> 76.00 | W2: =IF($D2="","",IF($S2>0,"REVIEW_SIZE_PRICING","OK")) -> REVIEW_SIZE_PRICING | AF2: =IF($Y2<>"",$Y2,$E2) -> Eternal Glow – Mandala of Light and Balance | AG2: =IF($Z2<>"",$Z2,$F2) -> dot-mandala | AH2: =IF($AG2="","",IFERROR(VLOOKUP($AG2,DB_Categories_Export!$A:$B,2,FALSE()),"INVALID CATEGORY")) -> Dot Mandala Art | AI2: =IF($AA2<>"",$AA2,$H2) -> A striking hand-painted dot mandala artwork bursting with warmth and movement. Set against a deep black background, layers of flowing petal-like forms in rich shades of orange, amber, gold, and green radiate outward from a detailed center, creating a sense of balance and positive energy. Every dot and stroke is carefully placed by hand, making this piece truly one of a kind. Perfect as a statement wall décor or tabletop display, this mandala brings vibrancy and artistic depth to living rooms, meditation spaces, offices, or creative corners. An eye-catching handmade gift for housewarmings, festivals, weddings, or for anyone who appreciates meaningful, soulful art. | AJ2: =IF($AB2<>"",$AB2,$I2) -> Wood | AK2: =IF($AC2<>"",$AC2,$J2) -> 4000.00 | AL2: =IF($AD2<>"",$AD2,$N2) -> f | AM2: =IF($AE2<>"",$AE2,$O2) -> https://chitrakalaarts-production.up.railway.app/api/images/artworks/art-1770419263598 | AO2: INV-03-01 reviewed: final action NO_CHANGE for artwork-level fields. Suggested Sync Action was NO_CHANGE and current artwork fields/category validate. REVIEW was driven by size-level pricing review flag; defer size-level USD/variant pricing to pricing subtask. No Corrected_* fields needed.
A3: NO_CHANGE | B3: =IF($D3="","",IF(COUNTA($Y3:$AE3)>0,"UPDATE","NO_CHANGE")) -> NO_CHANGE | C3: =IF($D3="","",IF($R3<>"OK","ERROR",IF(OR($E3="", $F3="", $J3=""),"ERROR",IF($W3<>"OK","WARNING","PASS")))) -> PASS | D3: =IF(DB_Artworks_Export!A3="","",DB_Artworks_Export!A3) -> art-1770419392051 | E3: =IF(DB_Artworks_Export!B3="","",DB_Artworks_Export!B3) -> Blush Serenity Mandala – Art in Soft Pink & White | F3: =IF(DB_Artworks_Export!C3="","",DB_Artworks_Export!C3) -> dot-mandala | G3: =IF(DB_Artworks_Export!D3="","",DB_Artworks_Export!D3) -> Dot Mandala Art | H3: =IF(DB_Artworks_Export!E3="","",DB_Artworks_Export!E3) -> A delicate hand-painted dot mandala artwork created in soothing blush pink and white tones. Intricate layers of flowing patterns and finely placed dots form a harmonious circular design that radiates calm, balance, and elegance. Each detail is painted by hand, making this artwork a truly one-of-a-kind piece. Perfect for adding a soft, peaceful touch to living rooms, bedrooms, meditation corners, or creative spaces, this mandala also makes a thoughtful handmade gift for housewarmings, weddings, anniversaries, or festive occasions. Its gentle color palette blends beautifully with modern, boho, and minimalist interiors. | I3: =IF(DB_Artworks_Export!F3="","",DB_Artworks_Export!F3) -> Wood | J3: =IF(DB_Artworks_Export!G3="","",DB_Artworks_Export!G3) -> 4000.00 | K3: =IF(DB_Artworks_Export!H3="","",DB_Artworks_Export!H3) -> 76.00 | ... Q3: =IF(DB_Artworks_Export!N3="","",DB_Artworks_Export!N3) -> 2026-03-17 03:31:03.510591 | R3: =IF($D3="","",IF(COUNTIF(DB_Categories_Export!$A:$A,$F3)>0,"OK","INVALID CATEGORY")) -> OK | S3: =IF($D3="","",COUNTIF(DB_Artwork_Sizes_Export!$B:$B,$D3)) -> 0 | T3: =IF($D3="","",IFERROR(INDEX(DB_Artwork_Sizes_Export!$D:$D,MATCH($D3,DB_Artwork_Sizes_Export!$B:$B,0)),"")) | U3: =IF($D3="","",IFERROR(INDEX(DB_Artwork_Sizes_Export!$E:$E,MATCH($D3,DB_Artwork_Sizes_Export!$B:$B,0)),"")) | V3: =IF($D3="","",IFERROR(INDEX(DB_Artwork_Sizes_Export!$F:$F,MATCH($D3,DB_Artwork_Sizes_Export!$B:$B,0)),"")) | W3: =IF($D3="","",IF($S3>0,"REVIEW_SIZE_PRICING","OK")) -> OK | AF3: =IF($Y3<>"",$Y3,$E3) -> Blush Serenity Mandala – Art in Soft Pink & White | AG3: =IF($Z3<>"",$Z3,$F3) -> dot-mandala | AH3: =IF($AG3="","",IFERROR(VLOOKUP($AG3,DB_Categories_Export!$A:$B,2,FALSE()),"INVALID CATEGORY")) -> Dot Mandala Art | AI3: =IF($AA3<>"",$AA3,$H3) -> A delicate hand-painted dot mandala artwork created in soothing blush pink and white tones. Intricate layers of flowing patterns and finely placed dots form a harmonious circular design that radiates calm, balance, and elegance. Each detail is painted by hand, making this artwork a truly one-of-a-kind piece. Perfect for adding a soft, peaceful touch to living rooms, bedrooms, meditation corners, or creative spaces, this mandala also makes a thoughtful handmade gift for housewarmings, weddings, anniversaries, or festive occasions. Its gentle color palette blends beautifully with modern, boho, and minimalist interiors. | AJ3: =IF($AB3<>"",$AB3,$I3) -> Wood | AK3: =IF($AC3<>"",$AC3,$J3) -> 4000.00 | AL3: =IF($AD3<>"",$AD3,$N3) -> f | AM3: =IF($AE3<>"",$AE3,$O3) -> https://chitrakalaarts-production.up.railway.app/api/images/artworks/art-1770419392051
A4: UPDATE | B4: =IF($D4="","",IF(COUNTA($Y4:$AE4)>0,"UPDATE","NO_CHANGE")) -> UPDATE | C4: =IF($D4="","",IF($R4<>"OK","ERROR",IF(OR($E4="", $F4="", $J4=""),"ERROR",IF($W4<>"OK","WARNING","PASS")))) -> WARNING | D4: =IF(DB_Artworks_Export!A4="","",DB_Artworks_Export!A4) -> art-1770419460850 | E4: =IF(DB_Artworks_Export!B4="","",DB_Artworks_Export!B4) -> Mandala in Blue and Peach | F4: =IF(DB_Artworks_Export!C4="","",DB_Artworks_Export!C4) -> dot-mandala | G4: =IF(DB_Artworks_Export!D4="","",DB_Artworks_Export!D4) -> Dot Mandala Art | H4: =IF(DB_Artworks_Export!E4="","",DB_Artworks_Export!E4) -> A captivating hand-painted round dot mandala artwork created in serene shades of blue and soft peach. Layers of intricate dot work and flowing floral patterns come together in perfect harmony, evoking a sense of calm, warmth, and balance. The soothing blue tones bring tranquility, while the peach accents add a gentle glow, making this piece both peaceful and uplifting. Each mandala is carefully painted by hand, ensuring every artwork is unique. Perfect as a statement wall décor, shelf display, or meditation centerpiece, this mandala adds refined beauty to living rooms, bedrooms, yoga spaces, or creative corners. It also makes a thoughtful handmade gift for housewarmings, weddings, festivals, or special occasions. 18" - Rs 6200 24" Rs 8000 36" Rs 16000 | I4: =IF(DB_Artworks_Export!F4="","",DB_Artworks_Export!F4) -> Wood | J4: =IF(DB_Artworks_Export!G4="","",DB_Artworks_Export!G4) -> 4000.00 | K4: =IF(DB_Artworks_Export!H4="","",DB_Artworks_Export!H4) -> 76.00 | ... Q4: =IF(DB_Artworks_Export!N4="","",DB_Artworks_Export!N4) -> 2026-03-17 03:31:03.532958 | R4: =IF($D4="","",IF(COUNTIF(DB_Categories_Export!$A:$A,$F4)>0,"OK","INVALID CATEGORY")) -> OK | S4: =IF($D4="","",COUNTIF(DB_Artwork_Sizes_Export!$B:$B,$D4)) -> 1 | T4: =IF($D4="","",IFERROR(INDEX(DB_Artwork_Sizes_Export!$D:$D,MATCH($D4,DB_Artwork_Sizes_Export!$B:$B,0)),"")) -> 12" | U4: =IF($D4="","",IFERROR(INDEX(DB_Artwork_Sizes_Export!$E:$E,MATCH($D4,DB_Artwork_Sizes_Export!$B:$B,0)),"")) -> 3500.00 | V4: =IF($D4="","",IFERROR(INDEX(DB_Artwork_Sizes_Export!$F:$F,MATCH($D4,DB_Artwork_Sizes_Export!$B:$B,0)),"")) -> 76.00 | W4: =IF($D4="","",IF($S4>0,"REVIEW_SIZE_PRICING","OK")) -> REVIEW_SIZE_PRICING | AA4: A captivating hand-painted round dot mandala artwork created in serene shades of blue and soft peach. Layers of intricate dot work and flowing floral patterns come together in perfect harmony, evoking a sense of calm, warmth, and balance. The soothing blue tones bring tranquility, while the peach accents add a gentle glow, making this piece both peaceful and uplifting. Each mandala is carefully painted by hand, ensuring every artwork is unique. Perfect as a statement wall décor, shelf display, or meditation centerpiece, this mandala adds refined beauty to living rooms, bedrooms, yoga spaces, or creative corners. It also makes a thoughtful handmade gift for housewarmings, weddings, festivals, or special occasions. | AF4: =IF($Y4<>"",$Y4,$E4) -> Mandala in Blue and Peach | AG4: =IF($Z4<>"",$Z4,$F4) -> dot-mandala | AH4: =IF($AG4="","",IFERROR(VLOOKUP($AG4,DB_Categories_Export!$A:$B,2,FALSE()),"INVALID CATEGORY")) -> Dot Mandala Art | AI4: =IF($AA4<>"",$AA4,$H4) -> A captivating hand-painted round dot mandala artwork created in serene shades of blue and soft peach. Layers of intricate dot work and flowing floral patterns come together in perfect harmony, evoking a sense of calm, warmth, and balance. The soothing blue tones bring tranquility, while the peach accents add a gentle glow, making this piece both peaceful and uplifting. Each mandala is carefully painted by hand, ensuring every artwork is unique. Perfect as a statement wall décor, shelf display, or meditation centerpiece, this mandala adds refined beauty to living rooms, bedrooms, yoga spaces, or creative corners. It also makes a thoughtful handmade gift for housewarmings, weddings, festivals, or special occasions. | AJ4: =IF($AB4<>"",$AB4,$I4) -> Wood | AK4: =IF($AC4<>"",$AC4,$J4) -> 4000.00 | AL4: =IF($AD4<>"",$AD4,$N4) -> f | AM4: =IF($AE4<>"",$AE4,$O4) -> https://chitrakalaarts-production.up.railway.app/api/images/artworks/art-1770419460850
A5: NO_CHANGE | B5: =IF($D5="","",IF(COUNTA($Y5:$AE5)>0,"UPDATE","NO_CHANGE")) -> NO_CHANGE | C5: =IF($D5="","",IF($R5<>"OK","ERROR",IF(OR($E5="", $F5="", $J5=""),"ERROR",IF($W5<>"OK","WARNING","PASS")))) -> WARNING | D5: =IF(DB_Artworks_Export!A5="","",DB_Artworks_Export!A5) -> art-1770771760544 | E5: =IF(DB_Artworks_Export!B5="","",DB_Artworks_Export!B5) -> Hand-Painted Keychains (set of 5) | F5: =IF(DB_Artworks_Export!C5="","",DB_Artworks_Export!C5) -> dot-mandala | G5: =IF(DB_Artworks_Export!D5="","",DB_Artworks_Export!D5) -> Dot Mandala Art | H5: =IF(DB_Artworks_Export!E5="","",DB_Artworks_Export!E5) -> Brighten someone’s day with these hand-painted dot mandala wooden keychains, full of color and joyful detail. A thoughtful and affordable gift for festivals, return gifts, party favors, or stocking stuffers—each piece handmade to spread happiness and charm. | I5: =IF(DB_Artworks_Export!F5="","",DB_Artworks_Export!F5) -> Wood | J5: =IF(DB_Artworks_Export!G5="","",DB_Artworks_Export!G5) -> 450.00 | K5: =IF(DB_Artworks_Export!H5="","",DB_Artworks_Export!H5) -> 9.00 | ... Q5: =IF(DB_Artworks_Export!N5="","",DB_Artworks_Export!N5) -> 2026-03-17 03:31:03.473272 | R5: =IF($D5="","",IF(COUNTIF(DB_Categories_Export!$A:$A,$F5)>0,"OK","INVALID CATEGORY")) -> OK | S5: =IF($D5="","",COUNTIF(DB_Artwork_Sizes_Export!$B:$B,$D5)) -> 1 | T5: =IF($D5="","",IFERROR(INDEX(DB_Artwork_Sizes_Export!$D:$D,MATCH($D5,DB_Artwork_Sizes_Export!$B:$B,0)),"")) -> custom | U5: =IF($D5="","",IFERROR(INDEX(DB_Artwork_Sizes_Export!$E:$E,MATCH($D5,DB_Artwork_Sizes_Export!$B:$B,0)),"")) -> 450.00 | V5: =IF($D5="","",IFERROR(INDEX(DB_Artwork_Sizes_Export!$F:$F,MATCH($D5,DB_Artwork_Sizes_Export!$B:$B,0)),"")) -> 9.00 | W5: =IF($D5="","",IF($S5>0,"REVIEW_SIZE_PRICING","OK")) -> REVIEW_SIZE_PRICING | AF5: =IF($Y5<>"",$Y5,$E5) -> Hand-Painted Keychains (set of 5) | AG5: =IF($Z5<>"",$Z5,$F5) -> dot-mandala | AH5: =IF($AG5="","",IFERROR(VLOOKUP($AG5,DB_Categories_Export!$A:$B,2,FALSE()),"INVALID CATEGORY")) -> Dot Mandala Art | AI5: =IF($AA5<>"",$AA5,$H5) -> Brighten someone’s day with these hand-painted dot mandala wooden keychains, full of color and joyful detail. A thoughtful and affordable gift for festivals, return gifts, party favors, or stocking stuffers—each piece handmade to spread happiness and charm. | AJ5: =IF($AB5<>"",$AB5,$I5) -> Wood | AK5: =IF($AC5<>"",$AC5,$J5) -> 450.00 | AL5: =IF($AD5<>"",$AD5,$N5) -> f | AM5: =IF($AE5<>"",$AE5,$O5) -> https://chitrakalaarts-production.up.railway.app/api/images/artworks/art-1770771760544 | AO5: INV-03-01 reviewed: final action NO_CHANGE for artwork-level fields. Suggested Sync Action was NO_CHANGE and current artwork fields/category validate. REVIEW was driven by size-level pricing review flag; defer size-level USD/variant pricing to pricing subtask. No Corrected_* fields needed.
A6: NO_CHANGE | B6: =IF($D6="","",IF(COUNTA($Y6:$AE6)>0,"UPDATE","NO_CHANGE")) -> NO_CHANGE | C6: =IF($D6="","",IF($R6<>"OK","ERROR",IF(OR($E6="", $F6="", $J6=""),"ERROR",IF($W6<>"OK","WARNING","PASS")))) -> WARNING | D6: =IF(DB_Artworks_Export!A6="","",DB_Artworks_Export!A6) -> art-1770771970545 | E6: =IF(DB_Artworks_Export!B6="","",DB_Artworks_Export!B6) -> Mango-Shaped storage box | F6: =IF(DB_Artworks_Export!C6="","",DB_Artworks_Export!C6) -> dot-mandala | G6: =IF(DB_Artworks_Export!D6="","",DB_Artworks_Export!D6) -> Dot Mandala Art | H6: =IF(DB_Artworks_Export!E6="","",DB_Artworks_Export!E6) -> Unique hand-painted mango-shaped wooden storage box decorated with detailed dot mandala artwork. Ideal for storing jewelry, trinkets, or small keepsakes while bringing a playful yet traditional artistic touch to your décor. | I6: =IF(DB_Artworks_Export!F6="","",DB_Artworks_Export!F6) -> Wood | J6: =IF(DB_Artworks_Export!G6="","",DB_Artworks_Export!G6) -> 450.00 | K6: =IF(DB_Artworks_Export!H6="","",DB_Artworks_Export!H6) -> 9.00 | ... Q6: =IF(DB_Artworks_Export!N6="","",DB_Artworks_Export!N6) -> 2026-03-17 03:31:03.469417 | R6: =IF($D6="","",IF(COUNTIF(DB_Categories_Export!$A:$A,$F6)>0,"OK","INVALID CATEGORY")) -> OK | S6: =IF($D6="","",COUNTIF(DB_Artwork_Sizes_Export!$B:$B,$D6)) -> 1 | T6: =IF($D6="","",IFERROR(INDEX(DB_Artwork_Sizes_Export!$D:$D,MATCH($D6,DB_Artwork_Sizes_Export!$B:$B,0)),"")) -> 4" X 2" | U6: =IF($D6="","",IFERROR(INDEX(DB_Artwork_Sizes_Export!$E:$E,MATCH($D6,DB_Artwork_Sizes_Export!$B:$B,0)),"")) -> 450.00 | V6: =IF($D6="","",IFERROR(INDEX(DB_Artwork_Sizes_Export!$F:$F,MATCH($D6,DB_Artwork_Sizes_Export!$B:$B,0)),"")) -> 9.00 | W6: =IF($D6="","",IF($S6>0,"REVIEW_SIZE_PRICING","OK")) -> REVIEW_SIZE_PRICING | AF6: =IF($Y6<>"",$Y6,$E6) -> Mango-Shaped storage box | AG6: =IF($Z6<>"",$Z6,$F6) -> dot-mandala | AH6: =IF($AG6="","",IFERROR(VLOOKUP($AG6,DB_Categories_Export!$A:$B,2,FALSE()),"INVALID CATEGORY")) -> Dot Mandala Art | AI6: =IF($AA6<>"",$AA6,$H6) -> Unique hand-painted mango-shaped wooden storage box decorated with detailed dot mandala artwork. Ideal for storing jewelry, trinkets, or small keepsakes while bringing a playful yet traditional artistic touch to your décor. | AJ6: =IF($AB6<>"",$AB6,$I6) -> Wood | AK6: =IF($AC6<>"",$AC6,$J6) -> 450.00 | AL6: =IF($AD6<>"",$AD6,$N6) -> f | AM6: =IF($AE6<>"",$AE6,$O6) -> https://chitrakalaarts-production.up.railway.app/api/images/artworks/art-1770771970545 | AO6: INV-03-01 reviewed: final action NO_CHANGE for artwork-level fields. Suggested Sync Action was NO_CHANGE and current artwork fields/category validate. REVIEW was driven by size-level pricing review flag; defer size-level USD/variant pricing to pricing subtask. No Corrected_* fields needed.
A7: UPDATE | B7: =IF($D7="","",IF(COUNTA($Y7:$AE7)>0,"UPDATE","NO_CHANGE")) -> UPDATE | C7: =IF($D7="","",IF($R7<>"OK","ERROR",IF(OR($E7="", $F7="", $J7=""),"ERROR",IF($W7<>"OK","WARNING","PASS")))) -> WARNING | D7: =IF(DB_Artworks_Export!A7="","",DB_Artworks_Export!A7) -> art-1770775579766 | E7: =IF(DB_Artworks_Export!B7="","",DB_Artworks_Export!B7) -> Intricate Floral Mandala Art in Green & Gold | F7: =IF(DB_Artworks_Export!C7="","",DB_Artworks_Export!C7) -> dot-mandala | G7: =IF(DB_Artworks_Export!D7="","",DB_Artworks_Export!D7) -> Dot Mandala Art | H7: =IF(DB_Artworks_Export!E7="","",DB_Artworks_Export!E7) -> An exquisite hand-painted dot mandala artwork, created with intricate layers of delicate dots and flowing floral patterns. Painted in soothing green and warm gold tones, this mandala radiates harmony, balance, and timeless beauty. Every detail is carefully handcrafted, making each piece truly one of a kind. Perfect as a statement wall décor, shelf accent, or meditation centerpiece, this mandala art brings a sense of calm and elegance to living rooms, entryways, yoga spaces, or gifting occasions. A meaningful handmade gift for art lovers, housewarmings, weddings, or festive celebrations. | I7: =IF(DB_Artworks_Export!F7="","",DB_Artworks_Export!F7) -> wood | J7: =IF(DB_Artworks_Export!G7="","",DB_Artworks_Export!G7) -> 4000.00 | K7: =IF(DB_Artworks_Export!H7="","",DB_Artworks_Export!H7) -> 76.00 | ... Q7: =IF(DB_Artworks_Export!N7="","",DB_Artworks_Export!N7) -> 2026-03-17 03:31:03.464546 | R7: =IF($D7="","",IF(COUNTIF(DB_Categories_Export!$A:$A,$F7)>0,"OK","INVALID CATEGORY")) -> OK | S7: =IF($D7="","",COUNTIF(DB_Artwork_Sizes_Export!$B:$B,$D7)) -> 4 | T7: =IF($D7="","",IFERROR(INDEX(DB_Artwork_Sizes_Export!$D:$D,MATCH($D7,DB_Artwork_Sizes_Export!$B:$B,0)),"")) -> 12" round | U7: =IF($D7="","",IFERROR(INDEX(DB_Artwork_Sizes_Export!$E:$E,MATCH($D7,DB_Artwork_Sizes_Export!$B:$B,0)),"")) -> 4000.00 | V7: =IF($D7="","",IFERROR(INDEX(DB_Artwork_Sizes_Export!$F:$F,MATCH($D7,DB_Artwork_Sizes_Export!$B:$B,0)),"")) -> 76.00 | W7: =IF($D7="","",IF($S7>0,"REVIEW_SIZE_PRICING","OK")) -> REVIEW_SIZE_PRICING | AB7: Wood | AF7: =IF($Y7<>"",$Y7,$E7) -> Intricate Floral Mandala Art in Green & Gold | AG7: =IF($Z7<>"",$Z7,$F7) -> dot-mandala | AH7: =IF($AG7="","",IFERROR(VLOOKUP($AG7,DB_Categories_Export!$A:$B,2,FALSE()),"INVALID CATEGORY")) -> Dot Mandala Art | AI7: =IF($AA7<>"",$AA7,$H7) -> An exquisite hand-painted dot mandala artwork, created with intricate layers of delicate dots and flowing floral patterns. Painted in soothing green and warm gold tones, this mandala radiates harmony, balance, and timeless beauty. Every detail is carefully handcrafted, making each piece truly one of a kind. Perfect as a statement wall décor, shelf accent, or meditation centerpiece, this mandala art brings a sense of calm and elegance to living rooms, entryways, yoga spaces, or gifting occasions. A meaningful handmade gift for art lovers, housewarmings, weddings, or festive celebrations. | AJ7: =IF($AB7<>"",$AB7,$I7) -> Wood | AK7: =IF($AC7<>"",$AC7,$J7) -> 4000.00 | AL7: =IF($AD7<>"",$AD7,$N7) -> t | AM7: =IF($AE7<>"",$AE7,$O7) -> https://chitrakalaarts-production.up.railway.app/api/images/artworks/art-1770775579766
A8: NO_CHANGE | B8: =IF($D8="","",IF(COUNTA($Y8:$AE8)>0,"UPDATE","NO_CHANGE")) -> NO_CHANGE | C8: =IF($D8="","",IF($R8<>"OK","ERROR",IF(OR($E8="", $F8="", $J8=""),"ERROR",IF($W8<>"OK","WARNING","PASS")))) -> WARNING | D8: =IF(DB_Artworks_Export!A8="","",DB_Artworks_Export!A8) -> art-1770777152872 | E8: =IF(DB_Artworks_Export!B8="","",DB_Artworks_Export!B8) -> Sacred Geometry in Clay & Mirror | F8: =IF(DB_Artworks_Export!C8="","",DB_Artworks_Export!C8) -> lippan-art | G8: =IF(DB_Artworks_Export!D8="","",DB_Artworks_Export!D8) -> Lippan Art | H8: =IF(DB_Artworks_Export!E8="","",DB_Artworks_Export!E8) -> A stunning Lippan art panel handcrafted with clay motifs and delicate mirror inlays, radiating harmony through its geometric symmetry. Framed by vibrant earthy tones, it brings a serene glow to any space. | I8: =IF(DB_Artworks_Export!F8="","",DB_Artworks_Export!F8) -> Wood | J8: =IF(DB_Artworks_Export!G8="","",DB_Artworks_Export!G8) -> 8000.00 | K8: =IF(DB_Artworks_Export!H8="","",DB_Artworks_Export!H8) -> 152.00 | ... Q8: =IF(DB_Artworks_Export!N8="","",DB_Artworks_Export!N8) -> 2026-04-28 17:54:38.817767 | R8: =IF($D8="","",IF(COUNTIF(DB_Categories_Export!$A:$A,$F8)>0,"OK","INVALID CATEGORY")) -> OK | S8: =IF($D8="","",COUNTIF(DB_Artwork_Sizes_Export!$B:$B,$D8)) -> 2 | T8: =IF($D8="","",IFERROR(INDEX(DB_Artwork_Sizes_Export!$D:$D,MATCH($D8,DB_Artwork_Sizes_Export!$B:$B,0)),"")) -> 18" X 18" | U8: =IF($D8="","",IFERROR(INDEX(DB_Artwork_Sizes_Export!$E:$E,MATCH($D8,DB_Artwork_Sizes_Export!$B:$B,0)),"")) -> 8000.00 | V8: =IF($D8="","",IFERROR(INDEX(DB_Artwork_Sizes_Export!$F:$F,MATCH($D8,DB_Artwork_Sizes_Export!$B:$B,0)),"")) -> 152.00 | W8: =IF($D8="","",IF($S8>0,"REVIEW_SIZE_PRICING","OK")) -> REVIEW_SIZE_PRICING | AF8: =IF($Y8<>"",$Y8,$E8) -> Sacred Geometry in Clay & Mirror | AG8: =IF($Z8<>"",$Z8,$F8) -> lippan-art | AH8: =IF($AG8="","",IFERROR(VLOOKUP($AG8,DB_Categories_Export!$A:$B,2,FALSE()),"INVALID CATEGORY")) -> Lippan Art | AI8: =IF($AA8<>"",$AA8,$H8) -> A stunning Lippan art panel handcrafted with clay motifs and delicate mirror inlays, radiating harmony through its geometric symmetry. Framed by vibrant earthy tones, it brings a serene glow to any space. | AJ8: =IF($AB8<>"",$AB8,$I8) -> Wood | AK8: =IF($AC8<>"",$AC8,$J8) -> 8000.00 | AL8: =IF($AD8<>"",$AD8,$N8) -> f | AM8: =IF($AE8<>"",$AE8,$O8) -> https://chitrakalaarts-production.up.railway.app/api/images/artworks/art-1770777152872 | AO8: INV-03-01 reviewed: final action NO_CHANGE for artwork-level fields. Suggested Sync Action was NO_CHANGE and current artwork fields/category validate. REVIEW was driven by size-level pricing review flag; defer size-level USD/variant pricing to pricing subtask. No Corrected_* fields needed.
A9: NO_CHANGE | B9: =IF($D9="","",IF(COUNTA($Y9:$AE9)>0,"UPDATE","NO_CHANGE")) -> NO_CHANGE | C9: =IF($D9="","",IF($R9<>"OK","ERROR",IF(OR($E9="", $F9="", $J9=""),"ERROR",IF($W9<>"OK","WARNING","PASS")))) -> PASS | D9: =IF(DB_Artworks_Export!A9="","",DB_Artworks_Export!A9) -> art-1770778179564 | E9: =IF(DB_Artworks_Export!B9="","",DB_Artworks_Export!B9) -> Colorful Mandala KeyChain Holder | F9: =IF(DB_Artworks_Export!C9="","",DB_Artworks_Export!C9) -> dot-mandala | G9: =IF(DB_Artworks_Export!D9="","",DB_Artworks_Export!D9) -> Dot Mandala Art | H9: =IF(DB_Artworks_Export!E9="","",DB_Artworks_Export!E9) -> Handcrafted wooden key holder adorned with a vibrant dot mandala design in calming shades of purple and teal. Finished with sturdy hooks, it’s perfect for organizing keys while adding a touch of artistic elegance to your home décor. A beautiful blend of functionality and mindful art—ideal for entryways or as a thoughtful handmade gift. | I9: =IF(DB_Artworks_Export!F9="","",DB_Artworks_Export!F9) -> Wood | J9: =IF(DB_Artworks_Export!G9="","",DB_Artworks_Export!G9) -> 1000.00 | K9: =IF(DB_Artworks_Export!H9="","",DB_Artworks_Export!H9) -> 19.00 | ... Q9: =IF(DB_Artworks_Export!N9="","",DB_Artworks_Export!N9) -> 2026-03-17 03:31:03.453632 | R9: =IF($D9="","",IF(COUNTIF(DB_Categories_Export!$A:$A,$F9)>0,"OK","INVALID CATEGORY")) -> OK | S9: =IF($D9="","",COUNTIF(DB_Artwork_Sizes_Export!$B:$B,$D9)) -> 0 | T9: =IF($D9="","",IFERROR(INDEX(DB_Artwork_Sizes_Export!$D:$D,MATCH($D9,DB_Artwork_Sizes_Export!$B:$B,0)),"")) | U9: =IF($D9="","",IFERROR(INDEX(DB_Artwork_Sizes_Export!$E:$E,MATCH($D9,DB_Artwork_Sizes_Export!$B:$B,0)),"")) | V9: =IF($D9="","",IFERROR(INDEX(DB_Artwork_Sizes_Export!$F:$F,MATCH($D9,DB_Artwork_Sizes_Export!$B:$B,0)),"")) | W9: =IF($D9="","",IF($S9>0,"REVIEW_SIZE_PRICING","OK")) -> OK | AF9: =IF($Y9<>"",$Y9,$E9) -> Colorful Mandala KeyChain Holder | AG9: =IF($Z9<>"",$Z9,$F9) -> dot-mandala | AH9: =IF($AG9="","",IFERROR(VLOOKUP($AG9,DB_Categories_Export!$A:$B,2,FALSE()),"INVALID CATEGORY")) -> Dot Mandala Art | AI9: =IF($AA9<>"",$AA9,$H9) -> Handcrafted wooden key holder adorned with a vibrant dot mandala design in calming shades of purple and teal. Finished with sturdy hooks, it’s perfect for organizing keys while adding a touch of artistic elegance to your home décor. A beautiful blend of functionality and mindful art—ideal for entryways or as a thoughtful handmade gift. | AJ9: =IF($AB9<>"",$AB9,$I9) -> Wood | AK9: =IF($AC9<>"",$AC9,$J9) -> 1000.00 | AL9: =IF($AD9<>"",$AD9,$N9) -> f | AM9: =IF($AE9<>"",$AE9,$O9) -> https://chitrakalaarts-production.up.railway.app/api/images/artworks/art-1770778179564
A10: NO_CHANGE | B10: =IF($D10="","",IF(COUNTA($Y10:$AE10)>0,"UPDATE","NO_CHANGE")) -> NO_CHANGE | C10: =IF($D10="","",IF($R10<>"OK","ERROR",IF(OR($E10="", $F10="", $J10=""),"ERROR",IF($W10<>"OK","WARNING","PASS")))) -> WARNING | D10: =IF(DB_Artworks_Export!A10="","",DB_Artworks_Export!A10) -> art-1770778384172 | E10: =IF(DB_Artworks_Export!B10="","",DB_Artworks_Export!B10) -> Butterfly Set (3 pieces) | F10: =IF(DB_Artworks_Export!C10="","",DB_Artworks_Export!C10) -> dot-mandala | G10: =IF(DB_Artworks_Export!D10="","",DB_Artworks_Export!D10) -> Dot Mandala Art | H10: =IF(DB_Artworks_Export!E10="","",DB_Artworks_Export!E10) -> A graceful butterfly brought to life through intricate dot mandala artistry, this hand-painted piece symbolizes transformation, joy, and renewal. Rendered in warm shades of gold, green, and soft orange, each delicate dot adds depth, movement, and a gentle sense of harmony. Perfect as a mindful décor piece, this artwork radiates elegance and positive energy—an exquisite reminder of beauty in transformation. Available in set of 3 - 8*, 6", 4" | I10: =IF(DB_Artworks_Export!F10="","",DB_Artworks_Export!F10) -> Wood | J10: =IF(DB_Artworks_Export!G10="","",DB_Artworks_Export!G10) -> 1500.00 | K10: =IF(DB_Artworks_Export!H10="","",DB_Artworks_Export!H10) -> 28.00 | ... Q10: =IF(DB_Artworks_Export!N10="","",DB_Artworks_Export!N10) -> 2026-03-17 03:31:03.447787 | R10: =IF($D10="","",IF(COUNTIF(DB_Categories_Export!$A:$A,$F10)>0,"OK","INVALID CATEGORY")) -> OK | S10: =IF($D10="","",COUNTIF(DB_Artwork_Sizes_Export!$B:$B,$D10)) -> 1 | T10: =IF($D10="","",IFERROR(INDEX(DB_Artwork_Sizes_Export!$D:$D,MATCH($D10,DB_Artwork_Sizes_Export!$B:$B,0)),"")) -> 4", 6", 8" set | U10: =IF($D10="","",IFERROR(INDEX(DB_Artwork_Sizes_Export!$E:$E,MATCH($D10,DB_Artwork_Sizes_Export!$B:$B,0)),"")) -> 1500.00 | V10: =IF($D10="","",IFERROR(INDEX(DB_Artwork_Sizes_Export!$F:$F,MATCH($D10,DB_Artwork_Sizes_Export!$B:$B,0)),"")) -> 28.00 | W10: =IF($D10="","",IF($S10>0,"REVIEW_SIZE_PRICING","OK")) -> REVIEW_SIZE_PRICING | AF10: =IF($Y10<>"",$Y10,$E10) -> Butterfly Set (3 pieces) | AG10: =IF($Z10<>"",$Z10,$F10) -> dot-mandala | AH10: =IF($AG10="","",IFERROR(VLOOKUP($AG10,DB_Categories_Export!$A:$B,2,FALSE()),"INVALID CATEGORY")) -> Dot Mandala Art | AI10: =IF($AA10<>"",$AA10,$H10) -> A graceful butterfly brought to life through intricate dot mandala artistry, this hand-painted piece symbolizes transformation, joy, and renewal. Rendered in warm shades of gold, green, and soft orange, each delicate dot adds depth, movement, and a gentle sense of harmony. Perfect as a mindful décor piece, this artwork radiates elegance and positive energy—an exquisite reminder of beauty in transformation. Available in set of 3 - 8*, 6", 4" | AJ10: =IF($AB10<>"",$AB10,$I10) -> Wood | AK10: =IF($AC10<>"",$AC10,$J10) -> 1500.00 | AL10: =IF($AD10<>"",$AD10,$N10) -> f | AM10: =IF($AE10<>"",$AE10,$O10) -> https://chitrakalaarts-production.up.railway.app/api/images/artworks/art-1770778384172 | AO10: INV-03-01 reviewed: final action NO_CHANGE for artwork-level fields. Suggested Sync Action was NO_CHANGE and current artwork fields/category validate. REVIEW was driven by size-level pricing review flag; defer size-level USD/variant pricing to pricing subtask. No Corrected_* fields needed.
A11: NO_CHANGE | B11: =IF($D11="","",IF(COUNTA($Y11:$AE11)>0,"UPDATE","NO_CHANGE")) -> NO_CHANGE | C11: =IF($D11="","",IF($R11<>"OK","ERROR",IF(OR($E11="", $F11="", $J11=""),"ERROR",IF($W11<>"OK","WARNING","PASS")))) -> WARNING | D11: =IF(DB_Artworks_Export!A11="","",DB_Artworks_Export!A11) -> art-1770778509370 | E11: =IF(DB_Artworks_Export!B11="","",DB_Artworks_Export!B11) -> Coaster Set (4 pieces) | F11: =IF(DB_Artworks_Export!C11="","",DB_Artworks_Export!C11) -> dot-mandala | G11: =IF(DB_Artworks_Export!D11="","",DB_Artworks_Export!D11) -> Dot Mandala Art | H11: =IF(DB_Artworks_Export!E11="","",DB_Artworks_Export!E11) -> Add a touch of handcrafted elegance to your everyday moments with this hand-painted dot mandala coaster set. Each coaster is meticulously adorned with intricate dot patterns, radiating symmetry, balance, and calming energy. The rich colors and delicate detailing create a harmonious blend of art and function, protecting your surfaces while elevating your décor. Perfect for tea tables, coffee corners, or thoughtful gifting, this coaster set brings mindful beauty and artisanal charm into every sip. Set of 4 - Rs 750 Set of 6 - Rs 1000 | I11: =IF(DB_Artworks_Export!F11="","",DB_Artworks_Export!F11) -> Wood | J11: =IF(DB_Artworks_Export!G11="","",DB_Artworks_Export!G11) -> 800.00 | K11: =IF(DB_Artworks_Export!H11="","",DB_Artworks_Export!H11) -> 15.00 | ... Q11: =IF(DB_Artworks_Export!N11="","",DB_Artworks_Export!N11) -> 2026-03-17 03:31:03.442637 | R11: =IF($D11="","",IF(COUNTIF(DB_Categories_Export!$A:$A,$F11)>0,"OK","INVALID CATEGORY")) -> OK | S11: =IF($D11="","",COUNTIF(DB_Artwork_Sizes_Export!$B:$B,$D11)) -> 4 | T11: =IF($D11="","",IFERROR(INDEX(DB_Artwork_Sizes_Export!$D:$D,MATCH($D11,DB_Artwork_Sizes_Export!$B:$B,0)),"")) -> 4" (set of 4) | U11: =IF($D11="","",IFERROR(INDEX(DB_Artwork_Sizes_Export!$E:$E,MATCH($D11,DB_Artwork_Sizes_Export!$B:$B,0)),"")) -> 800.00 | V11: =IF($D11="","",IFERROR(INDEX(DB_Artwork_Sizes_Export!$F:$F,MATCH($D11,DB_Artwork_Sizes_Export!$B:$B,0)),"")) -> 15.00 | W11: =IF($D11="","",IF($S11>0,"REVIEW_SIZE_PRICING","OK")) -> REVIEW_SIZE_PRICING | AF11: =IF($Y11<>"",$Y11,$E11) -> Coaster Set (4 pieces) | AG11: =IF($Z11<>"",$Z11,$F11) -> dot-mandala | AH11: =IF($AG11="","",IFERROR(VLOOKUP($AG11,DB_Categories_Export!$A:$B,2,FALSE()),"INVALID CATEGORY")) -> Dot Mandala Art | AI11: =IF($AA11<>"",$AA11,$H11) -> Add a touch of handcrafted elegance to your everyday moments with this hand-painted dot mandala coaster set. Each coaster is meticulously adorned with intricate dot patterns, radiating symmetry, balance, and calming energy. The rich colors and delicate detailing create a harmonious blend of art and function, protecting your surfaces while elevating your décor. Perfect for tea tables, coffee corners, or thoughtful gifting, this coaster set brings mindful beauty and artisanal charm into every sip. Set of 4 - Rs 750 Set of 6 - Rs 1000 | AJ11: =IF($AB11<>"",$AB11,$I11) -> Wood | AK11: =IF($AC11<>"",$AC11,$J11) -> 800.00 | AL11: =IF($AD11<>"",$AD11,$N11) -> f | AM11: =IF($AE11<>"",$AE11,$O11) -> https://chitrakalaarts-production.up.railway.app/api/images/artworks/art-1770778509370 | AO11: INV-03-01 reviewed: final action NO_CHANGE for artwork-level fields. Suggested Sync Action was NO_CHANGE and current artwork fields/category validate. REVIEW was driven by size-level pricing review flag; defer size-level USD/variant pricing to pricing subtask. No Corrected_* fields needed.
A12: NO_CHANGE | B12: =IF($D12="","",IF(COUNTA($Y12:$AE12)>0,"UPDATE","NO_CHANGE")) -> NO_CHANGE | C12: =IF($D12="","",IF($R12<>"OK","ERROR",IF(OR($E12="", $F12="", $J12=""),"ERROR",IF($W12<>"OK","WARNING","PASS")))) -> PASS | D12: =IF(DB_Artworks_Export!A12="","",DB_Artworks_Export!A12) -> art-1770778808201 | E12: =IF(DB_Artworks_Export!B12="","",DB_Artworks_Export!B12) -> Serene Teal Floral Mandala Box | F12: =IF(DB_Artworks_Export!C12="","",DB_Artworks_Export!C12) -> dot-mandala | G12: =IF(DB_Artworks_Export!D12="","",DB_Artworks_Export!D12) -> Dot Mandala Art | H12: =IF(DB_Artworks_Export!E12="","",DB_Artworks_Export!E12) -> Hand-painted dot mandala box in soothing teal and turquoise tones, adorned with intricate floral patterns. A perfect accent piece for storing jewelry, keys, or small keepsakes—bringing calm, color, and handmade charm to any space | I12: =IF(DB_Artworks_Export!F12="","",DB_Artworks_Export!F12) -> Wood | J12: =IF(DB_Artworks_Export!G12="","",DB_Artworks_Export!G12) -> 1000.00 | K12: =IF(DB_Artworks_Export!H12="","",DB_Artworks_Export!H12) -> 19.00 | ... Q12: =IF(DB_Artworks_Export!N12="","",DB_Artworks_Export!N12) -> 2026-03-17 03:31:03.439328 | R12: =IF($D12="","",IF(COUNTIF(DB_Categories_Export!$A:$A,$F12)>0,"OK","INVALID CATEGORY")) -> OK | S12: =IF($D12="","",COUNTIF(DB_Artwork_Sizes_Export!$B:$B,$D12)) -> 0 | T12: =IF($D12="","",IFERROR(INDEX(DB_Artwork_Sizes_Export!$D:$D,MATCH($D12,DB_Artwork_Sizes_Export!$B:$B,0)),"")) | U12: =IF($D12="","",IFERROR(INDEX(DB_Artwork_Sizes_Export!$E:$E,MATCH($D12,DB_Artwork_Sizes_Export!$B:$B,0)),"")) | V12: =IF($D12="","",IFERROR(INDEX(DB_Artwork_Sizes_Export!$F:$F,MATCH($D12,DB_Artwork_Sizes_Export!$B:$B,0)),"")) | W12: =IF($D12="","",IF($S12>0,"REVIEW_SIZE_PRICING","OK")) -> OK | AF12: =IF($Y12<>"",$Y12,$E12) -> Serene Teal Floral Mandala Box | AG12: =IF($Z12<>"",$Z12,$F12) -> dot-mandala | AH12: =IF($AG12="","",IFERROR(VLOOKUP($AG12,DB_Categories_Export!$A:$B,2,FALSE()),"INVALID CATEGORY")) -> Dot Mandala Art | AI12: =IF($AA12<>"",$AA12,$H12) -> Hand-painted dot mandala box in soothing teal and turquoise tones, adorned with intricate floral patterns. A perfect accent piece for storing jewelry, keys, or small keepsakes—bringing calm, color, and handmade charm to any space | AJ12: =IF($AB12<>"",$AB12,$I12) -> Wood | AK12: =IF($AC12<>"",$AC12,$J12) -> 1000.00 | AL12: =IF($AD12<>"",$AD12,$N12) -> f | AM12: =IF($AE12<>"",$AE12,$O12) -> https://chitrakalaarts-production.up.railway.app/api/images/artworks/art-1770778808201
A13: NO_CHANGE | B13: =IF($D13="","",IF(COUNTA($Y13:$AE13)>0,"UPDATE","NO_CHANGE")) -> NO_CHANGE | C13: =IF($D13="","",IF($R13<>"OK","ERROR",IF(OR($E13="", $F13="", $J13=""),"ERROR",IF($W13<>"OK","WARNING","PASS")))) -> WARNING | D13: =IF(DB_Artworks_Export!A13="","",DB_Artworks_Export!A13) -> art-1770779054676 | E13: =IF(DB_Artworks_Export!B13="","",DB_Artworks_Export!B13) -> Floral Rectangular Wooden Storage Box | F13: =IF(DB_Artworks_Export!C13="","",DB_Artworks_Export!C13) -> dot-mandala | G13: =IF(DB_Artworks_Export!D13="","",DB_Artworks_Export!D13) -> Dot Mandala Art | H13: =IF(DB_Artworks_Export!E13="","",DB_Artworks_Export!E13) -> Bring vibrant artistry into your home with this beautifully hand‑painted rectangular wooden storage box. Featuring an intricate floral design in rich shades of orange, green, mustard, and white, the artwork is set against a deep, elegant background that makes every detail pop. The flowing patterns and delicate dot work create a striking centerpiece that reflects traditional craftsmanship with a modern touch. | I13: =IF(DB_Artworks_Export!F13="","",DB_Artworks_Export!F13) -> Wood | J13: =IF(DB_Artworks_Export!G13="","",DB_Artworks_Export!G13) -> 1500.00 | K13: =IF(DB_Artworks_Export!H13="","",DB_Artworks_Export!H13) -> 28.00 | ... Q13: =IF(DB_Artworks_Export!N13="","",DB_Artworks_Export!N13) -> 2026-03-17 03:31:03.43306 | R13: =IF($D13="","",IF(COUNTIF(DB_Categories_Export!$A:$A,$F13)>0,"OK","INVALID CATEGORY")) -> OK | S13: =IF($D13="","",COUNTIF(DB_Artwork_Sizes_Export!$B:$B,$D13)) -> 2 | T13: =IF($D13="","",IFERROR(INDEX(DB_Artwork_Sizes_Export!$D:$D,MATCH($D13,DB_Artwork_Sizes_Export!$B:$B,0)),"")) -> 12" X 5" X 3" (2 partitions) | U13: =IF($D13="","",IFERROR(INDEX(DB_Artwork_Sizes_Export!$E:$E,MATCH($D13,DB_Artwork_Sizes_Export!$B:$B,0)),"")) -> 1500.00 | V13: =IF($D13="","",IFERROR(INDEX(DB_Artwork_Sizes_Export!$F:$F,MATCH($D13,DB_Artwork_Sizes_Export!$B:$B,0)),"")) -> 28.00 | W13: =IF($D13="","",IF($S13>0,"REVIEW_SIZE_PRICING","OK")) -> REVIEW_SIZE_PRICING | AF13: =IF($Y13<>"",$Y13,$E13) -> Floral Rectangular Wooden Storage Box | AG13: =IF($Z13<>"",$Z13,$F13) -> dot-mandala | AH13: =IF($AG13="","",IFERROR(VLOOKUP($AG13,DB_Categories_Export!$A:$B,2,FALSE()),"INVALID CATEGORY")) -> Dot Mandala Art | AI13: =IF($AA13<>"",$AA13,$H13) -> Bring vibrant artistry into your home with this beautifully hand‑painted rectangular wooden storage box. Featuring an intricate floral design in rich shades of orange, green, mustard, and white, the artwork is set against a deep, elegant background that makes every detail pop. The flowing patterns and delicate dot work create a striking centerpiece that reflects traditional craftsmanship with a modern touch. | AJ13: =IF($AB13<>"",$AB13,$I13) -> Wood | AK13: =IF($AC13<>"",$AC13,$J13) -> 1500.00 | AL13: =IF($AD13<>"",$AD13,$N13) -> f | AM13: =IF($AE13<>"",$AE13,$O13) -> https://chitrakalaarts-production.up.railway.app/api/images/artworks/art-1770779054676 | AO13: INV-03-01 reviewed: final action NO_CHANGE for artwork-level fields. Suggested Sync Action was NO_CHANGE and current artwork fields/category validate. REVIEW was driven by size-level pricing review flag; defer size-level USD/variant pricing to pricing subtask. No Corrected_* fields needed.
A14: NO_CHANGE | B14: =IF($D14="","",IF(COUNTA($Y14:$AE14)>0,"UPDATE","NO_CHANGE")) -> NO_CHANGE | C14: =IF($D14="","",IF($R14<>"OK","ERROR",IF(OR($E14="", $F14="", $J14=""),"ERROR",IF($W14<>"OK","WARNING","PASS")))) -> WARNING | D14: =IF(DB_Artworks_Export!A14="","",DB_Artworks_Export!A14) -> art-1770779208267 | E14: =IF(DB_Artworks_Export!B14="","",DB_Artworks_Export!B14) -> Rectangular Wooden box | F14: =IF(DB_Artworks_Export!C14="","",DB_Artworks_Export!C14) -> dot-mandala | G14: =IF(DB_Artworks_Export!D14="","",DB_Artworks_Export!D14) -> Dot Mandala Art | H14: =IF(DB_Artworks_Export!E14="","",DB_Artworks_Export!E14) -> Hand-painted rectangular wooden box featuring beautiful dot mandala artwork delicately painted along the top and bottom borders on all sides. The intricate detailing adds a touch of elegance while keeping the design balanced and timeless. Perfect for storing jewelry, incense, stationery, or small keepsakes, this handcrafted box makes a lovely décor accent | I14: =IF(DB_Artworks_Export!F14="","",DB_Artworks_Export!F14) -> Wood | J14: =IF(DB_Artworks_Export!G14="","",DB_Artworks_Export!G14) -> 700.00 | K14: =IF(DB_Artworks_Export!H14="","",DB_Artworks_Export!H14) -> 13.00 | ... Q14: =IF(DB_Artworks_Export!N14="","",DB_Artworks_Export!N14) -> 2026-05-01 22:02:14.458598 | R14: =IF($D14="","",IF(COUNTIF(DB_Categories_Export!$A:$A,$F14)>0,"OK","INVALID CATEGORY")) -> OK | S14: =IF($D14="","",COUNTIF(DB_Artwork_Sizes_Export!$B:$B,$D14)) -> 2 | T14: =IF($D14="","",IFERROR(INDEX(DB_Artwork_Sizes_Export!$D:$D,MATCH($D14,DB_Artwork_Sizes_Export!$B:$B,0)),"")) -> 9" x 2.5" X 2.5" (single) | U14: =IF($D14="","",IFERROR(INDEX(DB_Artwork_Sizes_Export!$E:$E,MATCH($D14,DB_Artwork_Sizes_Export!$B:$B,0)),"")) -> 700.00 | V14: =IF($D14="","",IFERROR(INDEX(DB_Artwork_Sizes_Export!$F:$F,MATCH($D14,DB_Artwork_Sizes_Export!$B:$B,0)),"")) -> 13.00 | W14: =IF($D14="","",IF($S14>0,"REVIEW_SIZE_PRICING","OK")) -> REVIEW_SIZE_PRICING | AF14: =IF($Y14<>"",$Y14,$E14) -> Rectangular Wooden box | AG14: =IF($Z14<>"",$Z14,$F14) -> dot-mandala | AH14: =IF($AG14="","",IFERROR(VLOOKUP($AG14,DB_Categories_Export!$A:$B,2,FALSE()),"INVALID CATEGORY")) -> Dot Mandala Art | AI14: =IF($AA14<>"",$AA14,$H14) -> Hand-painted rectangular wooden box featuring beautiful dot mandala artwork delicately painted along the top and bottom borders on all sides. The intricate detailing adds a touch of elegance while keeping the design balanced and timeless. Perfect for storing jewelry, incense, stationery, or small keepsakes, this handcrafted box makes a lovely décor accent | AJ14: =IF($AB14<>"",$AB14,$I14) -> Wood | AK14: =IF($AC14<>"",$AC14,$J14) -> 700.00 | AL14: =IF($AD14<>"",$AD14,$N14) -> f | AM14: =IF($AE14<>"",$AE14,$O14) -> https://chitrakalaarts-production.up.railway.app/api/images/artworks/art-1770779208267 | AO14: INV-03-01 reviewed: final action NO_CHANGE for artwork-level fields. Suggested Sync Action was NO_CHANGE and current artwork fields/category validate. REVIEW was driven by size-level pricing review flag; defer size-level USD/variant pricing to pricing subtask. No Corrected_* fields needed.
A15: NO_CHANGE | B15: =IF($D15="","",IF(COUNTA($Y15:$AE15)>0,"UPDATE","NO_CHANGE")) -> NO_CHANGE | C15: =IF($D15="","",IF($R15<>"OK","ERROR",IF(OR($E15="", $F15="", $J15=""),"ERROR",IF($W15<>"OK","WARNING","PASS")))) -> WARNING | D15: =IF(DB_Artworks_Export!A15="","",DB_Artworks_Export!A15) -> art-1770933508740 | E15: =IF(DB_Artworks_Export!B15="","",DB_Artworks_Export!B15) -> Canvas Bag - Birds | F15: =IF(DB_Artworks_Export!C15="","",DB_Artworks_Export!C15) -> textile-design | G15: =IF(DB_Artworks_Export!D15="","",DB_Artworks_Export!D15) -> Textile Art | H15: =IF(DB_Artworks_Export!E15="","",DB_Artworks_Export!E15) -> Beautiful, colorful birds sitting on a tree branch. | I15: =IF(DB_Artworks_Export!F15="","",DB_Artworks_Export!F15) -> Canvas Cloth | J15: =IF(DB_Artworks_Export!G15="","",DB_Artworks_Export!G15) -> 2000.00 | K15: =IF(DB_Artworks_Export!H15="","",DB_Artworks_Export!H15) -> 38.00 | ... Q15: =IF(DB_Artworks_Export!N15="","",DB_Artworks_Export!N15) -> 2026-03-17 03:31:03.42688 | R15: =IF($D15="","",IF(COUNTIF(DB_Categories_Export!$A:$A,$F15)>0,"OK","INVALID CATEGORY")) -> OK | S15: =IF($D15="","",COUNTIF(DB_Artwork_Sizes_Export!$B:$B,$D15)) -> 2 | T15: =IF($D15="","",IFERROR(INDEX(DB_Artwork_Sizes_Export!$D:$D,MATCH($D15,DB_Artwork_Sizes_Export!$B:$B,0)),"")) -> 10"x10" | U15: =IF($D15="","",IFERROR(INDEX(DB_Artwork_Sizes_Export!$E:$E,MATCH($D15,DB_Artwork_Sizes_Export!$B:$B,0)),"")) -> 1500.00 | V15: =IF($D15="","",IFERROR(INDEX(DB_Artwork_Sizes_Export!$F:$F,MATCH($D15,DB_Artwork_Sizes_Export!$B:$B,0)),"")) -> 38.00 | W15: =IF($D15="","",IF($S15>0,"REVIEW_SIZE_PRICING","OK")) -> REVIEW_SIZE_PRICING | AF15: =IF($Y15<>"",$Y15,$E15) -> Canvas Bag - Birds | AG15: =IF($Z15<>"",$Z15,$F15) -> textile-design | AH15: =IF($AG15="","",IFERROR(VLOOKUP($AG15,DB_Categories_Export!$A:$B,2,FALSE()),"INVALID CATEGORY")) -> Textile Art | AI15: =IF($AA15<>"",$AA15,$H15) -> Beautiful, colorful birds sitting on a tree branch. | AJ15: =IF($AB15<>"",$AB15,$I15) -> Canvas Cloth | AK15: =IF($AC15<>"",$AC15,$J15) -> 2000.00 | AL15: =IF($AD15<>"",$AD15,$N15) -> t | AM15: =IF($AE15<>"",$AE15,$O15) -> https://chitrakalaarts-production.up.railway.app/api/images/artworks/art-1770933508740 | AO15: INV-03-01 reviewed: final action NO_CHANGE for artwork-level fields. Suggested Sync Action was NO_CHANGE and current artwork fields/category validate. REVIEW was driven by size-level pricing review flag; defer size-level USD/variant pricing to pricing subtask. No Corrected_* fields needed.
A16: NO_CHANGE | B16: =IF($D16="","",IF(COUNTA($Y16:$AE16)>0,"UPDATE","NO_CHANGE")) -> NO_CHANGE | C16: =IF($D16="","",IF($R16<>"OK","ERROR",IF(OR($E16="", $F16="", $J16=""),"ERROR",IF($W16<>"OK","WARNING","PASS")))) -> WARNING | D16: =IF(DB_Artworks_Export!A16="","",DB_Artworks_Export!A16) -> art-1771030266195 | E16: =IF(DB_Artworks_Export!B16="","",DB_Artworks_Export!B16) -> Hand-Painted Floral Saree | F16: =IF(DB_Artworks_Export!C16="","",DB_Artworks_Export!C16) -> textile-design | G16: =IF(DB_Artworks_Export!D16="","",DB_Artworks_Export!D16) -> Textile Art | H16: =IF(DB_Artworks_Export!E16="","",DB_Artworks_Export!E16) -> Wrap yourself in art. This exquisite hand‑painted saree is a celebration of craftsmanship, tradition, and delicate beauty. Designed on a soft, lightweight fabric that drapes effortlessly, it features intricate floral motifs painted by hand and accented with fine embroidery and shimmering embellishments. Every detail—each petal, each stitch—reflects hours of skilled artisan work. | I16: =IF(DB_Artworks_Export!F16="","",DB_Artworks_Export!F16) -> Georgette | J16: =IF(DB_Artworks_Export!G16="","",DB_Artworks_Export!G16) -> 20000.00 | K16: =IF(DB_Artworks_Export!H16="","",DB_Artworks_Export!H16) -> 379.00 | ... Q16: =IF(DB_Artworks_Export!N16="","",DB_Artworks_Export!N16) -> 2026-03-17 03:31:03.418899 | R16: =IF($D16="","",IF(COUNTIF(DB_Categories_Export!$A:$A,$F16)>0,"OK","INVALID CATEGORY")) -> OK | S16: =IF($D16="","",COUNTIF(DB_Artwork_Sizes_Export!$B:$B,$D16)) -> 1 | T16: =IF($D16="","",IFERROR(INDEX(DB_Artwork_Sizes_Export!$D:$D,MATCH($D16,DB_Artwork_Sizes_Export!$B:$B,0)),"")) -> Standard | U16: =IF($D16="","",IFERROR(INDEX(DB_Artwork_Sizes_Export!$E:$E,MATCH($D16,DB_Artwork_Sizes_Export!$B:$B,0)),"")) -> 20000.00 | V16: =IF($D16="","",IFERROR(INDEX(DB_Artwork_Sizes_Export!$F:$F,MATCH($D16,DB_Artwork_Sizes_Export!$B:$B,0)),"")) -> 379.00 | W16: =IF($D16="","",IF($S16>0,"REVIEW_SIZE_PRICING","OK")) -> REVIEW_SIZE_PRICING | AF16: =IF($Y16<>"",$Y16,$E16) -> Hand-Painted Floral Saree | AG16: =IF($Z16<>"",$Z16,$F16) -> textile-design | AH16: =IF($AG16="","",IFERROR(VLOOKUP($AG16,DB_Categories_Export!$A:$B,2,FALSE()),"INVALID CATEGORY")) -> Textile Art | AI16: =IF($AA16<>"",$AA16,$H16) -> Wrap yourself in art. This exquisite hand‑painted saree is a celebration of craftsmanship, tradition, and delicate beauty. Designed on a soft, lightweight fabric that drapes effortlessly, it features intricate floral motifs painted by hand and accented with fine embroidery and shimmering embellishments. Every detail—each petal, each stitch—reflects hours of skilled artisan work. | AJ16: =IF($AB16<>"",$AB16,$I16) -> Georgette | AK16: =IF($AC16<>"",$AC16,$J16) -> 20000.00 | AL16: =IF($AD16<>"",$AD16,$N16) -> t | AM16: =IF($AE16<>"",$AE16,$O16) -> https://chitrakalaarts-production.up.railway.app/api/images/artworks/art-1771030266195 | AO16: INV-03-01 reviewed: final action NO_CHANGE for artwork-level fields. Suggested Sync Action was NO_CHANGE and current artwork fields/category validate. REVIEW was driven by size-level pricing review flag; defer size-level USD/variant pricing to pricing subtask. No Corrected_* fields needed.
A17: UPDATE | B17: =IF($D17="","",IF(COUNTA($Y17:$AE17)>0,"UPDATE","NO_CHANGE")) -> UPDATE | C17: =IF($D17="","",IF($R17<>"OK","ERROR",IF(OR($E17="", $F17="", $J17=""),"ERROR",IF($W17<>"OK","WARNING","PASS")))) -> WARNING | D17: =IF(DB_Artworks_Export!A17="","",DB_Artworks_Export!A17) -> art-1771030980031 | E17: =IF(DB_Artworks_Export!B17="","",DB_Artworks_Export!B17) -> Midnight Plum Hand-Painted Floral Saree | F17: =IF(DB_Artworks_Export!C17="","",DB_Artworks_Export!C17) -> textile-design | G17: =IF(DB_Artworks_Export!D17="","",DB_Artworks_Export!D17) -> Textile Art | H17: =IF(DB_Artworks_Export!E17="","",DB_Artworks_Export!E17) -> Wrap yourself in effortless elegance with this stunning midnight plum saree, adorned with delicately hand-painted floral motifs. Each bloom unfolds in soft shades of lavender, blush, and muted gold, accented with graceful green leaves that dance across the rich, deep backdrop. The artwork carries a romantic, almost vintage charm — subtle shimmer detailing adds depth and dimension, making the florals appear beautifully alive against the luxurious base. Perfect for evening gatherings, festive celebrations, cultural events, or intimate occasions where you want to make a refined yet unforgettable statement. | I17: =IF(DB_Artworks_Export!F17="","",DB_Artworks_Export!F17) -> Pure Wrinkle Cr | J17: =IF(DB_Artworks_Export!G17="","",DB_Artworks_Export!G17) -> 18000.00 | K17: =IF(DB_Artworks_Export!H17="","",DB_Artworks_Export!H17) -> 341.00 | ... Q17: =IF(DB_Artworks_Export!N17="","",DB_Artworks_Export!N17) -> 2026-03-17 03:31:03.41179 | R17: =IF($D17="","",IF(COUNTIF(DB_Categories_Export!$A:$A,$F17)>0,"OK","INVALID CATEGORY")) -> OK | S17: =IF($D17="","",COUNTIF(DB_Artwork_Sizes_Export!$B:$B,$D17)) -> 1 | T17: =IF($D17="","",IFERROR(INDEX(DB_Artwork_Sizes_Export!$D:$D,MATCH($D17,DB_Artwork_Sizes_Export!$B:$B,0)),"")) -> Standard | U17: =IF($D17="","",IFERROR(INDEX(DB_Artwork_Sizes_Export!$E:$E,MATCH($D17,DB_Artwork_Sizes_Export!$B:$B,0)),"")) -> 18000.00 | V17: =IF($D17="","",IFERROR(INDEX(DB_Artwork_Sizes_Export!$F:$F,MATCH($D17,DB_Artwork_Sizes_Export!$B:$B,0)),"")) -> 341.00 | W17: =IF($D17="","",IF($S17>0,"REVIEW_SIZE_PRICING","OK")) -> REVIEW_SIZE_PRICING | AB17: Pure Wrinkle Crepe | AF17: =IF($Y17<>"",$Y17,$E17) -> Midnight Plum Hand-Painted Floral Saree | AG17: =IF($Z17<>"",$Z17,$F17) -> textile-design | AH17: =IF($AG17="","",IFERROR(VLOOKUP($AG17,DB_Categories_Export!$A:$B,2,FALSE()),"INVALID CATEGORY")) -> Textile Art | AI17: =IF($AA17<>"",$AA17,$H17) -> Wrap yourself in effortless elegance with this stunning midnight plum saree, adorned with delicately hand-painted floral motifs. Each bloom unfolds in soft shades of lavender, blush, and muted gold, accented with graceful green leaves that dance across the rich, deep backdrop. The artwork carries a romantic, almost vintage charm — subtle shimmer detailing adds depth and dimension, making the florals appear beautifully alive against the luxurious base. Perfect for evening gatherings, festive celebrations, cultural events, or intimate occasions where you want to make a refined yet unforgettable statement. | AJ17: =IF($AB17<>"",$AB17,$I17) -> Pure Wrinkle Crepe | AK17: =IF($AC17<>"",$AC17,$J17) -> 18000.00 | AL17: =IF($AD17<>"",$AD17,$N17) -> f | AM17: =IF($AE17<>"",$AE17,$O17) -> https://chitrakalaarts-production.up.railway.app/api/images/artworks/art-1771030980031
A18: NO_CHANGE | B18: =IF($D18="","",IF(COUNTA($Y18:$AE18)>0,"UPDATE","NO_CHANGE")) -> NO_CHANGE | C18: =IF($D18="","",IF($R18<>"OK","ERROR",IF(OR($E18="", $F18="", $J18=""),"ERROR",IF($W18<>"OK","WARNING","PASS")))) -> WARNING | D18: =IF(DB_Artworks_Export!A18="","",DB_Artworks_Export!A18) -> art-1771031213758 | E18: =IF(DB_Artworks_Export!B18="","",DB_Artworks_Export!B18) -> Soft Romantic Pastel Drape with Lavender Blooms | F18: =IF(DB_Artworks_Export!C18="","",DB_Artworks_Export!C18) -> textile-design | G18: =IF(DB_Artworks_Export!D18="","",DB_Artworks_Export!D18) -> Textile Art | H18: =IF(DB_Artworks_Export!E18="","",DB_Artworks_Export!E18) -> Delicate, dreamy, and effortlessly graceful — this blush pink saree is a celebration of soft femininity and timeless artistry. Hand-painted with blooming lavender and rose-toned florals, the design flows gently across the fabric with elegant vine patterns and fresh green leaves. The pastel base enhances the airy watercolor effect of the flowers, creating a light, romantic aesthetic that feels both classic and contemporary. The subtle shimmer accents add just the right hint of refinement, making it perfect for daytime celebrations, festive gatherings, brunch events, or intimate occasions. | I18: =IF(DB_Artworks_Export!F18="","",DB_Artworks_Export!F18) -> Pure Chiffon | J18: =IF(DB_Artworks_Export!G18="","",DB_Artworks_Export!G18) -> 12000.00 | K18: =IF(DB_Artworks_Export!H18="","",DB_Artworks_Export!H18) -> 227.00 | ... Q18: =IF(DB_Artworks_Export!N18="","",DB_Artworks_Export!N18) -> 2026-03-17 03:31:03.406274 | R18: =IF($D18="","",IF(COUNTIF(DB_Categories_Export!$A:$A,$F18)>0,"OK","INVALID CATEGORY")) -> OK | S18: =IF($D18="","",COUNTIF(DB_Artwork_Sizes_Export!$B:$B,$D18)) -> 1 | T18: =IF($D18="","",IFERROR(INDEX(DB_Artwork_Sizes_Export!$D:$D,MATCH($D18,DB_Artwork_Sizes_Export!$B:$B,0)),"")) -> Standard | U18: =IF($D18="","",IFERROR(INDEX(DB_Artwork_Sizes_Export!$E:$E,MATCH($D18,DB_Artwork_Sizes_Export!$B:$B,0)),"")) -> 12000.00 | V18: =IF($D18="","",IFERROR(INDEX(DB_Artwork_Sizes_Export!$F:$F,MATCH($D18,DB_Artwork_Sizes_Export!$B:$B,0)),"")) -> 227.00 | W18: =IF($D18="","",IF($S18>0,"REVIEW_SIZE_PRICING","OK")) -> REVIEW_SIZE_PRICING | AF18: =IF($Y18<>"",$Y18,$E18) -> Soft Romantic Pastel Drape with Lavender Blooms | AG18: =IF($Z18<>"",$Z18,$F18) -> textile-design | AH18: =IF($AG18="","",IFERROR(VLOOKUP($AG18,DB_Categories_Export!$A:$B,2,FALSE()),"INVALID CATEGORY")) -> Textile Art | AI18: =IF($AA18<>"",$AA18,$H18) -> Delicate, dreamy, and effortlessly graceful — this blush pink saree is a celebration of soft femininity and timeless artistry. Hand-painted with blooming lavender and rose-toned florals, the design flows gently across the fabric with elegant vine patterns and fresh green leaves. The pastel base enhances the airy watercolor effect of the flowers, creating a light, romantic aesthetic that feels both classic and contemporary. The subtle shimmer accents add just the right hint of refinement, making it perfect for daytime celebrations, festive gatherings, brunch events, or intimate occasions. | AJ18: =IF($AB18<>"",$AB18,$I18) -> Pure Chiffon | AK18: =IF($AC18<>"",$AC18,$J18) -> 12000.00 | AL18: =IF($AD18<>"",$AD18,$N18) -> f | AM18: =IF($AE18<>"",$AE18,$O18) -> https://chitrakalaarts-production.up.railway.app/api/images/artworks/art-1771031213758 | AO18: INV-03-01 reviewed: final action NO_CHANGE for artwork-level fields. Suggested Sync Action was NO_CHANGE and current artwork fields/category validate. REVIEW was driven by size-level pricing review flag; defer size-level USD/variant pricing to pricing subtask. No Corrected_* fields needed.
A19: NO_CHANGE | B19: =IF($D19="","",IF(COUNTA($Y19:$AE19)>0,"UPDATE","NO_CHANGE")) -> NO_CHANGE | C19: =IF($D19="","",IF($R19<>"OK","ERROR",IF(OR($E19="", $F19="", $J19=""),"ERROR",IF($W19<>"OK","WARNING","PASS")))) -> WARNING | D19: =IF(DB_Artworks_Export!A19="","",DB_Artworks_Export!A19) -> art-1771033398626 | E19: =IF(DB_Artworks_Export!B19="","",DB_Artworks_Export!B19) -> Teal & Blue Boho Decorative Round | F19: =IF(DB_Artworks_Export!C19="","",DB_Artworks_Export!C19) -> dot-mandala | G19: =IF(DB_Artworks_Export!D19="","",DB_Artworks_Export!D19) -> Dot Mandala Art | H19: =IF(DB_Artworks_Export!E19="","",DB_Artworks_Export!E19) -> A small piece with a powerful presence. Available as single piece or in set. This mandala is more than décor — it’s a symbol of unity, mindfulness, and creative energy, crafted with patience and love. Add a touch of vibrant harmony to your space with this beautifully hand-painted 6-inch round dot mandala artwork. Designed with intricate layers of carefully placed dots, this piece radiates balance, calm, and artistic elegance. | I19: =IF(DB_Artworks_Export!F19="","",DB_Artworks_Export!F19) -> Wood | J19: =IF(DB_Artworks_Export!G19="","",DB_Artworks_Export!G19) -> 1000.00 | K19: =IF(DB_Artworks_Export!H19="","",DB_Artworks_Export!H19) -> 19.00 | ... Q19: =IF(DB_Artworks_Export!N19="","",DB_Artworks_Export!N19) -> 2026-03-17 03:31:03.400385 | R19: =IF($D19="","",IF(COUNTIF(DB_Categories_Export!$A:$A,$F19)>0,"OK","INVALID CATEGORY")) -> OK | S19: =IF($D19="","",COUNTIF(DB_Artwork_Sizes_Export!$B:$B,$D19)) -> 2 | T19: =IF($D19="","",IFERROR(INDEX(DB_Artwork_Sizes_Export!$D:$D,MATCH($D19,DB_Artwork_Sizes_Export!$B:$B,0)),"")) -> 6" (set of 2) | U19: =IF($D19="","",IFERROR(INDEX(DB_Artwork_Sizes_Export!$E:$E,MATCH($D19,DB_Artwork_Sizes_Export!$B:$B,0)),"")) -> 1000.00 | V19: =IF($D19="","",IFERROR(INDEX(DB_Artwork_Sizes_Export!$F:$F,MATCH($D19,DB_Artwork_Sizes_Export!$B:$B,0)),"")) -> 19.00 | W19: =IF($D19="","",IF($S19>0,"REVIEW_SIZE_PRICING","OK")) -> REVIEW_SIZE_PRICING | AF19: =IF($Y19<>"",$Y19,$E19) -> Teal & Blue Boho Decorative Round | AG19: =IF($Z19<>"",$Z19,$F19) -> dot-mandala | AH19: =IF($AG19="","",IFERROR(VLOOKUP($AG19,DB_Categories_Export!$A:$B,2,FALSE()),"INVALID CATEGORY")) -> Dot Mandala Art | AI19: =IF($AA19<>"",$AA19,$H19) -> A small piece with a powerful presence. Available as single piece or in set. This mandala is more than décor — it’s a symbol of unity, mindfulness, and creative energy, crafted with patience and love. Add a touch of vibrant harmony to your space with this beautifully hand-painted 6-inch round dot mandala artwork. Designed with intricate layers of carefully placed dots, this piece radiates balance, calm, and artistic elegance. | AJ19: =IF($AB19<>"",$AB19,$I19) -> Wood | AK19: =IF($AC19<>"",$AC19,$J19) -> 1000.00 | AL19: =IF($AD19<>"",$AD19,$N19) -> f | AM19: =IF($AE19<>"",$AE19,$O19) -> https://chitrakalaarts-production.up.railway.app/api/images/artworks/art-1771033398626 | AO19: INV-03-01 reviewed: final action NO_CHANGE for artwork-level fields. Suggested Sync Action was NO_CHANGE and current artwork fields/category validate. REVIEW was driven by size-level pricing review flag; defer size-level USD/variant pricing to pricing subtask. No Corrected_* fields needed.
A20: NO_CHANGE | B20: =IF($D20="","",IF(COUNTA($Y20:$AE20)>0,"UPDATE","NO_CHANGE")) -> NO_CHANGE | C20: =IF($D20="","",IF($R20<>"OK","ERROR",IF(OR($E20="", $F20="", $J20=""),"ERROR",IF($W20<>"OK","WARNING","PASS")))) -> WARNING | D20: =IF(DB_Artworks_Export!A20="","",DB_Artworks_Export!A20) -> art-1771101879286 | E20: =IF(DB_Artworks_Export!B20="","",DB_Artworks_Export!B20) -> Decorative Serving Board | F20: =IF(DB_Artworks_Export!C20="","",DB_Artworks_Export!C20) -> dot-mandala | G20: =IF(DB_Artworks_Export!D20="","",DB_Artworks_Export!D20) -> Dot Mandala Art | H20: =IF(DB_Artworks_Export!E20="","",DB_Artworks_Export!E20) -> Elevate your kitchen and dining space with this exquisite hand-painted wooden serving board. • Hand painted Durable wooden base with smooth finish • Intricate dot mandala design – each piece is one-of-a-kind • Sealed for light use and easy maintenance ✨ Perfect For: • Housewarming gifts • Wedding or anniversary presents • Boho or rustic kitchen décor • Art lovers and handmade collectors | I20: =IF(DB_Artworks_Export!F20="","",DB_Artworks_Export!F20) -> Wood | J20: =IF(DB_Artworks_Export!G20="","",DB_Artworks_Export!G20) -> 800.00 | K20: =IF(DB_Artworks_Export!H20="","",DB_Artworks_Export!H20) -> 15.00 | ... Q20: =IF(DB_Artworks_Export!N20="","",DB_Artworks_Export!N20) -> 2026-03-22 14:12:58.425012 | R20: =IF($D20="","",IF(COUNTIF(DB_Categories_Export!$A:$A,$F20)>0,"OK","INVALID CATEGORY")) -> OK | S20: =IF($D20="","",COUNTIF(DB_Artwork_Sizes_Export!$B:$B,$D20)) -> 6 | T20: =IF($D20="","",IFERROR(INDEX(DB_Artwork_Sizes_Export!$D:$D,MATCH($D20,DB_Artwork_Sizes_Export!$B:$B,0)),"")) -> 9" (single) | U20: =IF($D20="","",IFERROR(INDEX(DB_Artwork_Sizes_Export!$E:$E,MATCH($D20,DB_Artwork_Sizes_Export!$B:$B,0)),"")) -> 800.00 | V20: =IF($D20="","",IFERROR(INDEX(DB_Artwork_Sizes_Export!$F:$F,MATCH($D20,DB_Artwork_Sizes_Export!$B:$B,0)),"")) -> 15.00 | W20: =IF($D20="","",IF($S20>0,"REVIEW_SIZE_PRICING","OK")) -> REVIEW_SIZE_PRICING | AF20: =IF($Y20<>"",$Y20,$E20) -> Decorative Serving Board | AG20: =IF($Z20<>"",$Z20,$F20) -> dot-mandala | AH20: =IF($AG20="","",IFERROR(VLOOKUP($AG20,DB_Categories_Export!$A:$B,2,FALSE()),"INVALID CATEGORY")) -> Dot Mandala Art | AI20: =IF($AA20<>"",$AA20,$H20) -> Elevate your kitchen and dining space with this exquisite hand-painted wooden serving board. • Hand painted Durable wooden base with smooth finish • Intricate dot mandala design – each piece is one-of-a-kind • Sealed for light use and easy maintenance ✨ Perfect For: • Housewarming gifts • Wedding or anniversary presents • Boho or rustic kitchen décor • Art lovers and handmade collectors | AJ20: =IF($AB20<>"",$AB20,$I20) -> Wood | AK20: =IF($AC20<>"",$AC20,$J20) -> 800.00 | AL20: =IF($AD20<>"",$AD20,$N20) -> f | AM20: =IF($AE20<>"",$AE20,$O20) -> https://chitrakalaarts-production.up.railway.app/api/images/artworks/art-1771101879286 | AO20: INV-03-01 reviewed: final action NO_CHANGE for artwork-level fields. Suggested Sync Action was NO_CHANGE and current artwork fields/category validate. REVIEW was driven by size-level pricing review flag; defer size-level USD/variant pricing to pricing subtask. No Corrected_* fields needed.
A21: NO_CHANGE | B21: =IF($D21="","",IF(COUNTA($Y21:$AE21)>0,"UPDATE","NO_CHANGE")) -> NO_CHANGE | C21: =IF($D21="","",IF($R21<>"OK","ERROR",IF(OR($E21="", $F21="", $J21=""),"ERROR",IF($W21<>"OK","WARNING","PASS")))) -> WARNING | D21: =IF(DB_Artworks_Export!A21="","",DB_Artworks_Export!A21) -> art-1771101978525 | E21: =IF(DB_Artworks_Export!B21="","",DB_Artworks_Export!B21) -> Hand painted Tussar Saree | F21: =IF(DB_Artworks_Export!C21="","",DB_Artworks_Export!C21) -> textile-design | G21: =IF(DB_Artworks_Export!D21="","",DB_Artworks_Export!D21) -> Textile Art | H21: =IF(DB_Artworks_Export!E21="","",DB_Artworks_Export!E21) -> Beautiful hand painted saree with Ornamental design all over | I21: =IF(DB_Artworks_Export!F21="","",DB_Artworks_Export!F21) -> Pure Tussar | J21: =IF(DB_Artworks_Export!G21="","",DB_Artworks_Export!G21) -> 22000.00 | K21: =IF(DB_Artworks_Export!H21="","",DB_Artworks_Export!H21) -> 417.00 | ... Q21: =IF(DB_Artworks_Export!N21="","",DB_Artworks_Export!N21) -> 2026-03-17 03:31:03.383394 | R21: =IF($D21="","",IF(COUNTIF(DB_Categories_Export!$A:$A,$F21)>0,"OK","INVALID CATEGORY")) -> OK | S21: =IF($D21="","",COUNTIF(DB_Artwork_Sizes_Export!$B:$B,$D21)) -> 1 | T21: =IF($D21="","",IFERROR(INDEX(DB_Artwork_Sizes_Export!$D:$D,MATCH($D21,DB_Artwork_Sizes_Export!$B:$B,0)),"")) -> Standard | U21: =IF($D21="","",IFERROR(INDEX(DB_Artwork_Sizes_Export!$E:$E,MATCH($D21,DB_Artwork_Sizes_Export!$B:$B,0)),"")) -> 22000.00 | V21: =IF($D21="","",IFERROR(INDEX(DB_Artwork_Sizes_Export!$F:$F,MATCH($D21,DB_Artwork_Sizes_Export!$B:$B,0)),"")) -> 417.00 | W21: =IF($D21="","",IF($S21>0,"REVIEW_SIZE_PRICING","OK")) -> REVIEW_SIZE_PRICING | AF21: =IF($Y21<>"",$Y21,$E21) -> Hand painted Tussar Saree | AG21: =IF($Z21<>"",$Z21,$F21) -> textile-design | AH21: =IF($AG21="","",IFERROR(VLOOKUP($AG21,DB_Categories_Export!$A:$B,2,FALSE()),"INVALID CATEGORY")) -> Textile Art | AI21: =IF($AA21<>"",$AA21,$H21) -> Beautiful hand painted saree with Ornamental design all over | AJ21: =IF($AB21<>"",$AB21,$I21) -> Pure Tussar | AK21: =IF($AC21<>"",$AC21,$J21) -> 22000.00 | AL21: =IF($AD21<>"",$AD21,$N21) -> f | AM21: =IF($AE21<>"",$AE21,$O21) -> https://chitrakalaarts-production.up.railway.app/api/images/artworks/art-1771101978525 | AO21: INV-03-01 reviewed: final action NO_CHANGE for artwork-level fields. Suggested Sync Action was NO_CHANGE and current artwork fields/category validate. REVIEW was driven by size-level pricing review flag; defer size-level USD/variant pricing to pricing subtask. No Corrected_* fields needed.
A22: UPDATE | B22: =IF($D22="","",IF(COUNTA($Y22:$AE22)>0,"UPDATE","NO_CHANGE")) -> UPDATE | C22: =IF($D22="","",IF($R22<>"OK","ERROR",IF(OR($E22="", $F22="", $J22=""),"ERROR",IF($W22<>"OK","WARNING","PASS")))) -> WARNING | D22: =IF(DB_Artworks_Export!A22="","",DB_Artworks_Export!A22) -> art-1771102194181 | E22: =IF(DB_Artworks_Export!B22="","",DB_Artworks_Export!B22) -> Coaster Set (4 pieces) | F22: =IF(DB_Artworks_Export!C22="","",DB_Artworks_Export!C22) -> dot-mandala | G22: =IF(DB_Artworks_Export!D22="","",DB_Artworks_Export!D22) -> Dot Mandala Art | H22: =IF(DB_Artworks_Export!E22="","",DB_Artworks_Export!E22) -> Beautiful dot mandala coaster set in variety of patterns and colors | I22: =IF(DB_Artworks_Export!F22="","",DB_Artworks_Export!F22) -> Wood | J22: =IF(DB_Artworks_Export!G22="","",DB_Artworks_Export!G22) -> 800.00 | K22: =IF(DB_Artworks_Export!H22="","",DB_Artworks_Export!H22) -> 15.00 | ... Q22: =IF(DB_Artworks_Export!N22="","",DB_Artworks_Export!N22) -> 2026-03-20 01:19:53.847521 | R22: =IF($D22="","",IF(COUNTIF(DB_Categories_Export!$A:$A,$F22)>0,"OK","INVALID CATEGORY")) -> OK | S22: =IF($D22="","",COUNTIF(DB_Artwork_Sizes_Export!$B:$B,$D22)) -> 4 | T22: =IF($D22="","",IFERROR(INDEX(DB_Artwork_Sizes_Export!$D:$D,MATCH($D22,DB_Artwork_Sizes_Export!$B:$B,0)),"")) -> 4" (set of 4) | U22: =IF($D22="","",IFERROR(INDEX(DB_Artwork_Sizes_Export!$E:$E,MATCH($D22,DB_Artwork_Sizes_Export!$B:$B,0)),"")) -> 800.00 | V22: =IF($D22="","",IFERROR(INDEX(DB_Artwork_Sizes_Export!$F:$F,MATCH($D22,DB_Artwork_Sizes_Export!$B:$B,0)),"")) -> 15.00 | W22: =IF($D22="","",IF($S22>0,"REVIEW_SIZE_PRICING","OK")) -> REVIEW_SIZE_PRICING | Y22: Dot Mandala Coaster Set – Variety Pack (4 pieces) | AF22: =IF($Y22<>"",$Y22,$E22) -> Dot Mandala Coaster Set – Variety Pack (4 pieces) | AG22: =IF($Z22<>"",$Z22,$F22) -> dot-mandala | AH22: =IF($AG22="","",IFERROR(VLOOKUP($AG22,DB_Categories_Export!$A:$B,2,FALSE()),"INVALID CATEGORY")) -> Dot Mandala Art | AI22: =IF($AA22<>"",$AA22,$H22) -> Beautiful dot mandala coaster set in variety of patterns and colors | AJ22: =IF($AB22<>"",$AB22,$I22) -> Wood | AK22: =IF($AC22<>"",$AC22,$J22) -> 800.00 | AL22: =IF($AD22<>"",$AD22,$N22) -> f | AM22: =IF($AE22<>"",$AE22,$O22) -> https://chitrakalaarts-production.up.railway.app/api/images/artworks/art-1771102194181
A23: UPDATE | B23: =IF($D23="","",IF(COUNTA($Y23:$AE23)>0,"UPDATE","NO_CHANGE")) -> UPDATE | C23: =IF($D23="","",IF($R23<>"OK","ERROR",IF(OR($E23="", $F23="", $J23=""),"ERROR",IF($W23<>"OK","WARNING","PASS")))) -> WARNING | D23: =IF(DB_Artworks_Export!A23="","",DB_Artworks_Export!A23) -> art-1771102482592 | E23: =IF(DB_Artworks_Export!B23="","",DB_Artworks_Export!B23) -> Decorative Wall Panel | F23: =IF(DB_Artworks_Export!C23="","",DB_Artworks_Export!C23) -> lippan-art | G23: =IF(DB_Artworks_Export!D23="","",DB_Artworks_Export!D23) -> Lippan Art | H23: =IF(DB_Artworks_Export!E23="","",DB_Artworks_Export!E23) -> Beautiful piece decorated with clay and mirrors | I23: =IF(DB_Artworks_Export!F23="","",DB_Artworks_Export!F23) -> Wood, Clay and Mirrors | J23: =IF(DB_Artworks_Export!G23="","",DB_Artworks_Export!G23) -> 3000.00 | K23: =IF(DB_Artworks_Export!H23="","",DB_Artworks_Export!H23) -> 57.00 | ... Q23: =IF(DB_Artworks_Export!N23="","",DB_Artworks_Export!N23) -> 2026-03-17 03:31:03.372791 | R23: =IF($D23="","",IF(COUNTIF(DB_Categories_Export!$A:$A,$F23)>0,"OK","INVALID CATEGORY")) -> OK | S23: =IF($D23="","",COUNTIF(DB_Artwork_Sizes_Export!$B:$B,$D23)) -> 3 | T23: =IF($D23="","",IFERROR(INDEX(DB_Artwork_Sizes_Export!$D:$D,MATCH($D23,DB_Artwork_Sizes_Export!$B:$B,0)),"")) -> 8" (round) or 8" (square) | U23: =IF($D23="","",IFERROR(INDEX(DB_Artwork_Sizes_Export!$E:$E,MATCH($D23,DB_Artwork_Sizes_Export!$B:$B,0)),"")) -> 1600.00 | V23: =IF($D23="","",IFERROR(INDEX(DB_Artwork_Sizes_Export!$F:$F,MATCH($D23,DB_Artwork_Sizes_Export!$B:$B,0)),"")) -> 57.00 | W23: =IF($D23="","",IF($S23>0,"REVIEW_SIZE_PRICING","OK")) -> REVIEW_SIZE_PRICING | Y23: Lippan Decorative Wall Panel – Style A | AF23: =IF($Y23<>"",$Y23,$E23) -> Lippan Decorative Wall Panel – Style A | AG23: =IF($Z23<>"",$Z23,$F23) -> lippan-art | AH23: =IF($AG23="","",IFERROR(VLOOKUP($AG23,DB_Categories_Export!$A:$B,2,FALSE()),"INVALID CATEGORY")) -> Lippan Art | AI23: =IF($AA23<>"",$AA23,$H23) -> Beautiful piece decorated with clay and mirrors | AJ23: =IF($AB23<>"",$AB23,$I23) -> Wood, Clay and Mirrors | AK23: =IF($AC23<>"",$AC23,$J23) -> 3000.00 | AL23: =IF($AD23<>"",$AD23,$N23) -> f | AM23: =IF($AE23<>"",$AE23,$O23) -> https://chitrakalaarts-production.up.railway.app/api/images/artworks/art-1771102482592
A24: UPDATE | B24: =IF($D24="","",IF(COUNTA($Y24:$AE24)>0,"UPDATE","NO_CHANGE")) -> UPDATE | C24: =IF($D24="","",IF($R24<>"OK","ERROR",IF(OR($E24="", $F24="", $J24=""),"ERROR",IF($W24<>"OK","WARNING","PASS")))) -> WARNING | D24: =IF(DB_Artworks_Export!A24="","",DB_Artworks_Export!A24) -> art-1771102578812 | E24: =IF(DB_Artworks_Export!B24="","",DB_Artworks_Export!B24) -> Decorative Wall Panel | F24: =IF(DB_Artworks_Export!C24="","",DB_Artworks_Export!C24) -> lippan-art | G24: =IF(DB_Artworks_Export!D24="","",DB_Artworks_Export!D24) -> Lippan Art | H24: =IF(DB_Artworks_Export!E24="","",DB_Artworks_Export!E24) -> Beautiful arrangement with clay, colors and mirrors | I24: =IF(DB_Artworks_Export!F24="","",DB_Artworks_Export!F24) -> Wood | J24: =IF(DB_Artworks_Export!G24="","",DB_Artworks_Export!G24) -> 1800.00 | K24: =IF(DB_Artworks_Export!H24="","",DB_Artworks_Export!H24) -> 34.00 | ... Q24: =IF(DB_Artworks_Export!N24="","",DB_Artworks_Export!N24) -> 2026-03-17 03:31:03.365304 | R24: =IF($D24="","",IF(COUNTIF(DB_Categories_Export!$A:$A,$F24)>0,"OK","INVALID CATEGORY")) -> OK | S24: =IF($D24="","",COUNTIF(DB_Artwork_Sizes_Export!$B:$B,$D24)) -> 3 | T24: =IF($D24="","",IFERROR(INDEX(DB_Artwork_Sizes_Export!$D:$D,MATCH($D24,DB_Artwork_Sizes_Export!$B:$B,0)),"")) -> 8"(round) or 8" (square) | U24: =IF($D24="","",IFERROR(INDEX(DB_Artwork_Sizes_Export!$E:$E,MATCH($D24,DB_Artwork_Sizes_Export!$B:$B,0)),"")) -> 1600.00 | V24: =IF($D24="","",IFERROR(INDEX(DB_Artwork_Sizes_Export!$F:$F,MATCH($D24,DB_Artwork_Sizes_Export!$B:$B,0)),"")) -> 34.00 | W24: =IF($D24="","",IF($S24>0,"REVIEW_SIZE_PRICING","OK")) -> REVIEW_SIZE_PRICING | AB24: Wood, Clay and Mirrors | AF24: =IF($Y24<>"",$Y24,$E24) -> Decorative Wall Panel | AG24: =IF($Z24<>"",$Z24,$F24) -> lippan-art | AH24: =IF($AG24="","",IFERROR(VLOOKUP($AG24,DB_Categories_Export!$A:$B,2,FALSE()),"INVALID CATEGORY")) -> Lippan Art | AI24: =IF($AA24<>"",$AA24,$H24) -> Beautiful arrangement with clay, colors and mirrors | AJ24: =IF($AB24<>"",$AB24,$I24) -> Wood, Clay and Mirrors | AK24: =IF($AC24<>"",$AC24,$J24) -> 1800.00 | AL24: =IF($AD24<>"",$AD24,$N24) -> f | AM24: =IF($AE24<>"",$AE24,$O24) -> https://chitrakalaarts-production.up.railway.app/api/images/artworks/art-1771102578812
A25: UPDATE | B25: =IF($D25="","",IF(COUNTA($Y25:$AE25)>0,"UPDATE","NO_CHANGE")) -> UPDATE | C25: =IF($D25="","",IF($R25<>"OK","ERROR",IF(OR($E25="", $F25="", $J25=""),"ERROR",IF($W25<>"OK","WARNING","PASS")))) -> WARNING | D25: =IF(DB_Artworks_Export!A25="","",DB_Artworks_Export!A25) -> art-1771102688340 | E25: =IF(DB_Artworks_Export!B25="","",DB_Artworks_Export!B25) -> Small decorative Rounds (set of 5) | F25: =IF(DB_Artworks_Export!C25="","",DB_Artworks_Export!C25) -> lippan-art | G25: =IF(DB_Artworks_Export!D25="","",DB_Artworks_Export!D25) -> Lippan Art | H25: =IF(DB_Artworks_Export!E25="","",DB_Artworks_Export!E25) -> Small accent pieces | I25: =IF(DB_Artworks_Export!F25="","",DB_Artworks_Export!F25) -> Wood | J25: =IF(DB_Artworks_Export!G25="","",DB_Artworks_Export!G25) -> 1200.00 | K25: =IF(DB_Artworks_Export!H25="","",DB_Artworks_Export!H25) -> 23.00 | ... Q25: =IF(DB_Artworks_Export!N25="","",DB_Artworks_Export!N25) -> 2026-03-17 03:31:03.359987 | R25: =IF($D25="","",IF(COUNTIF(DB_Categories_Export!$A:$A,$F25)>0,"OK","INVALID CATEGORY")) -> OK | S25: =IF($D25="","",COUNTIF(DB_Artwork_Sizes_Export!$B:$B,$D25)) -> 1 | T25: =IF($D25="","",IFERROR(INDEX(DB_Artwork_Sizes_Export!$D:$D,MATCH($D25,DB_Artwork_Sizes_Export!$B:$B,0)),"")) -> 6" (set of 5) | U25: =IF($D25="","",IFERROR(INDEX(DB_Artwork_Sizes_Export!$E:$E,MATCH($D25,DB_Artwork_Sizes_Export!$B:$B,0)),"")) -> 1500.00 | V25: =IF($D25="","",IFERROR(INDEX(DB_Artwork_Sizes_Export!$F:$F,MATCH($D25,DB_Artwork_Sizes_Export!$B:$B,0)),"")) -> 23.00 | W25: =IF($D25="","",IF($S25>0,"REVIEW_SIZE_PRICING","OK")) -> REVIEW_SIZE_PRICING | AC25: 1500 | AF25: =IF($Y25<>"",$Y25,$E25) -> Small decorative Rounds (set of 5) | AG25: =IF($Z25<>"",$Z25,$F25) -> lippan-art | AH25: =IF($AG25="","",IFERROR(VLOOKUP($AG25,DB_Categories_Export!$A:$B,2,FALSE()),"INVALID CATEGORY")) -> Lippan Art | AI25: =IF($AA25<>"",$AA25,$H25) -> Small accent pieces | AJ25: =IF($AB25<>"",$AB25,$I25) -> Wood | AK25: =IF($AC25<>"",$AC25,$J25) -> 1500 | AL25: =IF($AD25<>"",$AD25,$N25) -> f | AM25: =IF($AE25<>"",$AE25,$O25) -> https://chitrakalaarts-production.up.railway.app/api/images/artworks/art-1771102688340
A26: NO_CHANGE | B26: =IF($D26="","",IF(COUNTA($Y26:$AE26)>0,"UPDATE","NO_CHANGE")) -> NO_CHANGE | C26: =IF($D26="","",IF($R26<>"OK","ERROR",IF(OR($E26="", $F26="", $J26=""),"ERROR",IF($W26<>"OK","WARNING","PASS")))) -> WARNING | D26: =IF(DB_Artworks_Export!A26="","",DB_Artworks_Export!A26) -> art-1771454920479 | E26: =IF(DB_Artworks_Export!B26="","",DB_Artworks_Export!B26) -> Canvas Bag - Flowers | F26: =IF(DB_Artworks_Export!C26="","",DB_Artworks_Export!C26) -> textile-design | G26: =IF(DB_Artworks_Export!D26="","",DB_Artworks_Export!D26) -> Textile Art | H26: =IF(DB_Artworks_Export!E26="","",DB_Artworks_Export!E26) -> Beautiful flowers with a butterflies showcased on a canvas bag. | I26: =IF(DB_Artworks_Export!F26="","",DB_Artworks_Export!F26) -> Canvas Cloth | J26: =IF(DB_Artworks_Export!G26="","",DB_Artworks_Export!G26) -> 1000.00 | K26: =IF(DB_Artworks_Export!H26="","",DB_Artworks_Export!H26) -> 19.00 | ... Q26: =IF(DB_Artworks_Export!N26="","",DB_Artworks_Export!N26) -> 2026-03-17 03:31:03.353663 | R26: =IF($D26="","",IF(COUNTIF(DB_Categories_Export!$A:$A,$F26)>0,"OK","INVALID CATEGORY")) -> OK | S26: =IF($D26="","",COUNTIF(DB_Artwork_Sizes_Export!$B:$B,$D26)) -> 2 | T26: =IF($D26="","",IFERROR(INDEX(DB_Artwork_Sizes_Export!$D:$D,MATCH($D26,DB_Artwork_Sizes_Export!$B:$B,0)),"")) -> 12" x 11" | U26: =IF($D26="","",IFERROR(INDEX(DB_Artwork_Sizes_Export!$E:$E,MATCH($D26,DB_Artwork_Sizes_Export!$B:$B,0)),"")) -> 1000.00 | V26: =IF($D26="","",IFERROR(INDEX(DB_Artwork_Sizes_Export!$F:$F,MATCH($D26,DB_Artwork_Sizes_Export!$B:$B,0)),"")) -> 19.00 | W26: =IF($D26="","",IF($S26>0,"REVIEW_SIZE_PRICING","OK")) -> REVIEW_SIZE_PRICING | AF26: =IF($Y26<>"",$Y26,$E26) -> Canvas Bag - Flowers | AG26: =IF($Z26<>"",$Z26,$F26) -> textile-design | AH26: =IF($AG26="","",IFERROR(VLOOKUP($AG26,DB_Categories_Export!$A:$B,2,FALSE()),"INVALID CATEGORY")) -> Textile Art | AI26: =IF($AA26<>"",$AA26,$H26) -> Beautiful flowers with a butterflies showcased on a canvas bag. | AJ26: =IF($AB26<>"",$AB26,$I26) -> Canvas Cloth | AK26: =IF($AC26<>"",$AC26,$J26) -> 1000.00 | AL26: =IF($AD26<>"",$AD26,$N26) -> t | AM26: =IF($AE26<>"",$AE26,$O26) -> https://chitrakalaarts-production.up.railway.app/api/images/artworks/art-1771454920479 | AO26: INV-03-01 reviewed: final action NO_CHANGE for artwork-level fields. Suggested Sync Action was NO_CHANGE and current artwork fields/category validate. REVIEW was driven by size-level pricing review flag; defer size-level USD/variant pricing to pricing subtask. No Corrected_* fields needed.
A27: NO_CHANGE | B27: =IF($D27="","",IF(COUNTA($Y27:$AE27)>0,"UPDATE","NO_CHANGE")) -> NO_CHANGE | C27: =IF($D27="","",IF($R27<>"OK","ERROR",IF(OR($E27="", $F27="", $J27=""),"ERROR",IF($W27<>"OK","WARNING","PASS")))) -> WARNING | D27: =IF(DB_Artworks_Export!A27="","",DB_Artworks_Export!A27) -> art-1771902788998 | E27: =IF(DB_Artworks_Export!B27="","",DB_Artworks_Export!B27) -> Hand Painted Wooden Mandala Tray (fillable Round) | F27: =IF(DB_Artworks_Export!C27="","",DB_Artworks_Export!C27) -> dot-mandala | G27: =IF(DB_Artworks_Export!D27="","",DB_Artworks_Export!D27) -> Dot Mandala Art | H27: =IF(DB_Artworks_Export!E27="","",DB_Artworks_Export!E27) -> An exquisite hand-painted wooden round mandala tray, designed to elevate your space with rich heritage and refined artistry. Set against a deep maroon base, intricate layers of radiant orange, green, and gold detailing form a beautifully balanced floral mandala — each element carefully painted by hand. Crafted on a solid wooden base and sealed for durability, this piece is designed as a decorative table accent — perfect for styling on a coffee table, console, or festive setting. Elegant, vibrant, and one-of-a-kind, it brings a touch of artisanal luxury and timeless craftsmanship into your home. | I27: =IF(DB_Artworks_Export!F27="","",DB_Artworks_Export!F27) -> Wood | J27: =IF(DB_Artworks_Export!G27="","",DB_Artworks_Export!G27) -> 1100.00 | K27: =IF(DB_Artworks_Export!H27="","",DB_Artworks_Export!H27) -> 21.00 | ... Q27: =IF(DB_Artworks_Export!N27="","",DB_Artworks_Export!N27) -> 2026-03-17 03:31:03.34836 | R27: =IF($D27="","",IF(COUNTIF(DB_Categories_Export!$A:$A,$F27)>0,"OK","INVALID CATEGORY")) -> OK | S27: =IF($D27="","",COUNTIF(DB_Artwork_Sizes_Export!$B:$B,$D27)) -> 4 | T27: =IF($D27="","",IFERROR(INDEX(DB_Artwork_Sizes_Export!$D:$D,MATCH($D27,DB_Artwork_Sizes_Export!$B:$B,0)),"")) -> 4.5" round | U27: =IF($D27="","",IFERROR(INDEX(DB_Artwork_Sizes_Export!$E:$E,MATCH($D27,DB_Artwork_Sizes_Export!$B:$B,0)),"")) -> 500.00 | V27: =IF($D27="","",IFERROR(INDEX(DB_Artwork_Sizes_Export!$F:$F,MATCH($D27,DB_Artwork_Sizes_Export!$B:$B,0)),"")) -> 21.00 | W27: =IF($D27="","",IF($S27>0,"REVIEW_SIZE_PRICING","OK")) -> REVIEW_SIZE_PRICING | AF27: =IF($Y27<>"",$Y27,$E27) -> Hand Painted Wooden Mandala Tray (fillable Round) | AG27: =IF($Z27<>"",$Z27,$F27) -> dot-mandala | AH27: =IF($AG27="","",IFERROR(VLOOKUP($AG27,DB_Categories_Export!$A:$B,2,FALSE()),"INVALID CATEGORY")) -> Dot Mandala Art | AI27: =IF($AA27<>"",$AA27,$H27) -> An exquisite hand-painted wooden round mandala tray, designed to elevate your space with rich heritage and refined artistry. Set against a deep maroon base, intricate layers of radiant orange, green, and gold detailing form a beautifully balanced floral mandala — each element carefully painted by hand. Crafted on a solid wooden base and sealed for durability, this piece is designed as a decorative table accent — perfect for styling on a coffee table, console, or festive setting. Elegant, vibrant, and one-of-a-kind, it brings a touch of artisanal luxury and timeless craftsmanship into your home. | AJ27: =IF($AB27<>"",$AB27,$I27) -> Wood | AK27: =IF($AC27<>"",$AC27,$J27) -> 1100.00 | AL27: =IF($AD27<>"",$AD27,$N27) -> f | AM27: =IF($AE27<>"",$AE27,$O27) -> https://chitrakalaarts-production.up.railway.app/api/images/artworks/art-1771902788998 | AO27: INV-03-01 reviewed: final action NO_CHANGE for artwork-level fields. Suggested Sync Action was NO_CHANGE and current artwork fields/category validate. REVIEW was driven by size-level pricing review flag; defer size-level USD/variant pricing to pricing subtask. No Corrected_* fields needed.
A28: NO_CHANGE | B28: =IF($D28="","",IF(COUNTA($Y28:$AE28)>0,"UPDATE","NO_CHANGE")) -> NO_CHANGE | C28: =IF($D28="","",IF($R28<>"OK","ERROR",IF(OR($E28="", $F28="", $J28=""),"ERROR",IF($W28<>"OK","WARNING","PASS")))) -> WARNING | D28: =IF(DB_Artworks_Export!A28="","",DB_Artworks_Export!A28) -> art-1771903158477 | E28: =IF(DB_Artworks_Export!B28="","",DB_Artworks_Export!B28) -> Luxury Lippan Art Wall Panel | F28: =IF(DB_Artworks_Export!C28="","",DB_Artworks_Export!C28) -> lippan-art | G28: =IF(DB_Artworks_Export!D28="","",DB_Artworks_Export!D28) -> Lippan Art | H28: =IF(DB_Artworks_Export!E28="","",DB_Artworks_Export!E28) -> A harmonious blend of tradition and contemporary luxury — designed to bring texture, light, and artistry into your space. The soft white tones, subtle metallic highlights, and reflective mirror detailing create a sophisticated statement — perfect for modern, minimal, or luxury interiors. Each element is meticulously shaped and placed by hand, making every piece truly one of a kind. Ideal for living rooms, entryways, meditation spaces, or as an elevated festive accent. | I28: =IF(DB_Artworks_Export!F28="","",DB_Artworks_Export!F28) -> Wood, Clay and Mirrors | J28: =IF(DB_Artworks_Export!G28="","",DB_Artworks_Export!G28) -> 8000.00 | K28: =IF(DB_Artworks_Export!H28="","",DB_Artworks_Export!H28) -> 152.00 | ... Q28: =IF(DB_Artworks_Export!N28="","",DB_Artworks_Export!N28) -> 2026-04-28 17:53:57.339945 | R28: =IF($D28="","",IF(COUNTIF(DB_Categories_Export!$A:$A,$F28)>0,"OK","INVALID CATEGORY")) -> OK | S28: =IF($D28="","",COUNTIF(DB_Artwork_Sizes_Export!$B:$B,$D28)) -> 2 | T28: =IF($D28="","",IFERROR(INDEX(DB_Artwork_Sizes_Export!$D:$D,MATCH($D28,DB_Artwork_Sizes_Export!$B:$B,0)),"")) -> 18" X 18" | U28: =IF($D28="","",IFERROR(INDEX(DB_Artwork_Sizes_Export!$E:$E,MATCH($D28,DB_Artwork_Sizes_Export!$B:$B,0)),"")) -> 8000.00 | V28: =IF($D28="","",IFERROR(INDEX(DB_Artwork_Sizes_Export!$F:$F,MATCH($D28,DB_Artwork_Sizes_Export!$B:$B,0)),"")) -> 152.00 | W28: =IF($D28="","",IF($S28>0,"REVIEW_SIZE_PRICING","OK")) -> REVIEW_SIZE_PRICING | AF28: =IF($Y28<>"",$Y28,$E28) -> Luxury Lippan Art Wall Panel | AG28: =IF($Z28<>"",$Z28,$F28) -> lippan-art | AH28: =IF($AG28="","",IFERROR(VLOOKUP($AG28,DB_Categories_Export!$A:$B,2,FALSE()),"INVALID CATEGORY")) -> Lippan Art | AI28: =IF($AA28<>"",$AA28,$H28) -> A harmonious blend of tradition and contemporary luxury — designed to bring texture, light, and artistry into your space. The soft white tones, subtle metallic highlights, and reflective mirror detailing create a sophisticated statement — perfect for modern, minimal, or luxury interiors. Each element is meticulously shaped and placed by hand, making every piece truly one of a kind. Ideal for living rooms, entryways, meditation spaces, or as an elevated festive accent. | AJ28: =IF($AB28<>"",$AB28,$I28) -> Wood, Clay and Mirrors | AK28: =IF($AC28<>"",$AC28,$J28) -> 8000.00 | AL28: =IF($AD28<>"",$AD28,$N28) -> f | AM28: =IF($AE28<>"",$AE28,$O28) -> https://chitrakalaarts-production.up.railway.app/api/images/artworks/art-1771903158477 | AO28: INV-03-01 reviewed: final action NO_CHANGE for artwork-level fields. Suggested Sync Action was NO_CHANGE and current artwork fields/category validate. REVIEW was driven by size-level pricing review flag; defer size-level USD/variant pricing to pricing subtask. No Corrected_* fields needed.
A29: NO_CHANGE | B29: =IF($D29="","",IF(COUNTA($Y29:$AE29)>0,"UPDATE","NO_CHANGE")) -> NO_CHANGE | C29: =IF($D29="","",IF($R29<>"OK","ERROR",IF(OR($E29="", $F29="", $J29=""),"ERROR",IF($W29<>"OK","WARNING","PASS")))) -> WARNING | D29: =IF(DB_Artworks_Export!A29="","",DB_Artworks_Export!A29) -> art-1771903526915 | E29: =IF(DB_Artworks_Export!B29="","",DB_Artworks_Export!B29) -> Handcrafted Mud & Mirror Floral Mandala | F29: =IF(DB_Artworks_Export!C29="","",DB_Artworks_Export!C29) -> lippan-art | G29: =IF(DB_Artworks_Export!D29="","",DB_Artworks_Export!D29) -> Lippan Art | H29: =IF(DB_Artworks_Export!E29="","",DB_Artworks_Export!E29) -> A bold celebration of heritage and artistry, this handcrafted Lippan artwork features an exquisite floral mandala sculpted in raised mud work and adorned with delicate mirror accents. Set against a rich crimson backdrop, the intricate white relief detailing creates a striking contrast, while the central mirror reflects light beautifully, adding depth and dimension. Inspired by the traditional mud and mirror art of Kutch, this piece blends cultural craftsmanship with refined elegance, making it a captivating statement for living rooms, entryways, or festive interiors. | I29: =IF(DB_Artworks_Export!F29="","",DB_Artworks_Export!F29) -> Wood, Clay and Mirrors | J29: =IF(DB_Artworks_Export!G29="","",DB_Artworks_Export!G29) -> 2800.00 | K29: =IF(DB_Artworks_Export!H29="","",DB_Artworks_Export!H29) -> 53.00 | ... Q29: =IF(DB_Artworks_Export!N29="","",DB_Artworks_Export!N29) -> 2026-03-17 03:31:03.334012 | R29: =IF($D29="","",IF(COUNTIF(DB_Categories_Export!$A:$A,$F29)>0,"OK","INVALID CATEGORY")) -> OK | S29: =IF($D29="","",COUNTIF(DB_Artwork_Sizes_Export!$B:$B,$D29)) -> 3 | T29: =IF($D29="","",IFERROR(INDEX(DB_Artwork_Sizes_Export!$D:$D,MATCH($D29,DB_Artwork_Sizes_Export!$B:$B,0)),"")) -> 8"(round) or 8" (square) | U29: =IF($D29="","",IFERROR(INDEX(DB_Artwork_Sizes_Export!$E:$E,MATCH($D29,DB_Artwork_Sizes_Export!$B:$B,0)),"")) -> 1600.00 | V29: =IF($D29="","",IFERROR(INDEX(DB_Artwork_Sizes_Export!$F:$F,MATCH($D29,DB_Artwork_Sizes_Export!$B:$B,0)),"")) -> 53.00 | W29: =IF($D29="","",IF($S29>0,"REVIEW_SIZE_PRICING","OK")) -> REVIEW_SIZE_PRICING | AF29: =IF($Y29<>"",$Y29,$E29) -> Handcrafted Mud & Mirror Floral Mandala | AG29: =IF($Z29<>"",$Z29,$F29) -> lippan-art | AH29: =IF($AG29="","",IFERROR(VLOOKUP($AG29,DB_Categories_Export!$A:$B,2,FALSE()),"INVALID CATEGORY")) -> Lippan Art | AI29: =IF($AA29<>"",$AA29,$H29) -> A bold celebration of heritage and artistry, this handcrafted Lippan artwork features an exquisite floral mandala sculpted in raised mud work and adorned with delicate mirror accents. Set against a rich crimson backdrop, the intricate white relief detailing creates a striking contrast, while the central mirror reflects light beautifully, adding depth and dimension. Inspired by the traditional mud and mirror art of Kutch, this piece blends cultural craftsmanship with refined elegance, making it a captivating statement for living rooms, entryways, or festive interiors. | AJ29: =IF($AB29<>"",$AB29,$I29) -> Wood, Clay and Mirrors | AK29: =IF($AC29<>"",$AC29,$J29) -> 2800.00 | AL29: =IF($AD29<>"",$AD29,$N29) -> f | AM29: =IF($AE29<>"",$AE29,$O29) -> https://chitrakalaarts-production.up.railway.app/api/images/artworks/art-1771903526915 | AO29: INV-03-01 reviewed: final action NO_CHANGE for artwork-level fields. Suggested Sync Action was NO_CHANGE and current artwork fields/category validate. REVIEW was driven by size-level pricing review flag; defer size-level USD/variant pricing to pricing subtask. No Corrected_* fields needed.
A30: UPDATE | B30: =IF($D30="","",IF(COUNTA($Y30:$AE30)>0,"UPDATE","NO_CHANGE")) -> UPDATE | C30: =IF($D30="","",IF($R30<>"OK","ERROR",IF(OR($E30="", $F30="", $J30=""),"ERROR",IF($W30<>"OK","WARNING","PASS")))) -> WARNING | D30: =IF(DB_Artworks_Export!A30="","",DB_Artworks_Export!A30) -> art-1771903835260 | E30: =IF(DB_Artworks_Export!B30="","",DB_Artworks_Export!B30) -> Wooden Coaster Set | F30: =IF(DB_Artworks_Export!C30="","",DB_Artworks_Export!C30) -> dot-mandala | G30: =IF(DB_Artworks_Export!D30="","",DB_Artworks_Export!D30) -> Dot Mandala Art | H30: =IF(DB_Artworks_Export!E30="","",DB_Artworks_Export!E30) -> Elevate your everyday moments with this exquisite set of hand-painted wooden coasters, adorned with intricate dot mandala artistry. Each coaster is carefully detailed with layered patterns of delicate dots, creating a harmonious design that feels both vibrant and meditative. Crafted on sturdy wooden bases and sealed for durability, these coasters are as functional as they are beautiful — protecting your surfaces while adding an artistic touch to your coffee table, dining space, or work desk. No two pieces are exactly alike, making your set truly one of a kind. | I30: =IF(DB_Artworks_Export!F30="","",DB_Artworks_Export!F30) -> wood | J30: =IF(DB_Artworks_Export!G30="","",DB_Artworks_Export!G30) -> 800.00 | K30: =IF(DB_Artworks_Export!H30="","",DB_Artworks_Export!H30) -> 15.00 | ... Q30: =IF(DB_Artworks_Export!N30="","",DB_Artworks_Export!N30) -> 2026-03-22 13:54:44.573696 | R30: =IF($D30="","",IF(COUNTIF(DB_Categories_Export!$A:$A,$F30)>0,"OK","INVALID CATEGORY")) -> OK | S30: =IF($D30="","",COUNTIF(DB_Artwork_Sizes_Export!$B:$B,$D30)) -> 4 | T30: =IF($D30="","",IFERROR(INDEX(DB_Artwork_Sizes_Export!$D:$D,MATCH($D30,DB_Artwork_Sizes_Export!$B:$B,0)),"")) -> 4" (set of 4) | U30: =IF($D30="","",IFERROR(INDEX(DB_Artwork_Sizes_Export!$E:$E,MATCH($D30,DB_Artwork_Sizes_Export!$B:$B,0)),"")) -> 800.00 | V30: =IF($D30="","",IFERROR(INDEX(DB_Artwork_Sizes_Export!$F:$F,MATCH($D30,DB_Artwork_Sizes_Export!$B:$B,0)),"")) -> 15.00 | W30: =IF($D30="","",IF($S30>0,"REVIEW_SIZE_PRICING","OK")) -> REVIEW_SIZE_PRICING | AB30: Wood | AF30: =IF($Y30<>"",$Y30,$E30) -> Wooden Coaster Set | AG30: =IF($Z30<>"",$Z30,$F30) -> dot-mandala | AH30: =IF($AG30="","",IFERROR(VLOOKUP($AG30,DB_Categories_Export!$A:$B,2,FALSE()),"INVALID CATEGORY")) -> Dot Mandala Art | AI30: =IF($AA30<>"",$AA30,$H30) -> Elevate your everyday moments with this exquisite set of hand-painted wooden coasters, adorned with intricate dot mandala artistry. Each coaster is carefully detailed with layered patterns of delicate dots, creating a harmonious design that feels both vibrant and meditative. Crafted on sturdy wooden bases and sealed for durability, these coasters are as functional as they are beautiful — protecting your surfaces while adding an artistic touch to your coffee table, dining space, or work desk. No two pieces are exactly alike, making your set truly one of a kind. | AJ30: =IF($AB30<>"",$AB30,$I30) -> Wood | AK30: =IF($AC30<>"",$AC30,$J30) -> 800.00 | AL30: =IF($AD30<>"",$AD30,$N30) -> f | AM30: =IF($AE30<>"",$AE30,$O30) -> https://chitrakalaarts-production.up.railway.app/api/images/artworks/art-1771903835260
A31: UPDATE | B31: =IF($D31="","",IF(COUNTA($Y31:$AE31)>0,"UPDATE","NO_CHANGE")) -> UPDATE | C31: =IF($D31="","",IF($R31<>"OK","ERROR",IF(OR($E31="", $F31="", $J31=""),"ERROR",IF($W31<>"OK","WARNING","PASS")))) -> WARNING | D31: =IF(DB_Artworks_Export!A31="","",DB_Artworks_Export!A31) -> art-1771904016600 | E31: =IF(DB_Artworks_Export!B31="","",DB_Artworks_Export!B31) -> Heart Shaped Wooden Coaster Set | F31: =IF(DB_Artworks_Export!C31="","",DB_Artworks_Export!C31) -> dot-mandala | G31: =IF(DB_Artworks_Export!D31="","",DB_Artworks_Export!D31) -> Dot Mandala Art | H31: =IF(DB_Artworks_Export!E31="","",DB_Artworks_Export!E31) -> Add a touch of love and artistry to your space with this charming set of heart-shaped wooden coasters, delicately hand-painted in intricate dot mandala patterns. Each piece is thoughtfully crafted with fine detailing and harmonious color layers, creating a design that feels both romantic and refined. Made on durable wooden bases and carefully sealed for protection, these coasters blend beauty with function — perfect for styling your coffee table, bedside, or intimate gatherings. Their heart silhouette makes them a meaningful gift for weddings, anniversaries, housewarmings, or simply to celebrate everyday moments. | I31: =IF(DB_Artworks_Export!F31="","",DB_Artworks_Export!F31) -> wood | J31: =IF(DB_Artworks_Export!G31="","",DB_Artworks_Export!G31) -> 800.00 | K31: =IF(DB_Artworks_Export!H31="","",DB_Artworks_Export!H31) -> 15.00 | ... Q31: =IF(DB_Artworks_Export!N31="","",DB_Artworks_Export!N31) -> 2026-03-17 03:31:03.310965 | R31: =IF($D31="","",IF(COUNTIF(DB_Categories_Export!$A:$A,$F31)>0,"OK","INVALID CATEGORY")) -> OK | S31: =IF($D31="","",COUNTIF(DB_Artwork_Sizes_Export!$B:$B,$D31)) -> 4 | T31: =IF($D31="","",IFERROR(INDEX(DB_Artwork_Sizes_Export!$D:$D,MATCH($D31,DB_Artwork_Sizes_Export!$B:$B,0)),"")) -> 4" (set of 4) | U31: =IF($D31="","",IFERROR(INDEX(DB_Artwork_Sizes_Export!$E:$E,MATCH($D31,DB_Artwork_Sizes_Export!$B:$B,0)),"")) -> 800.00 | V31: =IF($D31="","",IFERROR(INDEX(DB_Artwork_Sizes_Export!$F:$F,MATCH($D31,DB_Artwork_Sizes_Export!$B:$B,0)),"")) -> 15.00 | W31: =IF($D31="","",IF($S31>0,"REVIEW_SIZE_PRICING","OK")) -> REVIEW_SIZE_PRICING | AB31: Wood | AF31: =IF($Y31<>"",$Y31,$E31) -> Heart Shaped Wooden Coaster Set | AG31: =IF($Z31<>"",$Z31,$F31) -> dot-mandala | AH31: =IF($AG31="","",IFERROR(VLOOKUP($AG31,DB_Categories_Export!$A:$B,2,FALSE()),"INVALID CATEGORY")) -> Dot Mandala Art | AI31: =IF($AA31<>"",$AA31,$H31) -> Add a touch of love and artistry to your space with this charming set of heart-shaped wooden coasters, delicately hand-painted in intricate dot mandala patterns. Each piece is thoughtfully crafted with fine detailing and harmonious color layers, creating a design that feels both romantic and refined. Made on durable wooden bases and carefully sealed for protection, these coasters blend beauty with function — perfect for styling your coffee table, bedside, or intimate gatherings. Their heart silhouette makes them a meaningful gift for weddings, anniversaries, housewarmings, or simply to celebrate everyday moments. | AJ31: =IF($AB31<>"",$AB31,$I31) -> Wood | AK31: =IF($AC31<>"",$AC31,$J31) -> 800.00 | AL31: =IF($AD31<>"",$AD31,$N31) -> f | AM31: =IF($AE31<>"",$AE31,$O31) -> https://chitrakalaarts-production.up.railway.app/api/images/artworks/art-1771904016600
A32: NO_CHANGE | B32: =IF($D32="","",IF(COUNTA($Y32:$AE32)>0,"UPDATE","NO_CHANGE")) -> NO_CHANGE | C32: =IF($D32="","",IF($R32<>"OK","ERROR",IF(OR($E32="", $F32="", $J32=""),"ERROR",IF($W32<>"OK","WARNING","PASS")))) -> WARNING | D32: =IF(DB_Artworks_Export!A32="","",DB_Artworks_Export!A32) -> art-1772897507182 | E32: =IF(DB_Artworks_Export!B32="","",DB_Artworks_Export!B32) -> Peach & Ivory Mirror Work Mandala | F32: =IF(DB_Artworks_Export!C32="","",DB_Artworks_Export!C32) -> lippan-art | G32: =IF(DB_Artworks_Export!D32="","",DB_Artworks_Export!D32) -> Lippan Art | H32: =IF(DB_Artworks_Export!E32="","",DB_Artworks_Export!E32) -> Bring timeless elegance and traditional craftsmanship into your home with this exquisite handcrafted Lippan art wall décor. Created on a 24” x 24” panel, this stunning piece features an intricate mandala-inspired design highlighted with delicate mirror work and fine raised detailing. Set against a soft peach background, the symmetrical patterns bloom outward with graceful floral and geometric motifs. Each tiny mirror and hand-sculpted element reflects light beautifully, creating a subtle shimmer that brings the artwork to life. The carefully detailed border frames the central mandala, giving the piece a royal and sophisticated presence. Inspired by traditional Kutchi Lippan mud art of India, this modern interpretation blends heritage craftsmanship with contemporary elegance, making it a perfect statement piece for living rooms, entryways, meditation spaces, or luxury interiors. | I32: =IF(DB_Artworks_Export!F32="","",DB_Artworks_Export!F32) -> Wood, Clay and Mirrors | J32: =IF(DB_Artworks_Export!G32="","",DB_Artworks_Export!G32) -> 8000.00 | K32: =IF(DB_Artworks_Export!H32="","",DB_Artworks_Export!H32) -> 152.00 | ... Q32: =IF(DB_Artworks_Export!N32="","",DB_Artworks_Export!N32) -> 2026-04-28 17:52:33.072909 | R32: =IF($D32="","",IF(COUNTIF(DB_Categories_Export!$A:$A,$F32)>0,"OK","INVALID CATEGORY")) -> OK | S32: =IF($D32="","",COUNTIF(DB_Artwork_Sizes_Export!$B:$B,$D32)) -> 2 | T32: =IF($D32="","",IFERROR(INDEX(DB_Artwork_Sizes_Export!$D:$D,MATCH($D32,DB_Artwork_Sizes_Export!$B:$B,0)),"")) -> 18" X 18" | U32: =IF($D32="","",IFERROR(INDEX(DB_Artwork_Sizes_Export!$E:$E,MATCH($D32,DB_Artwork_Sizes_Export!$B:$B,0)),"")) -> 8000.00 | V32: =IF($D32="","",IFERROR(INDEX(DB_Artwork_Sizes_Export!$F:$F,MATCH($D32,DB_Artwork_Sizes_Export!$B:$B,0)),"")) -> 152.00 | W32: =IF($D32="","",IF($S32>0,"REVIEW_SIZE_PRICING","OK")) -> REVIEW_SIZE_PRICING | AF32: =IF($Y32<>"",$Y32,$E32) -> Peach & Ivory Mirror Work Mandala | AG32: =IF($Z32<>"",$Z32,$F32) -> lippan-art | AH32: =IF($AG32="","",IFERROR(VLOOKUP($AG32,DB_Categories_Export!$A:$B,2,FALSE()),"INVALID CATEGORY")) -> Lippan Art | AI32: =IF($AA32<>"",$AA32,$H32) -> Bring timeless elegance and traditional craftsmanship into your home with this exquisite handcrafted Lippan art wall décor. Created on a 24” x 24” panel, this stunning piece features an intricate mandala-inspired design highlighted with delicate mirror work and fine raised detailing. Set against a soft peach background, the symmetrical patterns bloom outward with graceful floral and geometric motifs. Each tiny mirror and hand-sculpted element reflects light beautifully, creating a subtle shimmer that brings the artwork to life. The carefully detailed border frames the central mandala, giving the piece a royal and sophisticated presence. Inspired by traditional Kutchi Lippan mud art of India, this modern interpretation blends heritage craftsmanship with contemporary elegance, making it a perfect statement piece for living rooms, entryways, meditation spaces, or luxury interiors. | AJ32: =IF($AB32<>"",$AB32,$I32) -> Wood, Clay and Mirrors | AK32: =IF($AC32<>"",$AC32,$J32) -> 8000.00 | AL32: =IF($AD32<>"",$AD32,$N32) -> f | AM32: =IF($AE32<>"",$AE32,$O32) -> https://chitrakalaarts-production.up.railway.app/api/images/artworks/art-1772897507182 | AO32: INV-03-01 reviewed: final action NO_CHANGE for artwork-level fields. Suggested Sync Action was NO_CHANGE and current artwork fields/category validate. REVIEW was driven by size-level pricing review flag; defer size-level USD/variant pricing to pricing subtask. No Corrected_* fields needed.
A33: NO_CHANGE | B33: =IF($D33="","",IF(COUNTA($Y33:$AE33)>0,"UPDATE","NO_CHANGE")) -> NO_CHANGE | C33: =IF($D33="","",IF($R33<>"OK","ERROR",IF(OR($E33="", $F33="", $J33=""),"ERROR",IF($W33<>"OK","WARNING","PASS")))) -> WARNING | D33: =IF(DB_Artworks_Export!A33="","",DB_Artworks_Export!A33) -> art-1772899719136 | E33: =IF(DB_Artworks_Export!B33="","",DB_Artworks_Export!B33) -> Lippan Art Small decorative Squares (set of 5) | F33: =IF(DB_Artworks_Export!C33="","",DB_Artworks_Export!C33) -> lippan-art | G33: =IF(DB_Artworks_Export!D33="","",DB_Artworks_Export!D33) -> Lippan Art | H33: =IF(DB_Artworks_Export!E33="","",DB_Artworks_Export!E33) -> Decorative squares and round in a set of 5 | I33: =IF(DB_Artworks_Export!F33="","",DB_Artworks_Export!F33) -> Wood | J33: =IF(DB_Artworks_Export!G33="","",DB_Artworks_Export!G33) -> 1000.00 | K33: =IF(DB_Artworks_Export!H33="","",DB_Artworks_Export!H33) -> 19.00 | ... Q33: =IF(DB_Artworks_Export!N33="","",DB_Artworks_Export!N33) -> 2026-03-22 13:52:52.683408 | R33: =IF($D33="","",IF(COUNTIF(DB_Categories_Export!$A:$A,$F33)>0,"OK","INVALID CATEGORY")) -> OK | S33: =IF($D33="","",COUNTIF(DB_Artwork_Sizes_Export!$B:$B,$D33)) -> 1 | T33: =IF($D33="","",IFERROR(INDEX(DB_Artwork_Sizes_Export!$D:$D,MATCH($D33,DB_Artwork_Sizes_Export!$B:$B,0)),"")) -> 4" (squares and round) | U33: =IF($D33="","",IFERROR(INDEX(DB_Artwork_Sizes_Export!$E:$E,MATCH($D33,DB_Artwork_Sizes_Export!$B:$B,0)),"")) -> 1000.00 | V33: =IF($D33="","",IFERROR(INDEX(DB_Artwork_Sizes_Export!$F:$F,MATCH($D33,DB_Artwork_Sizes_Export!$B:$B,0)),"")) -> 19.00 | W33: =IF($D33="","",IF($S33>0,"REVIEW_SIZE_PRICING","OK")) -> REVIEW_SIZE_PRICING | AF33: =IF($Y33<>"",$Y33,$E33) -> Lippan Art Small decorative Squares (set of 5) | AG33: =IF($Z33<>"",$Z33,$F33) -> lippan-art | AH33: =IF($AG33="","",IFERROR(VLOOKUP($AG33,DB_Categories_Export!$A:$B,2,FALSE()),"INVALID CATEGORY")) -> Lippan Art | AI33: =IF($AA33<>"",$AA33,$H33) -> Decorative squares and round in a set of 5 | AJ33: =IF($AB33<>"",$AB33,$I33) -> Wood | AK33: =IF($AC33<>"",$AC33,$J33) -> 1000.00 | AL33: =IF($AD33<>"",$AD33,$N33) -> f | AM33: =IF($AE33<>"",$AE33,$O33) -> https://chitrakalaarts-production.up.railway.app/api/images/artworks/art-1772899719136 | AO33: INV-03-01 reviewed: final action NO_CHANGE for artwork-level fields. Suggested Sync Action was NO_CHANGE and current artwork fields/category validate. REVIEW was driven by size-level pricing review flag; defer size-level USD/variant pricing to pricing subtask. No Corrected_* fields needed.
A34: NO_CHANGE | B34: =IF($D34="","",IF(COUNTA($Y34:$AE34)>0,"UPDATE","NO_CHANGE")) -> NO_CHANGE | C34: =IF($D34="","",IF($R34<>"OK","ERROR",IF(OR($E34="", $F34="", $J34=""),"ERROR",IF($W34<>"OK","WARNING","PASS")))) -> WARNING | D34: =IF(DB_Artworks_Export!A34="","",DB_Artworks_Export!A34) -> art-1772942427729 | E34: =IF(DB_Artworks_Export!B34="","",DB_Artworks_Export!B34) -> Hand-Painted Blue & Green Dot Mandala Wall Art | F34: =IF(DB_Artworks_Export!C34="","",DB_Artworks_Export!C34) -> dot-mandala | G34: =IF(DB_Artworks_Export!D34="","",DB_Artworks_Export!D34) -> Dot Mandala Art | H34: =IF(DB_Artworks_Export!E34="","",DB_Artworks_Export!E34) -> Bring harmony, color, and intricate beauty into your space with this hand-painted dot mandala artwork, created with meticulous layers of delicate dots and flowing patterns. This piece features soothing shades of deep blue, teal, and green, accented with subtle gold highlights, forming a mesmerizing mandala that radiates balance and symmetry. Each dot is carefully placed by hand to create a stunning pattern that draws the eye toward the center, symbolizing calm, focus, and unity. The rich color palette and detailed design make it a striking statement piece for living rooms, meditation spaces, yoga studios, or boho-inspired interiors. | I34: =IF(DB_Artworks_Export!F34="","",DB_Artworks_Export!F34) -> Wood | J34: =IF(DB_Artworks_Export!G34="","",DB_Artworks_Export!G34) -> 4000.00 | K34: =IF(DB_Artworks_Export!H34="","",DB_Artworks_Export!H34) -> 76.00 | ... Q34: =IF(DB_Artworks_Export!N34="","",DB_Artworks_Export!N34) -> 2026-03-17 15:17:48.809019 | R34: =IF($D34="","",IF(COUNTIF(DB_Categories_Export!$A:$A,$F34)>0,"OK","INVALID CATEGORY")) -> OK | S34: =IF($D34="","",COUNTIF(DB_Artwork_Sizes_Export!$B:$B,$D34)) -> 1 | T34: =IF($D34="","",IFERROR(INDEX(DB_Artwork_Sizes_Export!$D:$D,MATCH($D34,DB_Artwork_Sizes_Export!$B:$B,0)),"")) -> 12” x 12” | U34: =IF($D34="","",IFERROR(INDEX(DB_Artwork_Sizes_Export!$E:$E,MATCH($D34,DB_Artwork_Sizes_Export!$B:$B,0)),"")) -> 4000.00 | V34: =IF($D34="","",IFERROR(INDEX(DB_Artwork_Sizes_Export!$F:$F,MATCH($D34,DB_Artwork_Sizes_Export!$B:$B,0)),"")) -> 76.00 | W34: =IF($D34="","",IF($S34>0,"REVIEW_SIZE_PRICING","OK")) -> REVIEW_SIZE_PRICING | AF34: =IF($Y34<>"",$Y34,$E34) -> Hand-Painted Blue & Green Dot Mandala Wall Art | AG34: =IF($Z34<>"",$Z34,$F34) -> dot-mandala | AH34: =IF($AG34="","",IFERROR(VLOOKUP($AG34,DB_Categories_Export!$A:$B,2,FALSE()),"INVALID CATEGORY")) -> Dot Mandala Art | AI34: =IF($AA34<>"",$AA34,$H34) -> Bring harmony, color, and intricate beauty into your space with this hand-painted dot mandala artwork, created with meticulous layers of delicate dots and flowing patterns. This piece features soothing shades of deep blue, teal, and green, accented with subtle gold highlights, forming a mesmerizing mandala that radiates balance and symmetry. Each dot is carefully placed by hand to create a stunning pattern that draws the eye toward the center, symbolizing calm, focus, and unity. The rich color palette and detailed design make it a striking statement piece for living rooms, meditation spaces, yoga studios, or boho-inspired interiors. | AJ34: =IF($AB34<>"",$AB34,$I34) -> Wood | AK34: =IF($AC34<>"",$AC34,$J34) -> 4000.00 | AL34: =IF($AD34<>"",$AD34,$N34) -> f | AM34: =IF($AE34<>"",$AE34,$O34) -> https://chitrakalaarts-production.up.railway.app/api/images/artworks/art-1772942427729 | AO34: INV-03-01 reviewed: final action NO_CHANGE for artwork-level fields. Suggested Sync Action was NO_CHANGE and current artwork fields/category validate. REVIEW was driven by size-level pricing review flag; defer size-level USD/variant pricing to pricing subtask. No Corrected_* fields needed.
A35: NO_CHANGE | B35: =IF($D35="","",IF(COUNTA($Y35:$AE35)>0,"UPDATE","NO_CHANGE")) -> NO_CHANGE | C35: =IF($D35="","",IF($R35<>"OK","ERROR",IF(OR($E35="", $F35="", $J35=""),"ERROR",IF($W35<>"OK","WARNING","PASS")))) -> WARNING | D35: =IF(DB_Artworks_Export!A35="","",DB_Artworks_Export!A35) -> art-1772991773037 | E35: =IF(DB_Artworks_Export!B35="","",DB_Artworks_Export!B35) -> Elegant Pink Floral Texture Wall Art – 4 Panel Canvas Set | F35: =IF(DB_Artworks_Export!C35="","",DB_Artworks_Export!C35) -> texture-art | G35: =IF(DB_Artworks_Export!D35="","",DB_Artworks_Export!D35) -> Texture Art | H35: =IF(DB_Artworks_Export!E35="","",DB_Artworks_Export!E35) -> A refined expression of elegance, this hand-painted textured floral artwork unfolds across four graceful panels, forming a continuous composition of soft pink blossoms and delicate botanical stems. Subtle texture and gentle gold accents add depth and sophistication, while the neutral background enhances its timeless beauty. Designed to bring a sense of calm luxury and botanical charm, this piece creates a stunning focal point for living rooms, bedrooms, or serene interior spaces. Details: • Hand-painted textured floral artwork • 4-panel canvas set • Each panel: 24” x 12” • Elegant pink blossoms with subtle gold accents • A sophisticated statement piece for modern interiors ✨ | I35: =IF(DB_Artworks_Export!F35="","",DB_Artworks_Export!F35) -> Canvas, Clay | J35: =IF(DB_Artworks_Export!G35="","",DB_Artworks_Export!G35) -> 25000.00 | K35: =IF(DB_Artworks_Export!H35="","",DB_Artworks_Export!H35) -> 473.00 | ... Q35: =IF(DB_Artworks_Export!N35="","",DB_Artworks_Export!N35) -> 2026-05-10 03:46:19.596409 | R35: =IF($D35="","",IF(COUNTIF(DB_Categories_Export!$A:$A,$F35)>0,"OK","INVALID CATEGORY")) -> OK | S35: =IF($D35="","",COUNTIF(DB_Artwork_Sizes_Export!$B:$B,$D35)) -> 1 | T35: =IF($D35="","",IFERROR(INDEX(DB_Artwork_Sizes_Export!$D:$D,MATCH($D35,DB_Artwork_Sizes_Export!$B:$B,0)),"")) -> Each Panel - 24” x 12” (4 panels) | U35: =IF($D35="","",IFERROR(INDEX(DB_Artwork_Sizes_Export!$E:$E,MATCH($D35,DB_Artwork_Sizes_Export!$B:$B,0)),"")) -> 25000.00 | V35: =IF($D35="","",IFERROR(INDEX(DB_Artwork_Sizes_Export!$F:$F,MATCH($D35,DB_Artwork_Sizes_Export!$B:$B,0)),"")) -> 473.00 | W35: =IF($D35="","",IF($S35>0,"REVIEW_SIZE_PRICING","OK")) -> REVIEW_SIZE_PRICING | AF35: =IF($Y35<>"",$Y35,$E35) -> Elegant Pink Floral Texture Wall Art – 4 Panel Canvas Set | AG35: =IF($Z35<>"",$Z35,$F35) -> texture-art | AH35: =IF($AG35="","",IFERROR(VLOOKUP($AG35,DB_Categories_Export!$A:$B,2,FALSE()),"INVALID CATEGORY")) -> Texture Art | AI35: =IF($AA35<>"",$AA35,$H35) -> A refined expression of elegance, this hand-painted textured floral artwork unfolds across four graceful panels, forming a continuous composition of soft pink blossoms and delicate botanical stems. Subtle texture and gentle gold accents add depth and sophistication, while the neutral background enhances its timeless beauty. Designed to bring a sense of calm luxury and botanical charm, this piece creates a stunning focal point for living rooms, bedrooms, or serene interior spaces. Details: • Hand-painted textured floral artwork • 4-panel canvas set • Each panel: 24” x 12” • Elegant pink blossoms with subtle gold accents • A sophisticated statement piece for modern interiors ✨ | AJ35: =IF($AB35<>"",$AB35,$I35) -> Canvas, Clay | AK35: =IF($AC35<>"",$AC35,$J35) -> 25000.00 | AL35: =IF($AD35<>"",$AD35,$N35) -> t | AM35: =IF($AE35<>"",$AE35,$O35) -> https://chitrakalaarts-production.up.railway.app/api/images/artworks/art-1772991773037 | AO35: INV-03-01 reviewed: final action NO_CHANGE for artwork-level fields. Suggested Sync Action was NO_CHANGE and current artwork fields/category validate. REVIEW was driven by size-level pricing review flag; defer size-level USD/variant pricing to pricing subtask. No Corrected_* fields needed.
A36: NO_CHANGE | B36: =IF($D36="","",IF(COUNTA($Y36:$AE36)>0,"UPDATE","NO_CHANGE")) -> NO_CHANGE | C36: =IF($D36="","",IF($R36<>"OK","ERROR",IF(OR($E36="", $F36="", $J36=""),"ERROR",IF($W36<>"OK","WARNING","PASS")))) -> WARNING | D36: =IF(DB_Artworks_Export!A36="","",DB_Artworks_Export!A36) -> art-1778384480649 | E36: =IF(DB_Artworks_Export!B36="","",DB_Artworks_Export!B36) -> Rhythms of Heritage – Blue Mirror Mosaic Art Work | F36: =IF(DB_Artworks_Export!C36="","",DB_Artworks_Export!C36) -> mirror-mosaic | G36: =IF(DB_Artworks_Export!D36="","",DB_Artworks_Export!D36) -> Mirror Mosaic | H36: =IF(DB_Artworks_Export!E36="","",DB_Artworks_Export!E36) -> A striking fusion of tribal rhythm and contemporary elegance, this handcrafted blue mirror mosaic artwork is inspired by traditional Indian folk motifs arranged in mesmerizing concentric patterns. The deep royal blue tones paired with reflective mirror accents create a captivating visual balance that instantly elevates any space. Every detail is carefully handcrafted, bringing texture, symmetry, and cultural artistry together into a timeless statement piece. Perfect for living rooms, entryways, meditation corners, or modern interiors seeking a touch of heritage and sophistication. | I36: =IF(DB_Artworks_Export!F36="","",DB_Artworks_Export!F36) -> Glass Mirrors Cuttings | J36: =IF(DB_Artworks_Export!G36="","",DB_Artworks_Export!G36) -> 11500.00 | K36: =IF(DB_Artworks_Export!H36="","",DB_Artworks_Export!H36) -> 218.00 | ... Q36: =IF(DB_Artworks_Export!N36="","",DB_Artworks_Export!N36) -> 2026-05-10 03:41:20.877234 | R36: =IF($D36="","",IF(COUNTIF(DB_Categories_Export!$A:$A,$F36)>0,"OK","INVALID CATEGORY")) -> OK | S36: =IF($D36="","",COUNTIF(DB_Artwork_Sizes_Export!$B:$B,$D36)) -> 1 | T36: =IF($D36="","",IFERROR(INDEX(DB_Artwork_Sizes_Export!$D:$D,MATCH($D36,DB_Artwork_Sizes_Export!$B:$B,0)),"")) -> 12"x12" | U36: =IF($D36="","",IFERROR(INDEX(DB_Artwork_Sizes_Export!$E:$E,MATCH($D36,DB_Artwork_Sizes_Export!$B:$B,0)),"")) -> 11500.00 | V36: =IF($D36="","",IFERROR(INDEX(DB_Artwork_Sizes_Export!$F:$F,MATCH($D36,DB_Artwork_Sizes_Export!$B:$B,0)),"")) -> 218.00 | W36: =IF($D36="","",IF($S36>0,"REVIEW_SIZE_PRICING","OK")) -> REVIEW_SIZE_PRICING | AF36: =IF($Y36<>"",$Y36,$E36) -> Rhythms of Heritage – Blue Mirror Mosaic Art Work | AG36: =IF($Z36<>"",$Z36,$F36) -> mirror-mosaic | AH36: =IF($AG36="","",IFERROR(VLOOKUP($AG36,DB_Categories_Export!$A:$B,2,FALSE()),"INVALID CATEGORY")) -> Mirror Mosaic | AI36: =IF($AA36<>"",$AA36,$H36) -> A striking fusion of tribal rhythm and contemporary elegance, this handcrafted blue mirror mosaic artwork is inspired by traditional Indian folk motifs arranged in mesmerizing concentric patterns. The deep royal blue tones paired with reflective mirror accents create a captivating visual balance that instantly elevates any space. Every detail is carefully handcrafted, bringing texture, symmetry, and cultural artistry together into a timeless statement piece. Perfect for living rooms, entryways, meditation corners, or modern interiors seeking a touch of heritage and sophistication. | AJ36: =IF($AB36<>"",$AB36,$I36) -> Glass Mirrors Cuttings | AK36: =IF($AC36<>"",$AC36,$J36) -> 11500.00 | AL36: =IF($AD36<>"",$AD36,$N36) -> t | AM36: =IF($AE36<>"",$AE36,$O36) -> https://chitrakalaarts-production.up.railway.app/api/images/artworks/art-1778384480649 | AO36: INV-03-01 reviewed: final action NO_CHANGE for artwork-level fields. Suggested Sync Action was NO_CHANGE and current artwork fields/category validate. REVIEW was driven by size-level pricing review flag; defer size-level USD/variant pricing to pricing subtask. No Corrected_* fields needed.
A37: NO_CHANGE | B37: =IF($D37="","",IF(COUNTA($Y37:$AE37)>0,"UPDATE","NO_CHANGE")) -> NO_CHANGE | C37: =IF($D37="","",IF($R37<>"OK","ERROR",IF(OR($E37="", $F37="", $J37=""),"ERROR",IF($W37<>"OK","WARNING","PASS")))) -> WARNING | D37: =IF(DB_Artworks_Export!A37="","",DB_Artworks_Export!A37) -> art-1778384550442 | E37: =IF(DB_Artworks_Export!B37="","",DB_Artworks_Export!B37) -> Moonlit Lotus – White Mirror Mosaic Art Work | F37: =IF(DB_Artworks_Export!C37="","",DB_Artworks_Export!C37) -> mirror-mosaic | G37: =IF(DB_Artworks_Export!D37="","",DB_Artworks_Export!D37) -> Mirror Mosaic | H37: =IF(DB_Artworks_Export!E37="","",DB_Artworks_Export!E37) -> Delicate, luminous, and intricately detailed, this white mirror mosaic artwork draws inspiration from blooming lotus patterns and traditional mandala artistry. The soft textured white finish combined with shimmering mirror inlays creates a serene yet luxurious presence, reflecting light beautifully from every angle. Handcrafted with precision, this elegant piece symbolizes harmony, purity, and balance, making it a perfect addition to contemporary, minimal, or spiritual interiors. Its timeless design brings calm sophistication and artistic depth to any wall or décor setting. | I37: =IF(DB_Artworks_Export!F37="","",DB_Artworks_Export!F37) -> Glass Mirrors Cuttings | J37: =IF(DB_Artworks_Export!G37="","",DB_Artworks_Export!G37) -> 13500.00 | K37: =IF(DB_Artworks_Export!H37="","",DB_Artworks_Export!H37) -> 256.00 | ... Q37: =IF(DB_Artworks_Export!N37="","",DB_Artworks_Export!N37) -> 2026-05-10 03:42:30.676559 | R37: =IF($D37="","",IF(COUNTIF(DB_Categories_Export!$A:$A,$F37)>0,"OK","INVALID CATEGORY")) -> OK | S37: =IF($D37="","",COUNTIF(DB_Artwork_Sizes_Export!$B:$B,$D37)) -> 1 | T37: =IF($D37="","",IFERROR(INDEX(DB_Artwork_Sizes_Export!$D:$D,MATCH($D37,DB_Artwork_Sizes_Export!$B:$B,0)),"")) -> 12"x12" | U37: =IF($D37="","",IFERROR(INDEX(DB_Artwork_Sizes_Export!$E:$E,MATCH($D37,DB_Artwork_Sizes_Export!$B:$B,0)),"")) -> 13500.00 | V37: =IF($D37="","",IFERROR(INDEX(DB_Artwork_Sizes_Export!$F:$F,MATCH($D37,DB_Artwork_Sizes_Export!$B:$B,0)),"")) -> 256.00 | W37: =IF($D37="","",IF($S37>0,"REVIEW_SIZE_PRICING","OK")) -> REVIEW_SIZE_PRICING | AF37: =IF($Y37<>"",$Y37,$E37) -> Moonlit Lotus – White Mirror Mosaic Art Work | AG37: =IF($Z37<>"",$Z37,$F37) -> mirror-mosaic | AH37: =IF($AG37="","",IFERROR(VLOOKUP($AG37,DB_Categories_Export!$A:$B,2,FALSE()),"INVALID CATEGORY")) -> Mirror Mosaic | AI37: =IF($AA37<>"",$AA37,$H37) -> Delicate, luminous, and intricately detailed, this white mirror mosaic artwork draws inspiration from blooming lotus patterns and traditional mandala artistry. The soft textured white finish combined with shimmering mirror inlays creates a serene yet luxurious presence, reflecting light beautifully from every angle. Handcrafted with precision, this elegant piece symbolizes harmony, purity, and balance, making it a perfect addition to contemporary, minimal, or spiritual interiors. Its timeless design brings calm sophistication and artistic depth to any wall or décor setting. | AJ37: =IF($AB37<>"",$AB37,$I37) -> Glass Mirrors Cuttings | AK37: =IF($AC37<>"",$AC37,$J37) -> 13500.00 | AL37: =IF($AD37<>"",$AD37,$N37) -> f | AM37: =IF($AE37<>"",$AE37,$O37) -> https://chitrakalaarts-production.up.railway.app/api/images/artworks/art-1778384550442 | AO37: INV-03-01 reviewed: final action NO_CHANGE for artwork-level fields. Suggested Sync Action was NO_CHANGE and current artwork fields/category validate. REVIEW was driven by size-level pricing review flag; defer size-level USD/variant pricing to pricing subtask. No Corrected_* fields needed.
B38: =IF($D38="","",IF(COUNTA($Y38:$AE38)>0,"UPDATE","NO_CHANGE")) | C38: =IF($D38="","",IF($R38<>"OK","ERROR",IF(OR($E38="", $F38="", $J38=""),"ERROR",IF($W38<>"OK","WARNING","PASS")))) | D38: =IF(DB_Artworks_Export!A38="","",DB_Artworks_Export!A38) | E38: =IF(DB_Artworks_Export!B38="","",DB_Artworks_Export!B38) | F38: =IF(DB_Artworks_Export!C38="","",DB_Artworks_Export!C38) | G38: =IF(DB_Artworks_Export!D38="","",DB_Artworks_Export!D38) | H38: =IF(DB_Artworks_Export!E38="","",DB_Artworks_Export!E38) | I38: =IF(DB_Artworks_Export!F38="","",DB_Artworks_Export!F38) | J38: =IF(DB_Artworks_Export!G38="","",DB_Artworks_Export!G38) | K38: =IF(DB_Artworks_Export!H38="","",DB_Artworks_Export!H38) | ... Q38: =IF(DB_Artworks_Export!N38="","",DB_Artworks_Export!N38) | R38: =IF($D38="","",IF(COUNTIF(DB_Categories_Export!$A:$A,$F38)>0,"OK","INVALID CATEGORY")) | S38: =IF($D38="","",COUNTIF(DB_Artwork_Sizes_Export!$B:$B,$D38)) | T38: =IF($D38="","",IFERROR(INDEX(DB_Artwork_Sizes_Export!$D:$D,MATCH($D38,DB_Artwork_Sizes_Export!$B:$B,0)),"")) | U38: =IF($D38="","",IFERROR(INDEX(DB_Artwork_Sizes_Export!$E:$E,MATCH($D38,DB_Artwork_Sizes_Export!$B:$B,0)),"")) | V38: =IF($D38="","",IFERROR(INDEX(DB_Artwork_Sizes_Export!$F:$F,MATCH($D38,DB_Artwork_Sizes_Export!$B:$B,0)),"")) | W38: =IF($D38="","",IF($S38>0,"REVIEW_SIZE_PRICING","OK")) | AF38: =IF($Y38<>"",$Y38,$E38) | AG38: =IF($Z38<>"",$Z38,$F38) | AH38: =IF($AG38="","",IFERROR(VLOOKUP($AG38,DB_Categories_Export!$A:$B,2,FALSE()),"INVALID CATEGORY")) | AI38: =IF($AA38<>"",$AA38,$H38) | AJ38: =IF($AB38<>"",$AB38,$I38) | AK38: =IF($AC38<>"",$AC38,$J38) | AL38: =IF($AD38<>"",$AD38,$N38) | AM38: =IF($AE38<>"",$AE38,$O38)
B39: =IF($D39="","",IF(COUNTA($Y39:$AE39)>0,"UPDATE","NO_CHANGE")) | C39: =IF($D39="","",IF($R39<>"OK","ERROR",IF(OR($E39="", $F39="", $J39=""),"ERROR",IF($W39<>"OK","WARNING","PASS")))) | D39: =IF(DB_Artworks_Export!A39="","",DB_Artworks_Export!A39) | E39: =IF(DB_Artworks_Export!B39="","",DB_Artworks_Export!B39) | F39: =IF(DB_Artworks_Export!C39="","",DB_Artworks_Export!C39) | G39: =IF(DB_Artworks_Export!D39="","",DB_Artworks_Export!D39) | H39: =IF(DB_Artworks_Export!E39="","",DB_Artworks_Export!E39) | I39: =IF(DB_Artworks_Export!F39="","",DB_Artworks_Export!F39) | J39: =IF(DB_Artworks_Export!G39="","",DB_Artworks_Export!G39) | K39: =IF(DB_Artworks_Export!H39="","",DB_Artworks_Export!H39) | ... Q39: =IF(DB_Artworks_Export!N39="","",DB_Artworks_Export!N39) | R39: =IF($D39="","",IF(COUNTIF(DB_Categories_Export!$A:$A,$F39)>0,"OK","INVALID CATEGORY")) | S39: =IF($D39="","",COUNTIF(DB_Artwork_Sizes_Export!$B:$B,$D39)) | T39: =IF($D39="","",IFERROR(INDEX(DB_Artwork_Sizes_Export!$D:$D,MATCH($D39,DB_Artwork_Sizes_Export!$B:$B,0)),"")) | U39: =IF($D39="","",IFERROR(INDEX(DB_Artwork_Sizes_Export!$E:$E,MATCH($D39,DB_Artwork_Sizes_Export!$B:$B,0)),"")) | V39: =IF($D39="","",IFERROR(INDEX(DB_Artwork_Sizes_Export!$F:$F,MATCH($D39,DB_Artwork_Sizes_Export!$B:$B,0)),"")) | W39: =IF($D39="","",IF($S39>0,"REVIEW_SIZE_PRICING","OK")) | AF39: =IF($Y39<>"",$Y39,$E39) | AG39: =IF($Z39<>"",$Z39,$F39) | AH39: =IF($AG39="","",IFERROR(VLOOKUP($AG39,DB_Categories_Export!$A:$B,2,FALSE()),"INVALID CATEGORY")) | AI39: =IF($AA39<>"",$AA39,$H39) | AJ39: =IF($AB39<>"",$AB39,$I39) | AK39: =IF($AC39<>"",$AC39,$J39) | AL39: =IF($AD39<>"",$AD39,$N39) | AM39: =IF($AE39<>"",$AE39,$O39)
B40: =IF($D40="","",IF(COUNTA($Y40:$AE40)>0,"UPDATE","NO_CHANGE")) | C40: =IF($D40="","",IF($R40<>"OK","ERROR",IF(OR($E40="", $F40="", $J40=""),"ERROR",IF($W40<>"OK","WARNING","PASS")))) | D40: =IF(DB_Artworks_Export!A40="","",DB_Artworks_Export!A40) | E40: =IF(DB_Artworks_Export!B40="","",DB_Artworks_Export!B40) | F40: =IF(DB_Artworks_Export!C40="","",DB_Artworks_Export!C40) | G40: =IF(DB_Artworks_Export!D40="","",DB_Artworks_Export!D40) | H40: =IF(DB_Artworks_Export!E40="","",DB_Artworks_Export!E40) | I40: =IF(DB_Artworks_Export!F40="","",DB_Artworks_Export!F40) | J40: =IF(DB_Artworks_Export!G40="","",DB_Artworks_Export!G40) | K40: =IF(DB_Artworks_Export!H40="","",DB_Artworks_Export!H40) | ... Q40: =IF(DB_Artworks_Export!N40="","",DB_Artworks_Export!N40) | R40: =IF($D40="","",IF(COUNTIF(DB_Categories_Export!$A:$A,$F40)>0,"OK","INVALID CATEGORY")) | S40: =IF($D40="","",COUNTIF(DB_Artwork_Sizes_Export!$B:$B,$D40)) | T40: =IF($D40="","",IFERROR(INDEX(DB_Artwork_Sizes_Export!$D:$D,MATCH($D40,DB_Artwork_Sizes_Export!$B:$B,0)),"")) | U40: =IF($D40="","",IFERROR(INDEX(DB_Artwork_Sizes_Export!$E:$E,MATCH($D40,DB_Artwork_Sizes_Export!$B:$B,0)),"")) | V40: =IF($D40="","",IFERROR(INDEX(DB_Artwork_Sizes_Export!$F:$F,MATCH($D40,DB_Artwork_Sizes_Export!$B:$B,0)),"")) | W40: =IF($D40="","",IF($S40>0,"REVIEW_SIZE_PRICING","OK")) | AF40: =IF($Y40<>"",$Y40,$E40) | AG40: =IF($Z40<>"",$Z40,$F40) | AH40: =IF($AG40="","",IFERROR(VLOOKUP($AG40,DB_Categories_Export!$A:$B,2,FALSE()),"INVALID CATEGORY")) | AI40: =IF($AA40<>"",$AA40,$H40) | AJ40: =IF($AB40<>"",$AB40,$I40) | AK40: =IF($AC40<>"",$AC40,$J40) | AL40: =IF($AD40<>"",$AD40,$N40) | AM40: =IF($AE40<>"",$AE40,$O40)
B41: =IF($D41="","",IF(COUNTA($Y41:$AE41)>0,"UPDATE","NO_CHANGE")) | C41: =IF($D41="","",IF($R41<>"OK","ERROR",IF(OR($E41="", $F41="", $J41=""),"ERROR",IF($W41<>"OK","WARNING","PASS")))) | D41: =IF(DB_Artworks_Export!A41="","",DB_Artworks_Export!A41) | E41: =IF(DB_Artworks_Export!B41="","",DB_Artworks_Export!B41) | F41: =IF(DB_Artworks_Export!C41="","",DB_Artworks_Export!C41) | G41: =IF(DB_Artworks_Export!D41="","",DB_Artworks_Export!D41) | H41: =IF(DB_Artworks_Export!E41="","",DB_Artworks_Export!E41) | I41: =IF(DB_Artworks_Export!F41="","",DB_Artworks_Export!F41) | J41: =IF(DB_Artworks_Export!G41="","",DB_Artworks_Export!G41) | K41: =IF(DB_Artworks_Export!H41="","",DB_Artworks_Export!H41) | ... Q41: =IF(DB_Artworks_Export!N41="","",DB_Artworks_Export!N41) | R41: =IF($D41="","",IF(COUNTIF(DB_Categories_Export!$A:$A,$F41)>0,"OK","INVALID CATEGORY")) | S41: =IF($D41="","",COUNTIF(DB_Artwork_Sizes_Export!$B:$B,$D41)) | T41: =IF($D41="","",IFERROR(INDEX(DB_Artwork_Sizes_Export!$D:$D,MATCH($D41,DB_Artwork_Sizes_Export!$B:$B,0)),"")) | U41: =IF($D41="","",IFERROR(INDEX(DB_Artwork_Sizes_Export!$E:$E,MATCH($D41,DB_Artwork_Sizes_Export!$B:$B,0)),"")) | V41: =IF($D41="","",IFERROR(INDEX(DB_Artwork_Sizes_Export!$F:$F,MATCH($D41,DB_Artwork_Sizes_Export!$B:$B,0)),"")) | W41: =IF($D41="","",IF($S41>0,"REVIEW_SIZE_PRICING","OK")) | AF41: =IF($Y41<>"",$Y41,$E41) | AG41: =IF($Z41<>"",$Z41,$F41) | AH41: =IF($AG41="","",IFERROR(VLOOKUP($AG41,DB_Categories_Export!$A:$B,2,FALSE()),"INVALID CATEGORY")) | AI41: =IF($AA41<>"",$AA41,$H41) | AJ41: =IF($AB41<>"",$AB41,$I41) | AK41: =IF($AC41<>"",$AC41,$J41) | AL41: =IF($AD41<>"",$AD41,$N41) | AM41: =IF($AE41<>"",$AE41,$O41)
B42: =IF($D42="","",IF(COUNTA($Y42:$AE42)>0,"UPDATE","NO_CHANGE")) | C42: =IF($D42="","",IF($R42<>"OK","ERROR",IF(OR($E42="", $F42="", $J42=""),"ERROR",IF($W42<>"OK","WARNING","PASS")))) | D42: =IF(DB_Artworks_Export!A42="","",DB_Artworks_Export!A42) | E42: =IF(DB_Artworks_Export!B42="","",DB_Artworks_Export!B42) | F42: =IF(DB_Artworks_Export!C42="","",DB_Artworks_Export!C42) | G42: =IF(DB_Artworks_Export!D42="","",DB_Artworks_Export!D42) | H42: =IF(DB_Artworks_Export!E42="","",DB_Artworks_Export!E42) | I42: =IF(DB_Artworks_Export!F42="","",DB_Artworks_Export!F42) | J42: =IF(DB_Artworks_Export!G42="","",DB_Artworks_Export!G42) | K42: =IF(DB_Artworks_Export!H42="","",DB_Artworks_Export!H42) | ... Q42: =IF(DB_Artworks_Export!N42="","",DB_Artworks_Export!N42) | R42: =IF($D42="","",IF(COUNTIF(DB_Categories_Export!$A:$A,$F42)>0,"OK","INVALID CATEGORY")) | S42: =IF($D42="","",COUNTIF(DB_Artwork_Sizes_Export!$B:$B,$D42)) | T42: =IF($D42="","",IFERROR(INDEX(DB_Artwork_Sizes_Export!$D:$D,MATCH($D42,DB_Artwork_Sizes_Export!$B:$B,0)),"")) | U42: =IF($D42="","",IFERROR(INDEX(DB_Artwork_Sizes_Export!$E:$E,MATCH($D42,DB_Artwork_Sizes_Export!$B:$B,0)),"")) | V42: =IF($D42="","",IFERROR(INDEX(DB_Artwork_Sizes_Export!$F:$F,MATCH($D42,DB_Artwork_Sizes_Export!$B:$B,0)),"")) | W42: =IF($D42="","",IF($S42>0,"REVIEW_SIZE_PRICING","OK")) | AF42: =IF($Y42<>"",$Y42,$E42) | AG42: =IF($Z42<>"",$Z42,$F42) | AH42: =IF($AG42="","",IFERROR(VLOOKUP($AG42,DB_Categories_Export!$A:$B,2,FALSE()),"INVALID CATEGORY")) | AI42: =IF($AA42<>"",$AA42,$H42) | AJ42: =IF($AB42<>"",$AB42,$I42) | AK42: =IF($AC42<>"",$AC42,$J42) | AL42: =IF($AD42<>"",$AD42,$N42) | AM42: =IF($AE42<>"",$AE42,$O42)
B43: =IF($D43="","",IF(COUNTA($Y43:$AE43)>0,"UPDATE","NO_CHANGE")) | C43: =IF($D43="","",IF($R43<>"OK","ERROR",IF(OR($E43="", $F43="", $J43=""),"ERROR",IF($W43<>"OK","WARNING","PASS")))) | D43: =IF(DB_Artworks_Export!A43="","",DB_Artworks_Export!A43) | E43: =IF(DB_Artworks_Export!B43="","",DB_Artworks_Export!B43) | F43: =IF(DB_Artworks_Export!C43="","",DB_Artworks_Export!C43) | G43: =IF(DB_Artworks_Export!D43="","",DB_Artworks_Export!D43) | H43: =IF(DB_Artworks_Export!E43="","",DB_Artworks_Export!E43) | I43: =IF(DB_Artworks_Export!F43="","",DB_Artworks_Export!F43) | J43: =IF(DB_Artworks_Export!G43="","",DB_Artworks_Export!G43) | K43: =IF(DB_Artworks_Export!H43="","",DB_Artworks_Export!H43) | ... Q43: =IF(DB_Artworks_Export!N43="","",DB_Artworks_Export!N43) | R43: =IF($D43="","",IF(COUNTIF(DB_Categories_Export!$A:$A,$F43)>0,"OK","INVALID CATEGORY")) | S43: =IF($D43="","",COUNTIF(DB_Artwork_Sizes_Export!$B:$B,$D43)) | T43: =IF($D43="","",IFERROR(INDEX(DB_Artwork_Sizes_Export!$D:$D,MATCH($D43,DB_Artwork_Sizes_Export!$B:$B,0)),"")) | U43: =IF($D43="","",IFERROR(INDEX(DB_Artwork_Sizes_Export!$E:$E,MATCH($D43,DB_Artwork_Sizes_Export!$B:$B,0)),"")) | V43: =IF($D43="","",IFERROR(INDEX(DB_Artwork_Sizes_Export!$F:$F,MATCH($D43,DB_Artwork_Sizes_Export!$B:$B,0)),"")) | W43: =IF($D43="","",IF($S43>0,"REVIEW_SIZE_PRICING","OK")) | AF43: =IF($Y43<>"",$Y43,$E43) | AG43: =IF($Z43<>"",$Z43,$F43) | AH43: =IF($AG43="","",IFERROR(VLOOKUP($AG43,DB_Categories_Export!$A:$B,2,FALSE()),"INVALID CATEGORY")) | AI43: =IF($AA43<>"",$AA43,$H43) | AJ43: =IF($AB43<>"",$AB43,$I43) | AK43: =IF($AC43<>"",$AC43,$J43) | AL43: =IF($AD43<>"",$AD43,$N43) | AM43: =IF($AE43<>"",$AE43,$O43)
B44: =IF($D44="","",IF(COUNTA($Y44:$AE44)>0,"UPDATE","NO_CHANGE")) | C44: =IF($D44="","",IF($R44<>"OK","ERROR",IF(OR($E44="", $F44="", $J44=""),"ERROR",IF($W44<>"OK","WARNING","PASS")))) | D44: =IF(DB_Artworks_Export!A44="","",DB_Artworks_Export!A44) | E44: =IF(DB_Artworks_Export!B44="","",DB_Artworks_Export!B44) | F44: =IF(DB_Artworks_Export!C44="","",DB_Artworks_Export!C44) | G44: =IF(DB_Artworks_Export!D44="","",DB_Artworks_Export!D44) | H44: =IF(DB_Artworks_Export!E44="","",DB_Artworks_Export!E44) | I44: =IF(DB_Artworks_Export!F44="","",DB_Artworks_Export!F44) | J44: =IF(DB_Artworks_Export!G44="","",DB_Artworks_Export!G44) | K44: =IF(DB_Artworks_Export!H44="","",DB_Artworks_Export!H44) | ... Q44: =IF(DB_Artworks_Export!N44="","",DB_Artworks_Export!N44) | R44: =IF($D44="","",IF(COUNTIF(DB_Categories_Export!$A:$A,$F44)>0,"OK","INVALID CATEGORY")) | S44: =IF($D44="","",COUNTIF(DB_Artwork_Sizes_Export!$B:$B,$D44)) | T44: =IF($D44="","",IFERROR(INDEX(DB_Artwork_Sizes_Export!$D:$D,MATCH($D44,DB_Artwork_Sizes_Export!$B:$B,0)),"")) | U44: =IF($D44="","",IFERROR(INDEX(DB_Artwork_Sizes_Export!$E:$E,MATCH($D44,DB_Artwork_Sizes_Export!$B:$B,0)),"")) | V44: =IF($D44="","",IFERROR(INDEX(DB_Artwork_Sizes_Export!$F:$F,MATCH($D44,DB_Artwork_Sizes_Export!$B:$B,0)),"")) | W44: =IF($D44="","",IF($S44>0,"REVIEW_SIZE_PRICING","OK")) | AF44: =IF($Y44<>"",$Y44,$E44) | AG44: =IF($Z44<>"",$Z44,$F44) | AH44: =IF($AG44="","",IFERROR(VLOOKUP($AG44,DB_Categories_Export!$A:$B,2,FALSE()),"INVALID CATEGORY")) | AI44: =IF($AA44<>"",$AA44,$H44) | AJ44: =IF($AB44<>"",$AB44,$I44) | AK44: =IF($AC44<>"",$AC44,$J44) | AL44: =IF($AD44<>"",$AD44,$N44) | AM44: =IF($AE44<>"",$AE44,$O44)
B45: =IF($D45="","",IF(COUNTA($Y45:$AE45)>0,"UPDATE","NO_CHANGE")) | C45: =IF($D45="","",IF($R45<>"OK","ERROR",IF(OR($E45="", $F45="", $J45=""),"ERROR",IF($W45<>"OK","WARNING","PASS")))) | D45: =IF(DB_Artworks_Export!A45="","",DB_Artworks_Export!A45) | E45: =IF(DB_Artworks_Export!B45="","",DB_Artworks_Export!B45) | F45: =IF(DB_Artworks_Export!C45="","",DB_Artworks_Export!C45) | G45: =IF(DB_Artworks_Export!D45="","",DB_Artworks_Export!D45) | H45: =IF(DB_Artworks_Export!E45="","",DB_Artworks_Export!E45) | I45: =IF(DB_Artworks_Export!F45="","",DB_Artworks_Export!F45) | J45: =IF(DB_Artworks_Export!G45="","",DB_Artworks_Export!G45) | K45: =IF(DB_Artworks_Export!H45="","",DB_Artworks_Export!H45) | ... Q45: =IF(DB_Artworks_Export!N45="","",DB_Artworks_Export!N45) | R45: =IF($D45="","",IF(COUNTIF(DB_Categories_Export!$A:$A,$F45)>0,"OK","INVALID CATEGORY")) | S45: =IF($D45="","",COUNTIF(DB_Artwork_Sizes_Export!$B:$B,$D45)) | T45: =IF($D45="","",IFERROR(INDEX(DB_Artwork_Sizes_Export!$D:$D,MATCH($D45,DB_Artwork_Sizes_Export!$B:$B,0)),"")) | U45: =IF($D45="","",IFERROR(INDEX(DB_Artwork_Sizes_Export!$E:$E,MATCH($D45,DB_Artwork_Sizes_Export!$B:$B,0)),"")) | V45: =IF($D45="","",IFERROR(INDEX(DB_Artwork_Sizes_Export!$F:$F,MATCH($D45,DB_Artwork_Sizes_Export!$B:$B,0)),"")) | W45: =IF($D45="","",IF($S45>0,"REVIEW_SIZE_PRICING","OK")) | AF45: =IF($Y45<>"",$Y45,$E45) | AG45: =IF($Z45<>"",$Z45,$F45) | AH45: =IF($AG45="","",IFERROR(VLOOKUP($AG45,DB_Categories_Export!$A:$B,2,FALSE()),"INVALID CATEGORY")) | AI45: =IF($AA45<>"",$AA45,$H45) | AJ45: =IF($AB45<>"",$AB45,$I45) | AK45: =IF($AC45<>"",$AC45,$J45) | AL45: =IF($AD45<>"",$AD45,$N45) | AM45: =IF($AE45<>"",$AE45,$O45)
B46: =IF($D46="","",IF(COUNTA($Y46:$AE46)>0,"UPDATE","NO_CHANGE")) | C46: =IF($D46="","",IF($R46<>"OK","ERROR",IF(OR($E46="", $F46="", $J46=""),"ERROR",IF($W46<>"OK","WARNING","PASS")))) | D46: =IF(DB_Artworks_Export!A46="","",DB_Artworks_Export!A46) | E46: =IF(DB_Artworks_Export!B46="","",DB_Artworks_Export!B46) | F46: =IF(DB_Artworks_Export!C46="","",DB_Artworks_Export!C46) | G46: =IF(DB_Artworks_Export!D46="","",DB_Artworks_Export!D46) | H46: =IF(DB_Artworks_Export!E46="","",DB_Artworks_Export!E46) | I46: =IF(DB_Artworks_Export!F46="","",DB_Artworks_Export!F46) | J46: =IF(DB_Artworks_Export!G46="","",DB_Artworks_Export!G46) | K46: =IF(DB_Artworks_Export!H46="","",DB_Artworks_Export!H46) | ... Q46: =IF(DB_Artworks_Export!N46="","",DB_Artworks_Export!N46) | R46: =IF($D46="","",IF(COUNTIF(DB_Categories_Export!$A:$A,$F46)>0,"OK","INVALID CATEGORY")) | S46: =IF($D46="","",COUNTIF(DB_Artwork_Sizes_Export!$B:$B,$D46)) | T46: =IF($D46="","",IFERROR(INDEX(DB_Artwork_Sizes_Export!$D:$D,MATCH($D46,DB_Artwork_Sizes_Export!$B:$B,0)),"")) | U46: =IF($D46="","",IFERROR(INDEX(DB_Artwork_Sizes_Export!$E:$E,MATCH($D46,DB_Artwork_Sizes_Export!$B:$B,0)),"")) | V46: =IF($D46="","",IFERROR(INDEX(DB_Artwork_Sizes_Export!$F:$F,MATCH($D46,DB_Artwork_Sizes_Export!$B:$B,0)),"")) | W46: =IF($D46="","",IF($S46>0,"REVIEW_SIZE_PRICING","OK")) | AF46: =IF($Y46<>"",$Y46,$E46) | AG46: =IF($Z46<>"",$Z46,$F46) | AH46: =IF($AG46="","",IFERROR(VLOOKUP($AG46,DB_Categories_Export!$A:$B,2,FALSE()),"INVALID CATEGORY")) | AI46: =IF($AA46<>"",$AA46,$H46) | AJ46: =IF($AB46<>"",$AB46,$I46) | AK46: =IF($AC46<>"",$AC46,$J46) | AL46: =IF($AD46<>"",$AD46,$N46) | AM46: =IF($AE46<>"",$AE46,$O46)
B47: =IF($D47="","",IF(COUNTA($Y47:$AE47)>0,"UPDATE","NO_CHANGE")) | C47: =IF($D47="","",IF($R47<>"OK","ERROR",IF(OR($E47="", $F47="", $J47=""),"ERROR",IF($W47<>"OK","WARNING","PASS")))) | D47: =IF(DB_Artworks_Export!A47="","",DB_Artworks_Export!A47) | E47: =IF(DB_Artworks_Export!B47="","",DB_Artworks_Export!B47) | F47: =IF(DB_Artworks_Export!C47="","",DB_Artworks_Export!C47) | G47: =IF(DB_Artworks_Export!D47="","",DB_Artworks_Export!D47) | H47: =IF(DB_Artworks_Export!E47="","",DB_Artworks_Export!E47) | I47: =IF(DB_Artworks_Export!F47="","",DB_Artworks_Export!F47) | J47: =IF(DB_Artworks_Export!G47="","",DB_Artworks_Export!G47) | K47: =IF(DB_Artworks_Export!H47="","",DB_Artworks_Export!H47) | ... Q47: =IF(DB_Artworks_Export!N47="","",DB_Artworks_Export!N47) | R47: =IF($D47="","",IF(COUNTIF(DB_Categories_Export!$A:$A,$F47)>0,"OK","INVALID CATEGORY")) | S47: =IF($D47="","",COUNTIF(DB_Artwork_Sizes_Export!$B:$B,$D47)) | T47: =IF($D47="","",IFERROR(INDEX(DB_Artwork_Sizes_Export!$D:$D,MATCH($D47,DB_Artwork_Sizes_Export!$B:$B,0)),"")) | U47: =IF($D47="","",IFERROR(INDEX(DB_Artwork_Sizes_Export!$E:$E,MATCH($D47,DB_Artwork_Sizes_Export!$B:$B,0)),"")) | V47: =IF($D47="","",IFERROR(INDEX(DB_Artwork_Sizes_Export!$F:$F,MATCH($D47,DB_Artwork_Sizes_Export!$B:$B,0)),"")) | W47: =IF($D47="","",IF($S47>0,"REVIEW_SIZE_PRICING","OK")) | AF47: =IF($Y47<>"",$Y47,$E47) | AG47: =IF($Z47<>"",$Z47,$F47) | AH47: =IF($AG47="","",IFERROR(VLOOKUP($AG47,DB_Categories_Export!$A:$B,2,FALSE()),"INVALID CATEGORY")) | AI47: =IF($AA47<>"",$AA47,$H47) | AJ47: =IF($AB47<>"",$AB47,$I47) | AK47: =IF($AC47<>"",$AC47,$J47) | AL47: =IF($AD47<>"",$AD47,$N47) | AM47: =IF($AE47<>"",$AE47,$O47)
B48: =IF($D48="","",IF(COUNTA($Y48:$AE48)>0,"UPDATE","NO_CHANGE")) | C48: =IF($D48="","",IF($R48<>"OK","ERROR",IF(OR($E48="", $F48="", $J48=""),"ERROR",IF($W48<>"OK","WARNING","PASS")))) | D48: =IF(DB_Artworks_Export!A48="","",DB_Artworks_Export!A48) | E48: =IF(DB_Artworks_Export!B48="","",DB_Artworks_Export!B48) | F48: =IF(DB_Artworks_Export!C48="","",DB_Artworks_Export!C48) | G48: =IF(DB_Artworks_Export!D48="","",DB_Artworks_Export!D48) | H48: =IF(DB_Artworks_Export!E48="","",DB_Artworks_Export!E48) | I48: =IF(DB_Artworks_Export!F48="","",DB_Artworks_Export!F48) | J48: =IF(DB_Artworks_Export!G48="","",DB_Artworks_Export!G48) | K48: =IF(DB_Artworks_Export!H48="","",DB_Artworks_Export!H48) | ... Q48: =IF(DB_Artworks_Export!N48="","",DB_Artworks_Export!N48) | R48: =IF($D48="","",IF(COUNTIF(DB_Categories_Export!$A:$A,$F48)>0,"OK","INVALID CATEGORY")) | S48: =IF($D48="","",COUNTIF(DB_Artwork_Sizes_Export!$B:$B,$D48)) | T48: =IF($D48="","",IFERROR(INDEX(DB_Artwork_Sizes_Export!$D:$D,MATCH($D48,DB_Artwork_Sizes_Export!$B:$B,0)),"")) | U48: =IF($D48="","",IFERROR(INDEX(DB_Artwork_Sizes_Export!$E:$E,MATCH($D48,DB_Artwork_Sizes_Export!$B:$B,0)),"")) | V48: =IF($D48="","",IFERROR(INDEX(DB_Artwork_Sizes_Export!$F:$F,MATCH($D48,DB_Artwork_Sizes_Export!$B:$B,0)),"")) | W48: =IF($D48="","",IF($S48>0,"REVIEW_SIZE_PRICING","OK")) | AF48: =IF($Y48<>"",$Y48,$E48) | AG48: =IF($Z48<>"",$Z48,$F48) | AH48: =IF($AG48="","",IFERROR(VLOOKUP($AG48,DB_Categories_Export!$A:$B,2,FALSE()),"INVALID CATEGORY")) | AI48: =IF($AA48<>"",$AA48,$H48) | AJ48: =IF($AB48<>"",$AB48,$I48) | AK48: =IF($AC48<>"",$AC48,$J48) | AL48: =IF($AD48<>"",$AD48,$N48) | AM48: =IF($AE48<>"",$AE48,$O48)
B49: =IF($D49="","",IF(COUNTA($Y49:$AE49)>0,"UPDATE","NO_CHANGE")) | C49: =IF($D49="","",IF($R49<>"OK","ERROR",IF(OR($E49="", $F49="", $J49=""),"ERROR",IF($W49<>"OK","WARNING","PASS")))) | D49: =IF(DB_Artworks_Export!A49="","",DB_Artworks_Export!A49) | E49: =IF(DB_Artworks_Export!B49="","",DB_Artworks_Export!B49) | F49: =IF(DB_Artworks_Export!C49="","",DB_Artworks_Export!C49) | G49: =IF(DB_Artworks_Export!D49="","",DB_Artworks_Export!D49) | H49: =IF(DB_Artworks_Export!E49="","",DB_Artworks_Export!E49) | I49: =IF(DB_Artworks_Export!F49="","",DB_Artworks_Export!F49) | J49: =IF(DB_Artworks_Export!G49="","",DB_Artworks_Export!G49) | K49: =IF(DB_Artworks_Export!H49="","",DB_Artworks_Export!H49) | ... Q49: =IF(DB_Artworks_Export!N49="","",DB_Artworks_Export!N49) | R49: =IF($D49="","",IF(COUNTIF(DB_Categories_Export!$A:$A,$F49)>0,"OK","INVALID CATEGORY")) | S49: =IF($D49="","",COUNTIF(DB_Artwork_Sizes_Export!$B:$B,$D49)) | T49: =IF($D49="","",IFERROR(INDEX(DB_Artwork_Sizes_Export!$D:$D,MATCH($D49,DB_Artwork_Sizes_Export!$B:$B,0)),"")) | U49: =IF($D49="","",IFERROR(INDEX(DB_Artwork_Sizes_Export!$E:$E,MATCH($D49,DB_Artwork_Sizes_Export!$B:$B,0)),"")) | V49: =IF($D49="","",IFERROR(INDEX(DB_Artwork_Sizes_Export!$F:$F,MATCH($D49,DB_Artwork_Sizes_Export!$B:$B,0)),"")) | W49: =IF($D49="","",IF($S49>0,"REVIEW_SIZE_PRICING","OK")) | AF49: =IF($Y49<>"",$Y49,$E49) | AG49: =IF($Z49<>"",$Z49,$F49) | AH49: =IF($AG49="","",IFERROR(VLOOKUP($AG49,DB_Categories_Export!$A:$B,2,FALSE()),"INVALID CATEGORY")) | AI49: =IF($AA49<>"",$AA49,$H49) | AJ49: =IF($AB49<>"",$AB49,$I49) | AK49: =IF($AC49<>"",$AC49,$J49) | AL49: =IF($AD49<>"",$AD49,$N49) | AM49: =IF($AE49<>"",$AE49,$O49)
... B500: =IF($D500="","",IF(COUNTA($Y500:$AE500)>0,"UPDATE","NO_CHANGE")) | C500: =IF($D500="","",IF($R500<>"OK","ERROR",IF(OR($E500="", $F500="", $J500=""),"ERROR",IF($W500<>"OK","WARNING","PASS")))) | D500: =IF(DB_Artworks_Export!A500="","",DB_Artworks_Export!A500) | E500: =IF(DB_Artworks_Export!B500="","",DB_Artworks_Export!B500) | F500: =IF(DB_Artworks_Export!C500="","",DB_Artworks_Export!C500) | G500: =IF(DB_Artworks_Export!D500="","",DB_Artworks_Export!D500) | H500: =IF(DB_Artworks_Export!E500="","",DB_Artworks_Export!E500) | I500: =IF(DB_Artworks_Export!F500="","",DB_Artworks_Export!F500) | J500: =IF(DB_Artworks_Export!G500="","",DB_Artworks_Export!G500) | K500: =IF(DB_Artworks_Export!H500="","",DB_Artworks_Export!H500) | ... Q500: =IF(DB_Artworks_Export!N500="","",DB_Artworks_Export!N500) | R500: =IF($D500="","",IF(COUNTIF(DB_Categories_Export!$A:$A,$F500)>0,"OK","INVALID CATEGORY")) | S500: =IF($D500="","",COUNTIF(DB_Artwork_Sizes_Export!$B:$B,$D500)) | T500: =IF($D500="","",IFERROR(INDEX(DB_Artwork_Sizes_Export!$D:$D,MATCH($D500,DB_Artwork_Sizes_Export!$B:$B,0)),"")) | U500: =IF($D500="","",IFERROR(INDEX(DB_Artwork_Sizes_Export!$E:$E,MATCH($D500,DB_Artwork_Sizes_Export!$B:$B,0)),"")) | V500: =IF($D500="","",IFERROR(INDEX(DB_Artwork_Sizes_Export!$F:$F,MATCH($D500,DB_Artwork_Sizes_Export!$B:$B,0)),"")) | W500: =IF($D500="","",IF($S500>0,"REVIEW_SIZE_PRICING","OK")) | AF500: =IF($Y500<>"",$Y500,$E500) | AG500: =IF($Z500<>"",$Z500,$F500) | AH500: =IF($AG500="","",IFERROR(VLOOKUP($AG500,DB_Categories_Export!$A:$B,2,FALSE()),"INVALID CATEGORY")) | AI500: =IF($AA500<>"",$AA500,$H500) | AJ500: =IF($AB500<>"",$AB500,$I500) | AK500: =IF($AC500<>"",$AC500,$J500) | AL500: =IF($AD500<>"",$AD500,$N500) | AM500: =IF($AE500<>"",$AE500,$O500)

Sheet Potential_Issues_Auto
A1: Artwork ID | B1: Title | C1: Validation Status | D1: Category Validation | E1: Size Review Flag | F1: Issue Summary | G1: Needs Reconciliation Log? | H1: Suggested Issue Type | I1: Suggested Severity | J1: Suggested Sync Action
A2: art-1770419263598 | B2: Eternal Glow – Mandala of Light and Balance | C2: WARNING | D2: OK | E2: REVIEW_SIZE_PRICING | F2: Has size variants; Review warning | G2: YES | H2: Size Price Review | I2: MEDIUM | J2: REVIEW
A3: art-1770419392051 | B3: Blush Serenity Mandala – Art in Soft Pink & White | C3: PASS | D3: OK | E3: OK | G3: NO
A4: art-1770419460850 | B4: Mandala in Blue and Peach | C4: WARNING | D4: OK | E4: REVIEW_SIZE_PRICING | F4: Has size variants; Review warning | G4: YES | H4: Size Price Review | I4: MEDIUM | J4: REVIEW
A5: art-1770771760544 | B5: Hand-Painted Keychains (set of 5) | C5: WARNING | D5: OK | E5: REVIEW_SIZE_PRICING | F5: Has size variants; Review warning | G5: YES | H5: Size Price Review | I5: MEDIUM | J5: REVIEW
A6: art-1770771970545 | B6: Mango-Shaped storage box | C6: WARNING | D6: OK | E6: REVIEW_SIZE_PRICING | F6: Has size variants; Review warning | G6: YES | H6: Size Price Review | I6: MEDIUM | J6: REVIEW
A7: art-1770775579766 | B7: Intricate Floral Mandala Art in Green & Gold | C7: WARNING | D7: OK | E7: REVIEW_SIZE_PRICING | F7: Has size variants; Review warning | G7: YES | H7: Size Price Review | I7: MEDIUM | J7: REVIEW
A8: art-1770777152872 | B8: Sacred Geometry in Clay & Mirror | C8: WARNING | D8: OK | E8: REVIEW_SIZE_PRICING | F8: Has size variants; Review warning | G8: YES | H8: Size Price Review | I8: MEDIUM | J8: REVIEW
A9: art-1770778179564 | B9: Colorful Mandala KeyChain Holder | C9: PASS | D9: OK | E9: OK | G9: NO
A10: art-1770778384172 | B10: Butterfly Set (3 pieces) | C10: WARNING | D10: OK | E10: REVIEW_SIZE_PRICING | F10: Has size variants; Review warning | G10: YES | H10: Size Price Review | I10: MEDIUM | J10: REVIEW
A11: art-1770778509370 | B11: Coaster Set (4 pieces) | C11: WARNING | D11: OK | E11: REVIEW_SIZE_PRICING | F11: Has size variants; Review warning | G11: YES | H11: Size Price Review | I11: MEDIUM | J11: REVIEW
A12: art-1770778808201 | B12: Serene Teal Floral Mandala Box | C12: PASS | D12: OK | E12: OK | G12: NO
A13: art-1770779054676 | B13: Floral Rectangular Wooden Storage Box | C13: WARNING | D13: OK | E13: REVIEW_SIZE_PRICING | F13: Has size variants; Review warning | G13: YES | H13: Size Price Review | I13: MEDIUM | J13: REVIEW
A14: art-1770779208267 | B14: Rectangular Wooden box | C14: WARNING | D14: OK | E14: REVIEW_SIZE_PRICING | F14: Has size variants; Review warning | G14: YES | H14: Size Price Review | I14: MEDIUM | J14: REVIEW
A15: art-1770933508740 | B15: Canvas Bag - Birds | C15: WARNING | D15: OK | E15: REVIEW_SIZE_PRICING | F15: Has size variants; Review warning | G15: YES | H15: Size Price Review | I15: MEDIUM | J15: REVIEW
A16: art-1771030266195 | B16: Hand-Painted Floral Saree | C16: WARNING | D16: OK | E16: REVIEW_SIZE_PRICING | F16: Has size variants; Review warning | G16: YES | H16: Size Price Review | I16: MEDIUM | J16: REVIEW
A17: art-1771030980031 | B17: Midnight Plum Hand-Painted Floral Saree | C17: WARNING | D17: OK | E17: REVIEW_SIZE_PRICING | F17: Has size variants; Review warning | G17: YES | H17: Size Price Review | I17: MEDIUM | J17: REVIEW
A18: art-1771031213758 | B18: Soft Romantic Pastel Drape with Lavender Blooms | C18: WARNING | D18: OK | E18: REVIEW_SIZE_PRICING | F18: Has size variants; Review warning | G18: YES | H18: Size Price Review | I18: MEDIUM | J18: REVIEW
A19: art-1771033398626 | B19: Teal & Blue Boho Decorative Round | C19: WARNING | D19: OK | E19: REVIEW_SIZE_PRICING | F19: Has size variants; Review warning | G19: YES | H19: Size Price Review | I19: MEDIUM | J19: REVIEW
A20: art-1771101879286 | B20: Decorative Serving Board | C20: WARNING | D20: OK | E20: REVIEW_SIZE_PRICING | F20: Has size variants; Review warning | G20: YES | H20: Size Price Review | I20: MEDIUM | J20: REVIEW
A21: art-1771101978525 | B21: Hand painted Tussar Saree | C21: WARNING | D21: OK | E21: REVIEW_SIZE_PRICING | F21: Has size variants; Review warning | G21: YES | H21: Size Price Review | I21: MEDIUM | J21: REVIEW
A22: art-1771102194181 | B22: Coaster Set (4 pieces) | C22: WARNING | D22: OK | E22: REVIEW_SIZE_PRICING | F22: Has size variants; Review warning | G22: YES | H22: Size Price Review | I22: MEDIUM | J22: REVIEW
A23: art-1771102482592 | B23: Decorative Wall Panel | C23: WARNING | D23: OK | E23: REVIEW_SIZE_PRICING | F23: Has size variants; Review warning | G23: YES | H23: Size Price Review | I23: MEDIUM | J23: REVIEW
A24: art-1771102578812 | B24: Decorative Wall Panel | C24: WARNING | D24: OK | E24: REVIEW_SIZE_PRICING | F24: Has size variants; Review warning | G24: YES | H24: Size Price Review | I24: MEDIUM | J24: REVIEW
... A37: art-1778384550442 | B37: Moonlit Lotus – White Mirror Mosaic Art Work | C37: WARNING | D37: OK | E37: REVIEW_SIZE_PRICING | F37: Has size variants; Review warning | G37: YES | H37: Size Price Review | I37: MEDIUM | J37: REVIEW
A50: =Inventory_Master!D50 | B50: =Inventory_Master!E50 | C50: =Inventory_Master!C50 | D50: =Inventory_Master!R50 | E50: =Inventory_Master!W50 | F50: =IF($A50="","",TRIM(_xludf.textjoin("; ",TRUE(),IF(Inventory_Master!R50<>"OK","Invalid category",""),IF(Inventory_Master!J50="","Missing price_inr",""),IF(Inventory_Master!O50="","Missing image",""),IF(Inventory_Master!S50>0,"Has size variants",""),IF(Inventory_Master!C50="ERROR","Validation error",""),IF(Inventory_Master!C50="WARNING","Review warning","")))) | G50: =IF($F50="","NO","YES") -> NO | H50: =IF($A50="","",IF(Inventory_Master!R50<>"OK","Invalid Category",IF(Inventory_Master!J50="","Missing Price",IF(Inventory_Master!O50="","Missing Image",IF(Inventory_Master!S50>0,"Size Price Review",IF(Inventory_Master!C50="ERROR","Validation Error","")))))) | I50: =IF($G50="NO","",IF(OR($H50="Invalid Category",$H50="Missing Price",$H50="Validation Error"),"HIGH","MEDIUM")) | J50: =IF($G50="NO","",IF($H50="Size Price Review","REVIEW",IF($H50="Missing Image","REVIEW","REVIEW")))
A51: =Inventory_Master!D51 | B51: =Inventory_Master!E51 | C51: =Inventory_Master!C51 | D51: =Inventory_Master!R51 | E51: =Inventory_Master!W51 | F51: =IF($A51="","",TRIM(_xludf.textjoin("; ",TRUE(),IF(Inventory_Master!R51<>"OK","Invalid category",""),IF(Inventory_Master!J51="","Missing price_inr",""),IF(Inventory_Master!O51="","Missing image",""),IF(Inventory_Master!S51>0,"Has size variants",""),IF(Inventory_Master!C51="ERROR","Validation error",""),IF(Inventory_Master!C51="WARNING","Review warning","")))) | G51: =IF($F51="","NO","YES") -> NO | H51: =IF($A51="","",IF(Inventory_Master!R51<>"OK","Invalid Category",IF(Inventory_Master!J51="","Missing Price",IF(Inventory_Master!O51="","Missing Image",IF(Inventory_Master!S51>0,"Size Price Review",IF(Inventory_Master!C51="ERROR","Validation Error","")))))) | I51: =IF($G51="NO","",IF(OR($H51="Invalid Category",$H51="Missing Price",$H51="Validation Error"),"HIGH","MEDIUM")) | J51: =IF($G51="NO","",IF($H51="Size Price Review","REVIEW",IF($H51="Missing Image","REVIEW","REVIEW")))
A52: =Inventory_Master!D52 | B52: =Inventory_Master!E52 | C52: =Inventory_Master!C52 | D52: =Inventory_Master!R52 | E52: =Inventory_Master!W52 | F52: =IF($A52="","",TRIM(_xludf.textjoin("; ",TRUE(),IF(Inventory_Master!R52<>"OK","Invalid category",""),IF(Inventory_Master!J52="","Missing price_inr",""),IF(Inventory_Master!O52="","Missing image",""),IF(Inventory_Master!S52>0,"Has size variants",""),IF(Inventory_Master!C52="ERROR","Validation error",""),IF(Inventory_Master!C52="WARNING","Review warning","")))) | G52: =IF($F52="","NO","YES") -> NO | H52: =IF($A52="","",IF(Inventory_Master!R52<>"OK","Invalid Category",IF(Inventory_Master!J52="","Missing Price",IF(Inventory_Master!O52="","Missing Image",IF(Inventory_Master!S52>0,"Size Price Review",IF(Inventory_Master!C52="ERROR","Validation Error","")))))) | I52: =IF($G52="NO","",IF(OR($H52="Invalid Category",$H52="Missing Price",$H52="Validation Error"),"HIGH","MEDIUM")) | J52: =IF($G52="NO","",IF($H52="Size Price Review","REVIEW",IF($H52="Missing Image","REVIEW","REVIEW")))
A53: =Inventory_Master!D53 | B53: =Inventory_Master!E53 | C53: =Inventory_Master!C53 | D53: =Inventory_Master!R53 | E53: =Inventory_Master!W53 | F53: =IF($A53="","",TRIM(_xludf.textjoin("; ",TRUE(),IF(Inventory_Master!R53<>"OK","Invalid category",""),IF(Inventory_Master!J53="","Missing price_inr",""),IF(Inventory_Master!O53="","Missing image",""),IF(Inventory_Master!S53>0,"Has size variants",""),IF(Inventory_Master!C53="ERROR","Validation error",""),IF(Inventory_Master!C53="WARNING","Review warning","")))) | G53: =IF($F53="","NO","YES") -> NO | H53: =IF($A53="","",IF(Inventory_Master!R53<>"OK","Invalid Category",IF(Inventory_Master!J53="","Missing Price",IF(Inventory_Master!O53="","Missing Image",IF(Inventory_Master!S53>0,"Size Price Review",IF(Inventory_Master!C53="ERROR","Validation Error","")))))) | I53: =IF($G53="NO","",IF(OR($H53="Invalid Category",$H53="Missing Price",$H53="Validation Error"),"HIGH","MEDIUM")) | J53: =IF($G53="NO","",IF($H53="Size Price Review","REVIEW",IF($H53="Missing Image","REVIEW","REVIEW")))
A54: =Inventory_Master!D54 | B54: =Inventory_Master!E54 | C54: =Inventory_Master!C54 | D54: =Inventory_Master!R54 | E54: =Inventory_Master!W54 | F54: =IF($A54="","",TRIM(_xludf.textjoin("; ",TRUE(),IF(Inventory_Master!R54<>"OK","Invalid category",""),IF(Inventory_Master!J54="","Missing price_inr",""),IF(Inventory_Master!O54="","Missing image",""),IF(Inventory_Master!S54>0,"Has size variants",""),IF(Inventory_Master!C54="ERROR","Validation error",""),IF(Inventory_Master!C54="WARNING","Review warning","")))) | G54: =IF($F54="","NO","YES") -> NO | H54: =IF($A54="","",IF(Inventory_Master!R54<>"OK","Invalid Category",IF(Inventory_Master!J54="","Missing Price",IF(Inventory_Master!O54="","Missing Image",IF(Inventory_Master!S54>0,"Size Price Review",IF(Inventory_Master!C54="ERROR","Validation Error","")))))) | I54: =IF($G54="NO","",IF(OR($H54="Invalid Category",$H54="Missing Price",$H54="Validation Error"),"HIGH","MEDIUM")) | J54: =IF($G54="NO","",IF($H54="Size Price Review","REVIEW",IF($H54="Missing Image","REVIEW","REVIEW")))
A55: =Inventory_Master!D55 | B55: =Inventory_Master!E55 | C55: =Inventory_Master!C55 | D55: =Inventory_Master!R55 | E55: =Inventory_Master!W55 | F55: =IF($A55="","",TRIM(_xludf.textjoin("; ",TRUE(),IF(Inventory_Master!R55<>"OK","Invalid category",""),IF(Inventory_Master!J55="","Missing price_inr",""),IF(Inventory_Master!O55="","Missing image",""),IF(Inventory_Master!S55>0,"Has size variants",""),IF(Inventory_Master!C55="ERROR","Validation error",""),IF(Inventory_Master!C55="WARNING","Review warning","")))) | G55: =IF($F55="","NO","YES") -> NO | H55: =IF($A55="","",IF(Inventory_Master!R55<>"OK","Invalid Category",IF(Inventory_Master!J55="","Missing Price",IF(Inventory_Master!O55="","Missing Image",IF(Inventory_Master!S55>0,"Size Price Review",IF(Inventory_Master!C55="ERROR","Validation Error","")))))) | I55: =IF($G55="NO","",IF(OR($H55="Invalid Category",$H55="Missing Price",$H55="Validation Error"),"HIGH","MEDIUM")) | J55: =IF($G55="NO","",IF($H55="Size Price Review","REVIEW",IF($H55="Missing Image","REVIEW","REVIEW")))
A56: =Inventory_Master!D56 | B56: =Inventory_Master!E56 | C56: =Inventory_Master!C56 | D56: =Inventory_Master!R56 | E56: =Inventory_Master!W56 | F56: =IF($A56="","",TRIM(_xludf.textjoin("; ",TRUE(),IF(Inventory_Master!R56<>"OK","Invalid category",""),IF(Inventory_Master!J56="","Missing price_inr",""),IF(Inventory_Master!O56="","Missing image",""),IF(Inventory_Master!S56>0,"Has size variants",""),IF(Inventory_Master!C56="ERROR","Validation error",""),IF(Inventory_Master!C56="WARNING","Review warning","")))) | G56: =IF($F56="","NO","YES") -> NO | H56: =IF($A56="","",IF(Inventory_Master!R56<>"OK","Invalid Category",IF(Inventory_Master!J56="","Missing Price",IF(Inventory_Master!O56="","Missing Image",IF(Inventory_Master!S56>0,"Size Price Review",IF(Inventory_Master!C56="ERROR","Validation Error","")))))) | I56: =IF($G56="NO","",IF(OR($H56="Invalid Category",$H56="Missing Price",$H56="Validation Error"),"HIGH","MEDIUM")) | J56: =IF($G56="NO","",IF($H56="Size Price Review","REVIEW",IF($H56="Missing Image","REVIEW","REVIEW")))
A57: =Inventory_Master!D57 | B57: =Inventory_Master!E57 | C57: =Inventory_Master!C57 | D57: =Inventory_Master!R57 | E57: =Inventory_Master!W57 | F57: =IF($A57="","",TRIM(_xludf.textjoin("; ",TRUE(),IF(Inventory_Master!R57<>"OK","Invalid category",""),IF(Inventory_Master!J57="","Missing price_inr",""),IF(Inventory_Master!O57="","Missing image",""),IF(Inventory_Master!S57>0,"Has size variants",""),IF(Inventory_Master!C57="ERROR","Validation error",""),IF(Inventory_Master!C57="WARNING","Review warning","")))) | G57: =IF($F57="","NO","YES") -> NO | H57: =IF($A57="","",IF(Inventory_Master!R57<>"OK","Invalid Category",IF(Inventory_Master!J57="","Missing Price",IF(Inventory_Master!O57="","Missing Image",IF(Inventory_Master!S57>0,"Size Price Review",IF(Inventory_Master!C57="ERROR","Validation Error","")))))) | I57: =IF($G57="NO","",IF(OR($H57="Invalid Category",$H57="Missing Price",$H57="Validation Error"),"HIGH","MEDIUM")) | J57: =IF($G57="NO","",IF($H57="Size Price Review","REVIEW",IF($H57="Missing Image","REVIEW","REVIEW")))
A58: =Inventory_Master!D58 | B58: =Inventory_Master!E58 | C58: =Inventory_Master!C58 | D58: =Inventory_Master!R58 | E58: =Inventory_Master!W58 | F58: =IF($A58="","",TRIM(_xludf.textjoin("; ",TRUE(),IF(Inventory_Master!R58<>"OK","Invalid category",""),IF(Inventory_Master!J58="","Missing price_inr",""),IF(Inventory_Master!O58="","Missing image",""),IF(Inventory_Master!S58>0,"Has size variants",""),IF(Inventory_Master!C58="ERROR","Validation error",""),IF(Inventory_Master!C58="WARNING","Review warning","")))) | G58: =IF($F58="","NO","YES") -> NO | H58: =IF($A58="","",IF(Inventory_Master!R58<>"OK","Invalid Category",IF(Inventory_Master!J58="","Missing Price",IF(Inventory_Master!O58="","Missing Image",IF(Inventory_Master!S58>0,"Size Price Review",IF(Inventory_Master!C58="ERROR","Validation Error","")))))) | I58: =IF($G58="NO","",IF(OR($H58="Invalid Category",$H58="Missing Price",$H58="Validation Error"),"HIGH","MEDIUM")) | J58: =IF($G58="NO","",IF($H58="Size Price Review","REVIEW",IF($H58="Missing Image","REVIEW","REVIEW")))
A59: =Inventory_Master!D59 | B59: =Inventory_Master!E59 | C59: =Inventory_Master!C59 | D59: =Inventory_Master!R59 | E59: =Inventory_Master!W59 | F59: =IF($A59="","",TRIM(_xludf.textjoin("; ",TRUE(),IF(Inventory_Master!R59<>"OK","Invalid category",""),IF(Inventory_Master!J59="","Missing price_inr",""),IF(Inventory_Master!O59="","Missing image",""),IF(Inventory_Master!S59>0,"Has size variants",""),IF(Inventory_Master!C59="ERROR","Validation error",""),IF(Inventory_Master!C59="WARNING","Review warning","")))) | G59: =IF($F59="","NO","YES") -> NO | H59: =IF($A59="","",IF(Inventory_Master!R59<>"OK","Invalid Category",IF(Inventory_Master!J59="","Missing Price",IF(Inventory_Master!O59="","Missing Image",IF(Inventory_Master!S59>0,"Size Price Review",IF(Inventory_Master!C59="ERROR","Validation Error","")))))) | I59: =IF($G59="NO","",IF(OR($H59="Invalid Category",$H59="Missing Price",$H59="Validation Error"),"HIGH","MEDIUM")) | J59: =IF($G59="NO","",IF($H59="Size Price Review","REVIEW",IF($H59="Missing Image","REVIEW","REVIEW")))
A60: =Inventory_Master!D60 | B60: =Inventory_Master!E60 | C60: =Inventory_Master!C60 | D60: =Inventory_Master!R60 | E60: =Inventory_Master!W60 | F60: =IF($A60="","",TRIM(_xludf.textjoin("; ",TRUE(),IF(Inventory_Master!R60<>"OK","Invalid category",""),IF(Inventory_Master!J60="","Missing price_inr",""),IF(Inventory_Master!O60="","Missing image",""),IF(Inventory_Master!S60>0,"Has size variants",""),IF(Inventory_Master!C60="ERROR","Validation error",""),IF(Inventory_Master!C60="WARNING","Review warning","")))) | G60: =IF($F60="","NO","YES") -> NO | H60: =IF($A60="","",IF(Inventory_Master!R60<>"OK","Invalid Category",IF(Inventory_Master!J60="","Missing Price",IF(Inventory_Master!O60="","Missing Image",IF(Inventory_Master!S60>0,"Size Price Review",IF(Inventory_Master!C60="ERROR","Validation Error","")))))) | I60: =IF($G60="NO","",IF(OR($H60="Invalid Category",$H60="Missing Price",$H60="Validation Error"),"HIGH","MEDIUM")) | J60: =IF($G60="NO","",IF($H60="Size Price Review","REVIEW",IF($H60="Missing Image","REVIEW","REVIEW")))
A61: =Inventory_Master!D61 | B61: =Inventory_Master!E61 | C61: =Inventory_Master!C61 | D61: =Inventory_Master!R61 | E61: =Inventory_Master!W61 | F61: =IF($A61="","",TRIM(_xludf.textjoin("; ",TRUE(),IF(Inventory_Master!R61<>"OK","Invalid category",""),IF(Inventory_Master!J61="","Missing price_inr",""),IF(Inventory_Master!O61="","Missing image",""),IF(Inventory_Master!S61>0,"Has size variants",""),IF(Inventory_Master!C61="ERROR","Validation error",""),IF(Inventory_Master!C61="WARNING","Review warning","")))) | G61: =IF($F61="","NO","YES") -> NO | H61: =IF($A61="","",IF(Inventory_Master!R61<>"OK","Invalid Category",IF(Inventory_Master!J61="","Missing Price",IF(Inventory_Master!O61="","Missing Image",IF(Inventory_Master!S61>0,"Size Price Review",IF(Inventory_Master!C61="ERROR","Validation Error","")))))) | I61: =IF($G61="NO","",IF(OR($H61="Invalid Category",$H61="Missing Price",$H61="Validation Error"),"HIGH","MEDIUM")) | J61: =IF($G61="NO","",IF($H61="Size Price Review","REVIEW",IF($H61="Missing Image","REVIEW","REVIEW")))
... A500: =Inventory_Master!D500 | B500: =Inventory_Master!E500 | C500: =Inventory_Master!C500 | D500: =Inventory_Master!R500 | E500: =Inventory_Master!W500 | F500: =IF($A500="","",TRIM(_xludf.textjoin("; ",TRUE(),IF(Inventory_Master!R500<>"OK","Invalid category",""),IF(Inventory_Master!J500="","Missing price_inr",""),IF(Inventory_Master!O500="","Missing image",""),IF(Inventory_Master!S500>0,"Has size variants",""),IF(Inventory_Master!C500="ERROR","Validation error",""),IF(Inventory_Master!C500="WARNING","Review warning","")))) | G500: =IF($F500="","NO","YES") -> NO | H500: =IF($A500="","",IF(Inventory_Master!R500<>"OK","Invalid Category",IF(Inventory_Master!J500="","Missing Price",IF(Inventory_Master!O500="","Missing Image",IF(Inventory_Master!S500>0,"Size Price Review",IF(Inventory_Master!C500="ERROR","Validation Error","")))))) | I500: =IF($G500="NO","",IF(OR($H500="Invalid Category",$H500="Missing Price",$H500="Validation Error"),"HIGH","MEDIUM")) | J500: =IF($G500="NO","",IF($H500="Size Price Review","REVIEW",IF($H500="Missing Image","REVIEW","REVIEW")))

Sheet Reconciliation_Report
A1: Issue ID | B1: Issue Type | C1: Severity | D1: Source Tab | E1: Artwork ID | F1: Inventory SKU | G1: Title | H1: Field Name | I1: DB Value | J1: Inventory/Proposed Value | K1: Expected Value | L1: Recommended Action | M1: Sync Action | N1: Assigned To | O1: Resolved? | P1: Resolution Notes
A2: REC-001 | B2: Size Price Review | C2: MEDIUM | D2: DB_Artwork_Sizes_Export | E2: art-1770419263598 | G2: Eternal Glow – Mandala of Light and Balance | H2: price_inr / size price | I2: Base price: ₹4,000 | Size prices: 12"×12" ₹4,500 | 18"×18" ₹7,500 | 24"×24" ₹10,000 | 36"×36" ₹20,000 | J2: Size-specific pricing supersedes base price | K2: Base price should reflect minimum/smallest size or be updated to match size table | L2: Confirm which size corresponds to the ₹4,000 base price, or update base to ₹4,500 (12" min size). Verify USD pricing across all sizes — all show ₹76 regardless of size. | M2: REVIEW | N2: Sanjay | O2: NO
A3: REC-002 | B3: Size Price Review | C3: HIGH | D3: DB_Artwork_Sizes_Export | E3: art-1770419263598 | G3: Eternal Glow – Mandala of Light and Balance | H3: price_usd (all size rows) | I3: All 4 size rows show price_usd = 76.00 regardless of size | J3: USD price should scale with INR size price using FX rate (92.40) × multiplier (1.75) | K3: 12" ≈ $85 | 18" ≈ $142 | 24" ≈ $190 | 36" ≈ $379 | L3: All size-variant USD prices appear frozen at the base-artwork USD value. Confirm whether USD is recalculated per size or inherited. Fix for all affected artworks. | M3: REVIEW | N3: Sanjay | O3: NO | P3: Affects most artworks with size variants — systemic issue
A4: REC-003 | B4: Size Price Review | C4: MEDIUM | D4: DB_Artwork_Sizes_Export | E4: art-1770419460850 | G4: Mandala in Blue and Peach | H4: price_inr / size variants | I4: Base price: ₹4,000 | Only 1 size row: 12" @ ₹3,500 | J4: Description mentions 18"=₹6,200, 24"=₹8,000, 36"=₹16,000 | K4: 3 additional size rows for 18", 24", 36" per description | L4: Add missing size rows for 18", 24", and 36" per pricing in description. Also note base price (₹4,000) is higher than the listed 12" size price (₹3,500) — confirm correct base. | M4: UPDATE | N4: Sanjay | O4: NO | P4: Pricing found in description text: '18" - Rs 6200 24" Rs 8000 36" Rs 16000'
A5: REC-004 | B5: Size Price Review | C5: MEDIUM | D5: DB_Artwork_Sizes_Export | E5: art-1770778509370 | G5: Coaster Set (4 pieces) | H5: price_inr (description vs size rows) | I5: Base: ₹800 | Description mentions 'Set of 4 - Rs 750, Set of 6 - Rs 1000' | Size rows: Set of 4 = ₹800, Set of 6 = ₹1,000 | J5: Description says set of 4 = ₹750 but DB/size rows show ₹800 | K5: Confirm correct set-of-4 price: ₹750 or ₹800 | L5: Reconcile description pricing (₹750 for set of 4) against size table and base price (₹800). Update description or price to match actual. | M5: REVIEW | N5: Sanjay | O5: NO
A6: REC-005 | B6: Size Price Review | C6: MEDIUM | D6: DB_Artwork_Sizes_Export | E6: art-1770779208267 | G6: Rectangular Wooden box | H6: price_inr / size variants | I6: Base: ₹700 | 2 size rows: single (₹700), set of 3 (₹1,900) | price_usd both = 13.00 | J6: USD for 'set of 3' should be higher than single | K6: Set of 3 USD ≈ ₹1,900 / 92.4 × 1.75 ≈ $36 | L6: Update USD price for the 'set of 3' size variant (currently frozen at $13 same as single). Confirm INR pricing is correct. | M6: REVIEW | N6: Sanjay | O6: NO
A7: REC-006 | B7: Size Price Review | C7: MEDIUM | D7: DB_Artwork_Sizes_Export | E7: art-1770933508740 | G7: Canvas Bag - Birds | H7: price_inr / size variants | I7: Base: ₹2,000 | Size rows: 10"×10" = ₹1,500, 12"×12" = ₹2,000 | Both USD = $38 | J7: 10"×10" USD should be lower than $38 (same as 12"×12") | K7: 10"×10" ≈ ₹1,500 / 92.4 × 1.75 ≈ $28 | L7: Confirm base price matches 12"×12" size. Fix USD for 10"×10" size variant. Check if $38 is correct for 12"×12" (₹2,000 / 92.4 × 1.75 = $38 ✓). | M7: REVIEW | N7: Sanjay | O7: NO
A8: REC-007 | B8: Size Price Review | C8: MEDIUM | D8: DB_Artwork_Sizes_Export | E8: art-1771033398626 | G8: Teal & Blue Boho Decorative Round | H8: price_inr / size variants | I8: Base: ₹1,000 | Size rows: 6" set of 2 = ₹1,000, 6" with resin set of 2 = ₹1,500 | Both USD = $19 | J8: Resin variant USD should be higher | K8: With resin variant ≈ ₹1,500 / 92.4 × 1.75 ≈ $28 | L8: Update USD price for resin size variant. Also verify whether base price ($1,000) correctly represents the plain variant or should reflect minimum. | M8: REVIEW | N8: Sanjay | O8: NO
A9: REC-008 | B9: Size Price Review | C9: MEDIUM | D9: DB_Artwork_Sizes_Export | E9: art-1771102688340 | G9: Small decorative Rounds (set of 5) | H9: price_inr / base vs size | I9: Base price: ₹1,200 | Size row: 6" set of 5 = ₹1,500 | J9: Base price (₹1,200) does not match the only size row (₹1,500) | K9: Base price should match or be explained relative to size row | L9: Clarify which price is correct. If ₹1,500 is current price, update base price_inr to ₹1,500. | M9: REVIEW | N9: Sanjay | O9: NO
A10: REC-009 | B10: Size Price Review | C10: MEDIUM | D10: DB_Artwork_Sizes_Export | E10: art-1771454920479 | G10: Canvas Bag - Flowers | H10: price_inr / size variants | I10: Base: ₹1,000 | Size rows: 12"×11" = ₹1,000, 14"×15" = ₹1,800 | Both USD = $19 | J10: 14"×15" USD should be higher than $19 | K10: 14"×15" ≈ ₹1,800 / 92.4 × 1.75 ≈ $34 | L10: Update USD price for 14"×15" size variant. Confirm base price matches 12"×11". | M10: REVIEW | N10: Sanjay | O10: NO
A11: REC-010 | B11: Size Price Review | C11: MEDIUM | D11: DB_Artwork_Sizes_Export | E11: art-1771902788998 | G11: Hand Painted Wooden Mandala Tray (fillable Round) | H11: price_inr / base vs size | I11: Base: ₹1,100 | Size rows: 4.5" ₹500, 6" ₹700, 8" ₹900, 10" ₹1,100 | All USD = $21 | J11: Base (₹1,100) matches 10" size. USD should scale per size. | K11: 4.5" ≈ $9 | 6" ≈ $13 | 8" ≈ $17 | 10" ≈ $21 | L11: Confirm base price correctly represents 10" size. Fix USD pricing for all 4 size variants — currently all frozen at $21. | M11: REVIEW | N11: Sanjay | O11: NO
A12: REC-011 | B12: Size Price Review | C12: MEDIUM | D12: DB_Artwork_Sizes_Export | E12: art-1770779054676 | G12: Floral Rectangular Wooden Storage Box | H12: price_inr / size variants | I12: Base: ₹1,500 | Size rows: 12"×5"×3" = ₹1,500, 9"×9"×4" = ₹1,800 | Both USD = $28 | J12: Second size USD should be higher | K12: 9"×9"×4" ≈ ₹1,800 / 92.4 × 1.75 ≈ $34 | L12: Update USD price for 9"×9"×4" size variant. | M12: REVIEW | N12: Sanjay | O12: NO
A13: REC-012 | B13: Duplicate Title | C13: HIGH | D13: DB_Artworks_Export | E13: art-1771102194181 | G13: Coaster Set (4 pieces) | H13: title | I13: Coaster Set (4 pieces) — art-1771102194181 | J13: art-1770778509370 also titled 'Coaster Set (4 pieces)' | K13: Unique title per artwork | L13: Differentiate titles. Suggest renaming art-1771102194181 to 'Dot Mandala Coaster Set (4 pieces) – Variety Pack' or similar. Review descriptions to confirm these are truly different products. | M13: UPDATE | N13: Chitrakala Team | O13: NO | P13: Two separate artworks share identical title; can cause confusion in sync and on website
A14: REC-013 | B14: Duplicate Title | C14: HIGH | D14: DB_Artworks_Export | E14: art-1771102482592 | G14: Decorative Wall Panel | H14: title | I14: Decorative Wall Panel — art-1771102482592 (Lippan, ₹3,000) | J14: art-1771102578812 also titled 'Decorative Wall Panel' (Lippan, ₹1,800) | K14: Unique title per artwork | L14: Differentiate titles for the two Lippan 'Decorative Wall Panel' artworks. Suggest e.g. 'Lippan Decorative Wall Panel – Large' vs 'Lippan Decorative Wall Panel – Small'. | M14: UPDATE | N14: Chitrakala Team | O14: NO | P14: Two separate Lippan artworks share identical title — different prices (₹3,000 vs ₹1,800) and different materials
A15: REC-014 | B15: Proposed Update | C15: LOW | D15: Inventory_Master | E15: art-1770775579766 | G15: Intricate Floral Mandala Art in Green & Gold | H15: materials | I15: wood | J15: Wood | K15: Wood | L15: Capitalize 'wood' to 'Wood' for consistency with all other artworks. Update Corrected_materials field. | M15: UPDATE | N15: Intern | O15: NO
A16: REC-015 | B16: Proposed Update | C16: LOW | D16: Inventory_Master | E16: art-1771903835260 | G16: Wooden Coaster Set | H16: materials | I16: wood | J16: Wood | K16: Wood | L16: Capitalize 'wood' to 'Wood' for consistency with all other artworks. | M16: UPDATE | N16: Intern | O16: NO
A17: REC-016 | B17: Proposed Update | C17: LOW | D17: Inventory_Master | E17: art-1771904016600 | G17: Heart Shaped Wooden Coaster Set | H17: materials | I17: wood | J17: Wood | K17: Wood | L17: Capitalize 'wood' to 'Wood' for consistency with all other artworks. | M17: UPDATE | N17: Intern | O17: NO
A18: REC-017 | B18: Proposed Update | C18: MEDIUM | D18: DB_Artworks_Export | E18: art-1771030980031 | G18: Midnight Plum Hand-Painted Floral Saree | H18: materials | I18: Pure Wrinkle Cr | J18: Pure Wrinkle Crepe (or confirm full material name) | K18: Full material name | L18: Materials field appears truncated at 'Pure Wrinkle Cr'. Confirm full fabric name (likely 'Pure Wrinkle Crepe') and update Corrected_materials. | M18: UPDATE | N18: Chitrakala Team | O18: NO | P18: Appears to be a data truncation from DB
A19: REC-018 | B19: Proposed Update | C19: LOW | D19: Inventory_Master | E19: art-1770419392051 | G19: Blush Serenity Mandala – Art in Soft Pink & White | H19: featured | I19: f (false) | J19: Review — no featured artworks in dot-mandala besides art-1770775579766 | K19: Confirm intentional | L19: Only one dot-mandala artwork (Intricate Floral Mandala in Green & Gold) is featured. Confirm whether 'Blush Serenity Mandala' should be featured. | M19: REVIEW | N19: Sanjay | O19: NO | P19: Featured=false for this well-described, complete artwork — confirm intentional
A20: REC-019 | B20: Proposed Update | C20: MEDIUM | D20: DB_Artworks_Export | E20: art-1770419460850 | G20: Mandala in Blue and Peach | H20: description | I20: Description ends with: '18" - Rs 6200 24" Rs 8000 36" Rs 16000' | J20: Remove pricing from description; pricing should live in size rows only | K20: Clean product description without embedded pricing | L20: Remove price list from end of description. Add missing size rows (18", 24", 36") to DB_Artwork_Sizes_Export instead. Update Corrected_description. | M20: UPDATE | N20: Intern | O20: NO | P20: Pricing in description is a data quality issue — should be managed via size variants
A21: REC-020 | B21: Proposed Update | C21: MEDIUM | D21: DB_Artworks_Export | E21: art-1771102578812 | G21: Decorative Wall Panel (Lippan, ₹1,800) | H21: materials | I21: Wood | J21: Wood, Clay and Mirrors | K21: Wood, Clay and Mirrors (consistent with other Lippan artworks) | L21: This Lippan artwork lists only 'Wood' as material while all other Lippan artworks use 'Wood, Clay and Mirrors'. The description says 'clay, colors and mirrors'. Update Corrected_materials to 'Wood, Clay and Mirrors'. | M21: UPDATE | N21: Intern | O21: NO | P21: Likely data entry omission; description confirms clay and mirrors are used
A22: REC-021 | B22: Size Price Review | C22: MEDIUM | D22: DB_Artwork_Sizes_Export | E22: art-1770777152872 | G22: Sacred Geometry in Clay & Mirror | H22: price_usd (size rows) | I22: 18"×18" ₹8,000 = $152 | 24"×24" ₹12,000 = $152 | J22: 24"×24" USD should be higher than 18"×18" | K22: 24"×24" ≈ ₹12,000 / 92.4 × 1.75 ≈ $227 | L22: Update USD price for 24"×24" size row. Applies similarly to Luxury Lippan Art Wall Panel and Peach & Ivory Mirror Work Mandala which have the same issue. | M22: REVIEW | N22: Sanjay | O22: NO | P22: Systemic USD freeze issue across Lippan panel artworks with 2 sizes
A23: REC-022 | B23: Size Price Review | C23: MEDIUM | D23: DB_Artwork_Sizes_Export | E23: art-1771101879286 | G23: Decorative Serving Board | H23: price_usd (all 6 size rows) | I23: 6 sizes: ₹800–₹2,100 INR | All show price_usd = $15 | J23: USD should scale with INR price per size | K23: 9" single ≈$15 | 10" single ≈$17 | 15" single ≈$24 | 9" ×2 ≈$28 | 10" ×2 ≈$30 | 15" ×2 ≈$40 | L23: Fix USD pricing for all 6 size rows. This is the most extreme example of the systemic USD freeze issue. | M23: REVIEW | N23: Sanjay | O23: NO | P23: All 6 sizes show $15 USD regardless of INR price ranging from ₹800 to ₹2,100
A24: REC-023 | B24: Size Price Review | C24: MEDIUM | D24: DB_Artwork_Sizes_Export | E24: art-1771903526915 | G24: Handcrafted Mud & Mirror Floral Mandala | H24: price_usd (size rows) | I24: 3 sizes: ₹1,600, ₹2,000, ₹2,800 | All USD = $53 | J24: USD should scale with INR price per size | K24: 8" ≈$30 | 10" ≈$38 | 12"×14" ≈$53 | L24: Fix USD pricing for the 8" and 10" size variants. $53 is only correct for the 12"×14" size. | M24: REVIEW | N24: Sanjay | O24: NO
A25: REC-024 | B25: Size Price Review | C25: HIGH | D25: Potential_Issues_Auto | E25: art-1770419263598 art-1770419460850 art-1770771760544 art-1770771970545 art-1770775579766 art-1770777152872 art-1770778384172 art-1770778509370 art-1770779054676 art-1770779208267 art-1770933508740 art-1771030266195 art-1771030980031 art-1771031213758 art-1771033398626 art-1771101879286 art-1771101978525 art-1771102194181 art-1771102482592 art-1771102578812 art-1771102688340 art-1771454920479 art-1771902788998 art-1771903158477 art-1771903526915 art-1771903835260 art-1771904016600 art-1772897507182 art-1772899719136 art-1772942427729 art-1772991773037 art-1778384480649 art-1778384550442 | G25: ALL artworks with size variants (33 of 36 artworks; 73 size rows total) | H25: price_usd across all size rows | I25: price_usd in DB_Artwork_Sizes_Export is frozen at the artwork-level base USD price for virtually all size variants | J25: Each size row should have USD = round(INR_price / fx_rate × multiplier, 2) | K25: Dynamic USD per size variant | L25: This is a systemic bug/gap. Recommend coding agent recalculate USD for all size rows using: price_usd = price_inr / fx_rate_used * multiplier_used (from DB_Artworks_Export). Do not manually fix 70+ rows; request automated fix. | M25: REVIEW | N25: Coding Agent | O25: NO | P25: Root cause: price_usd in DB_Artwork_Sizes_Export was not recalculated per size when size rows were created/updated — it inherited the artwork-level base USD. Affects all 33 artworks listed in Artwork ID column (73 size rows). Coding agent fix: UPDATE artwork_sizes s JOIN artworks a ON s.artwork_id = a.id SET s.price_usd = ROUND(s.price / a.fx_rate_used * a.multiplier_used, 2) WHERE s.price_usd != ROUND(s.price / a.fx_rate_used * a.multiplier_used, 2);
A26: =IF(B26<>"","REC-"&TEXT(ROW()-1,"000"),"")
A27: =IF(B27<>"","REC-"&TEXT(ROW()-1,"000"),"")
A28: =IF(B28<>"","REC-"&TEXT(ROW()-1,"000"),"")
A29: =IF(B29<>"","REC-"&TEXT(ROW()-1,"000"),"")
A30: =IF(B30<>"","REC-"&TEXT(ROW()-1,"000"),"")
A31: =IF(B31<>"","REC-"&TEXT(ROW()-1,"000"),"")
A32: =IF(B32<>"","REC-"&TEXT(ROW()-1,"000"),"")
A33: =IF(B33<>"","REC-"&TEXT(ROW()-1,"000"),"")
A34: =IF(B34<>"","REC-"&TEXT(ROW()-1,"000"),"")
A35: =IF(B35<>"","REC-"&TEXT(ROW()-1,"000"),"")
A36: =IF(B36<>"","REC-"&TEXT(ROW()-1,"000"),"")
A37: =IF(B37<>"","REC-"&TEXT(ROW()-1,"000"),"")
... A500: =IF(B500<>"","REC-"&TEXT(ROW()-1,"000"),"")

Sheet Import_Validation_Rules
A1: Rule ID | B1: Workbook Tab | C1: Spreadsheet Column | D1: Source/DB Column | E1: Required? | F1: Manual or Formula? | G1: Data Type | H1: Allowed Values | I1: Validation Rule | J1: Error Message | K1: Severity | L1: Example Valid | M1: Example Invalid
A2: VAL-001 | B2: DB_Artworks_Export | C2: id | D2: export column 1 | E2: Yes | F2: Raw export | G2: Text | H2: Non-empty | I2: Must remain first column in DB_Artworks_Export. | J2: Missing artwork id. | K2: HIGH | L2: art-1770419263598 | M2: blank
A3: VAL-002 | B3: DB_Artworks_Export | C3: title | D3: export column 2 | E3: Yes | F3: Raw export | G3: Text | H3: Non-empty | I3: Artwork title should not be blank. | J3: Missing title. | K3: HIGH | L3: Eternal Glow | M3: blank
A4: VAL-003 | B4: DB_Artworks_Export | C4: category_slug | D4: export column 3 | E4: Yes | F4: Raw export | G4: Text | H4: Must match DB_Categories_Export.id | I4: Category slug must exist in categories export. | J4: Invalid category slug. | K4: HIGH | L4: dot-mandala | M4: textile
A5: VAL-004 | B5: DB_Artworks_Export | C5: category_name | D5: export column 4 | E5: Reference | F5: Raw export | G5: Text | H5: Category display name | I5: Category name is reference/display only, not key. | J5: Use category_slug as key. | K5: LOW | L5: Dot Mandala Art
A6: VAL-005 | B6: DB_Artworks_Export | C6: description | D6: export column 5 | E6: Recommended | F6: Raw export | G6: Text | H6: Any text | I6: Description should be reviewed for completeness. | J6: Description may be missing. | K6: MEDIUM | L6: Full description | M6: blank
A7: VAL-006 | B7: DB_Artworks_Export | C7: materials | D7: export column 6 | E7: Recommended | F7: Raw export | G7: Text | H7: Any text | I7: Materials should be reviewed for completeness. | J7: Materials may be missing. | K7: MEDIUM | L7: Wood | M7: blank
A8: VAL-007 | B8: DB_Artworks_Export | C8: price_inr | D8: export column 7 | E8: Yes | F8: Raw export / final formula | G8: Number | H8: >=0 | I8: INR price is master price and should be numeric. | J8: Invalid INR price. | K8: HIGH | L8: 4000.00 | M8: text
A9: VAL-008 | B9: DB_Artworks_Export | C9: price_usd | D9: export column 8 | E9: Reference | F9: Formula/system | G9: Number | H9: System-calculated | I9: USD price should not be manually corrected in spreadsheet. | J9: Do not manually import USD price. | K9: HIGH | L9: 76.00 | M9: manual override
A10: VAL-009 | B10: DB_Artworks_Export | C10: fx_rate_used | D10: export column 9 | E10: Reference | F10: System | G10: Number | H10: System-controlled | I10: FX rate is reference only. | J10: Do not manually import FX rate. | K10: HIGH | L10: 92.4000 | M10: manual override
A11: VAL-010 | B11: DB_Artworks_Export | C11: multiplier_used | D11: export column 10 | E11: Reference | F11: System | G11: Number | H11: System-controlled | I11: Multiplier is reference only. | J11: Do not manually import multiplier. | K11: HIGH | L11: 1.7500 | M11: manual override
A12: VAL-011 | B12: DB_Artworks_Export | C12: featured | D12: export column 11 | E12: No | F12: Raw export / corrected manual | G12: Boolean | H12: TRUE/FALSE | I12: Featured must be TRUE or FALSE if corrected. | J12: Invalid featured value. | K12: MEDIUM | L12: TRUE | M12: yes
A13: VAL-012 | B13: DB_Artworks_Export | C13: image | D13: export column 12 | E13: Recommended | F13: Raw export / corrected manual | G13: Text | H13: Path/URL | I13: Image path should be reviewed but not auto-replaced in Phase 1. | J13: Missing image. | K13: MEDIUM | L13: /uploads/file.jpg | M13: blank
A14: VAL-013 | B14: DB_Artworks_Export | C14: created_at | D14: export column 13 | E14: Reference | F14: System | G14: Timestamp | H14: System-generated | I14: Do not import/edit created_at. | J14: created_at is system-controlled. | K14: MEDIUM | L14: 2026-03-17 03:31 | M14: manual
A15: VAL-014 | B15: DB_Artworks_Export | C15: updated_at | D15: export column 14 | E15: Reference | F15: System | G15: Timestamp | H15: System-generated | I15: Do not import/edit updated_at. | J15: updated_at is system-controlled. | K15: MEDIUM | L15: 2026-03-17 03:31 | M15: manual
A16: VAL-015 | B16: DB_Artwork_Sizes_Export | C16: artwork_id | D16: export column 2 | E16: Yes for sizes | F16: Raw export | G16: Text | H16: Must match DB_Artworks_Export.id | I16: Size row must link to valid artwork id. | J16: Invalid artwork_id. | K16: HIGH | L16: art-1770419263598 | M16: unknown id
A17: VAL-016 | B17: DB_Artwork_Sizes_Export | C17: size_label | D17: export column 4 | E17: Yes for sizes | F17: Raw export | G17: Text | H17: Non-empty | I17: Size label required when size row exists. | J17: Missing size label. | K17: HIGH | L17: 12 x 12 | M17: blank
... A24: VAL-023 | B24: Inventory_Master | C24: Final_* fields | D24: formula | E24: Yes | F24: Formula | G24: Mixed | H24: Uses corrected if present, else DB | I24: Final fields are calculated for future sync preview. | J24: Do not manually edit final fields. | K24: HIGH | L24: Formula output | M24: manual value

Sheet DB_to_Inventory_Field_Mapping
A1: Source Tab | B1: Source Column Order | C1: Source Column | D1: Inventory_Master Column | E1: Auto/Manual | F1: Rule / Notes
A2: DB_Artworks_Export | B2: 1 | C2: id | D2: DB id | E2: Auto formula | F2: Exact uploaded export column order preserved.
A3: DB_Artworks_Export | B3: 2 | C3: title | D3: DB title | E3: Auto formula | F3: Exact uploaded export column order preserved.
A4: DB_Artworks_Export | B4: 3 | C4: category_slug | D4: DB category_slug | E4: Auto formula | F4: Exact uploaded export column order preserved.
A5: DB_Artworks_Export | B5: 4 | C5: category_name | D5: DB category_name | E5: Auto formula | F5: Exact uploaded export column order preserved.
A6: DB_Artworks_Export | B6: 5 | C6: description | D6: DB description | E6: Auto formula | F6: Exact uploaded export column order preserved.
A7: DB_Artworks_Export | B7: 6 | C7: materials | D7: DB materials | E7: Auto formula | F7: Exact uploaded export column order preserved.
A8: DB_Artworks_Export | B8: 7 | C8: price_inr | D8: DB price_inr | E8: Auto formula | F8: Exact uploaded export column order preserved.
A9: DB_Artworks_Export | B9: 8 | C9: price_usd | D9: DB price_usd | E9: Auto formula | F9: Exact uploaded export column order preserved.
A10: DB_Artworks_Export | B10: 9 | C10: fx_rate_used | D10: DB fx_rate_used | E10: Auto formula | F10: Exact uploaded export column order preserved.
A11: DB_Artworks_Export | B11: 10 | C11: multiplier_used | D11: DB multiplier_used | E11: Auto formula | F11: Exact uploaded export column order preserved.
A12: DB_Artworks_Export | B12: 11 | C12: featured | D12: DB featured | E12: Auto formula | F12: Exact uploaded export column order preserved.
A13: DB_Artworks_Export | B13: 12 | C13: image | D13: DB image | E13: Auto formula | F13: Exact uploaded export column order preserved.
... A27: DB_Categories_Export | B27: 5 | C27: display_order | D27: Reference only | E27: Auto formula/reference | F27: Exact uploaded export column order preserved.
A28: Inventory_Master | C28: Sync Action | D28: Sync Action | E28: Manual | F28: Intern selects final planned action.
A29: Inventory_Master | C29: Inventory SKU | D29: Inventory SKU | E29: Manual | F29: Optional internal SKU.
A30: Inventory_Master | C30: Corrected title | D30: Corrected title | E30: Manual | F30: Fill only if title should change.
A31: Inventory_Master | C31: Corrected category_slug | D31: Corrected category_slug | E31: Manual | F31: Fill only if category should change.
A32: Inventory_Master | C32: Corrected description | D32: Corrected description | E32: Manual | F32: Fill only if description should change.
A33: Inventory_Master | C33: Corrected materials | D33: Corrected materials | E33: Manual | F33: Fill only if materials should change.
A34: Inventory_Master | C34: Corrected price_inr | D34: Corrected price_inr | E34: Manual | F34: Fill only if INR price should change.
A35: Inventory_Master | C35: Corrected featured | D35: Corrected featured | E35: Manual | F35: Fill only if featured flag should change.
A36: Inventory_Master | C36: Corrected image | D36: Corrected image | E36: Manual | F36: Review only; do not automate image replacement in Phase 1.
